Workbook

Sheet HCO_Data
A1: HCO Class | C1: HCO Information | I1: HCO Details | S1: HCO Claims | W1: Clinical Trials | AC1: Associations
C2: HCO Comments | D2: Expert Centre | E2: Pancreatic (Cancer) Center | F2: HCP count | G2: Testing check | H2: Referral check | I2: Finessgeo | J2: VeevaID | K2: GDS_HCO_ID | L2: HCO name | M2: Address | N2: Zipcode | O2: City | P2: Region | Q2: Country | S2: C25 | T2: C25 Helper Column | U2: CCAM HNFA0070 | V2: 80% hospital | W2: Unique Clinical Trials | X2: PDAC OR Pancreatic Adenocarcinoma | Y2: KRAS mutation | Z2: Pancreatic cancer | AA2: Unresectable | AB2: Metastatic | AC2: BACAP | AD2: Unicancer Network | AE2: OECI Member | AF2: INCa : Chemotherapy or other cancer specific medical treatments | AG2: INCa : Cancer Surgery: digestive
A3: filter | C3: filter | D3: filter | E3: filter | J3: filter | K3: filter | L3: filter | M3: filter | N3: filter | O3: filter | P3: filter | Q3: filter | R3: Number | S3: filter | U3: filter | W3: filter | X3: filter | Y3: filter | Z3: filter | AA3: filter | AB3: filter | AC3: filter | AD3: filter | AE3: filter | AF3: filter | AG3: filter
B4: 49 | C4: IPC provides multidisciplinary pancreatic cancer care including surgery, systemic therapy and pancreatic-specific research. | D4: Unicancer | F4: =COUNTIF(HCPs!W:W,HCO_Data!K4) -> 25 | G4: =IF(COUNTIF('Testing Referrals'!B:B,HCO_Data!K4)>0,"Yes","") -> Yes | H4: =COUNTIF('HCO referrals'!B:B,HCO_Data!K4)+COUNTIF('HCO referrals'!C:C,HCO_Data!K4) -> 0 | I4: 130001647 | K4: ID00011 | L4: Institut Paoli-Calmettes | M4: 232 Boulevard de Sainte-Marguerite | N4: 13009 | O4: Marseille | P4: Provence-Alpes-Côte d’Azur | Q4: France | R4: 2 | S4: 539 | T4: 539 | V4: Yes | W4: =COUNTIFS('Clinical Trials HCO'!$A:$A, K4, 'Clinical Trials HCO'!$D:$D, "<>") -> 60 | AE4: Certified Comprehensive Cancer Centre
B5: 273 | C5: Beaujon has site-level evidence for pancreatic oncology/pancreatology, pancreatic surgery, EUS/CPRE and rapid pancreatic diagnosis. These activities are organised across dedicated pancreatic, HPB surgical and digestive endoscopy services. | F5: =COUNTIF(HCPs!W:W,HCO_Data!K5) -> 18 | G5: =IF(COUNTIF('Testing Referrals'!B:B,HCO_Data!K5)>0,"Yes","") -> Yes | H5: =COUNTIF('HCO referrals'!B:B,HCO_Data!K5)+COUNTIF('HCO referrals'!C:C,HCO_Data!K5) -> 1 | I5: 920100039 | K5: ID00001 | L5: Hôpital Beaujon | M5: 100 BOULEVARD DU GÉNÉRAL LECLERC | N5: 92118 | O5: CLICHY | Q5: France | R5: 1 | S5: 537 | T5: 537 | V5: Yes | W5: =COUNTIFS('Clinical Trials HCO'!$A:$A, K5, 'Clinical Trials HCO'!$D:$D, "<>") -> 50 | AE5: Certified Comprehensive Cancer Centre
B6: 661 | F6: =COUNTIF(HCPs!W:W,HCO_Data!K6) -> 4 | G6: =IF(COUNTIF('Testing Referrals'!B:B,HCO_Data!K6)>0,"Yes","") -> Yes | H6: =COUNTIF('HCO referrals'!B:B,HCO_Data!K6)+COUNTIF('HCO referrals'!C:C,HCO_Data!K6) -> 0 | I6: 330783648 | K6: ID00031 | L6: Hôpital Haut-Lévêque | M6: AVENUE DE MAGELLAN | N6: 33604 | O6: PESSAC | Q6: France | R6: 3 | S6: 493 | T6: 493 | V6: Yes | W6: =COUNTIFS('Clinical Trials HCO'!$A:$A, K6, 'Clinical Trials HCO'!$D:$D, "<>") -> 23 | AC6: Yes | AG6: Yes
B7: 572 | C7: Jean Mermoz is a genuine comprehensive pancreatic centre rather than merely a diagnostic or surgical provider. Diagnosis/EUS-biopsy, advanced biliopancreatic endoscopy, pancreatic oncology, pancreatic research and high-volume pancreatic surgery are all documented locally. | F7: =COUNTIF(HCPs!W:W,HCO_Data!K7) -> 13 | G7: =IF(COUNTIF('Testing Referrals'!B:B,HCO_Data!K7)>0,"Yes","") | H7: =COUNTIF('HCO referrals'!B:B,HCO_Data!K7)+COUNTIF('HCO referrals'!C:C,HCO_Data!K7) -> 0 | I7: 690023411 | K7: ID00015 | L7: Hôpital Privé Jean Mermoz | M7: 55 AVENUE JEAN MERMOZ | N7: 69008 | O7: LYON | Q7: France | R7: 6 | S7: 384 | T7: 384 | V7: Yes | W7: =COUNTIFS('Clinical Trials HCO'!$A:$A, K7, 'Clinical Trials HCO'!$D:$D, "<>") -> 25 | AC7: Yes | AG7: Yes
B8: 46 | C8: Gustave Roussy provides pancreatic cancer diagnosis, systemic therapy, oncological surgery, EUS and weekly multidisciplinary review at Villejuif. The InstaDiag Pancreas pathway directly integrates radiology, oncology and surgery. | D8: Unicancer | F8: =COUNTIF(HCPs!W:W,HCO_Data!K8) -> 13 | G8: =IF(COUNTIF('Testing Referrals'!B:B,HCO_Data!K8)>0,"Yes","") -> Yes | H8: =COUNTIF('HCO referrals'!B:B,HCO_Data!K8)+COUNTIF('HCO referrals'!C:C,HCO_Data!K8) -> 3 | I8: 940000664 | K8: ID00007 | L8: Institut Gustave Roussy | M8: 114 Rue Edouard Vaillant | N8: 94805 | O8: Villejuif | P8: Ile-de-France | Q8: France | R8: 0 | S8: 364 | T8: 364 | V8: Yes | W8: =COUNTIFS('Clinical Trials HCO'!$A:$A, K8, 'Clinical Trials HCO'!$D:$D, "<>") -> 92 | AF8: Yes | AG8: Yes
B9: 282 | C9: The leading center for the treatment of pancreatic cancer in Montpellier | D9: Unicancer | F9: =COUNTIF(HCPs!W:W,HCO_Data!K9) -> 12 | G9: =IF(COUNTIF('Testing Referrals'!B:B,HCO_Data!K9)>0,"Yes","") -> Yes | H9: =COUNTIF('HCO referrals'!B:B,HCO_Data!K9)+COUNTIF('HCO referrals'!C:C,HCO_Data!K9) -> 2 | I9: 340000207 | K9: ID00026 | L9: ICM Montpellier | M9: 208 RUE DES APOTHICAIRES | N9: 34298 | O9: MONTPELLIER | Q9: France | R9: 5 | S9: 309 | T9: 309 | V9: Yes | W9: =COUNTIFS('Clinical Trials HCO'!$A:$A, K9, 'Clinical Trials HCO'!$D:$D, "<>") -> 42 | AC9: Yes
B10: 243 | F10: =COUNTIF(HCPs!W:W,HCO_Data!K10) -> 14 | G10: =IF(COUNTIF('Testing Referrals'!B:B,HCO_Data!K10)>0,"Yes","") | H10: =COUNTIF('HCO referrals'!B:B,HCO_Data!K10)+COUNTIF('HCO referrals'!C:C,HCO_Data!K10) -> 2 | I10: 310783055 | K10: ID00018 | L10: Hôpital de Rangueil | M10: 1 AVENUE PR JEAN POULHES | N10: 31059 | O10: TOULOUSE | Q10: France | R10: 17 | S10: 299 | T10: 299 | V10: Yes | W10: =COUNTIFS('Clinical Trials HCO'!$A:$A, K10, 'Clinical Trials HCO'!$D:$D, "<>") -> 18 | AC10: Yes
B11: 519 | C11: Dedicated HPB surgery service states that it treats pancreatic disease surgically and explicitly describes pancreatectomy. | F11: =COUNTIF(HCPs!W:W,HCO_Data!K11) -> 4 | G11: =IF(COUNTIF('Testing Referrals'!B:B,HCO_Data!K11)>0,"Yes","") -> Yes | H11: =COUNTIF('HCO referrals'!B:B,HCO_Data!K11)+COUNTIF('HCO referrals'!C:C,HCO_Data!K11) -> 4 | I11: 250006954 | K11: ID00051 | L11: CHRU Jean Minjoz | M11: 3 BOULEVARD FLEMING | N11: 25030 | O11: BESANCON | Q11: France | R11: 13 | S11: 286 | T11: 286 | V11: Yes | W11: =COUNTIFS('Clinical Trials HCO'!$A:$A, K11, 'Clinical Trials HCO'!$D:$D, "<>") -> 23 | AG11: Yes
B12: 509 | C12: Huriez has medical oncology, pancreatic surgery, pancreatic disease/endoscopy, RCP, trials and translational research. The ARS specifically authorises the CHU Lille site for complex digestive oncological surgery including the pancreas. | F12: =COUNTIF(HCPs!W:W,HCO_Data!K12) -> 7 | G12: =IF(COUNTIF('Testing Referrals'!B:B,HCO_Data!K12)>0,"Yes","") | H12: =COUNTIF('HCO referrals'!B:B,HCO_Data!K12)+COUNTIF('HCO referrals'!C:C,HCO_Data!K12) -> 2 | I12: 590811279 | K12: ID00012 | L12: Hôpital Claude Huriez | M12: RUE MICHEL POLONOWSKI | N12: 59037 | Q12: France | R12: 28 | S12: 278 | T12: 278 | V12: Yes | W12: =COUNTIFS('Clinical Trials HCO'!$A:$A, K12, 'Clinical Trials HCO'!$D:$D, "<>") -> 20 | AC12: Yes | AF12: Yes
B13: 269 | C13: Saint-Antoine has explicit pancreatic cancer surgery through a named HPB team and integrated medical oncology/digestive care. | F13: =COUNTIF(HCPs!W:W,HCO_Data!K13) -> 4 | G13: =IF(COUNTIF('Testing Referrals'!B:B,HCO_Data!K13)>0,"Yes","") -> Yes | H13: =COUNTIF('HCO referrals'!B:B,HCO_Data!K13)+COUNTIF('HCO referrals'!C:C,HCO_Data!K13) -> 2 | I13: 750100091 | K13: ID00066 | L13: Hôpital Saint-Antoine | M13: 184 RUE DU FAUBOURG SAINT ANTOINE | N13: 75571 | O13: PARIS | Q13: France | R13: 22 | S13: 253 | T13: 253 | V13: Yes | W13: =COUNTIFS('Clinical Trials HCO'!$A:$A, K13, 'Clinical Trials HCO'!$D:$D, "<>") -> 0 | AF13: Yes | AG13: Yes
B14: 279 | C14: Paul-Brousse combines a pancreatic/HPB surgical pathway in the Centre Hépato-Biliaire with a medical oncology service explicitly treating malignant pancreatic tumours. The site also conducts pancreatic systemic-treatment research. | F14: =COUNTIF(HCPs!W:W,HCO_Data!K14) -> 7 | G14: =IF(COUNTIF('Testing Referrals'!B:B,HCO_Data!K14)>0,"Yes","") | H14: =COUNTIF('HCO referrals'!B:B,HCO_Data!K14)+COUNTIF('HCO referrals'!C:C,HCO_Data!K14) -> 1 | I14: 940100068 | K14: ID00008 | L14: Hôpital Paul Brousse | M14: 12 AVENUE PAUL VAILLANT COUTURIER | N14: 94804 | O14: VILLEJUIF | Q14: France | R14: 15 | S14: 251 | T14: 251 | V14: Yes | W14: =COUNTIFS('Clinical Trials HCO'!$A:$A, K14, 'Clinical Trials HCO'!$D:$D, "<>") -> 18 | AF14: Yes | AG14: Yes
B15: 701 | C15: CHU Reims explicitly treats pancreatic cancers, performs biliary/pancreatic ERCP, chemotherapy and endoscopy, and in 2026 launched a dedicated “Urgence tumeur pancréas” pathway for suspected pancreatic lesions with rapid access to diagnosis and treatment. | F15: =COUNTIF(HCPs!W:W,HCO_Data!K15) -> 7 | G15: =IF(COUNTIF('Testing Referrals'!B:B,HCO_Data!K15)>0,"Yes","") -> Yes | H15: =COUNTIF('HCO referrals'!B:B,HCO_Data!K15)+COUNTIF('HCO referrals'!C:C,HCO_Data!K15) -> 2 | I15: 510002447 | K15: ID00014 | L15: Hôpital Robert Debré | M15: RUE DU GENERAL KOENIG | N15: 51092 | O15: REIMS | Q15: France | R15: 9 | S15: 247 | T15: 247 | V15: Yes | W15: =COUNTIFS('Clinical Trials HCO'!$A:$A, K15, 'Clinical Trials HCO'!$D:$D, "<>") -> 32 | AG15: Yes
B16: 715 | F16: =COUNTIF(HCPs!W:W,HCO_Data!K16) -> 5 | G16: =IF(COUNTIF('Testing Referrals'!B:B,HCO_Data!K16)>0,"Yes","") | H16: =COUNTIF('HCO referrals'!B:B,HCO_Data!K16)+COUNTIF('HCO referrals'!C:C,HCO_Data!K16) -> 0 | I16: 540002698 | K16: ID00084 | L16: Hôpitaux de Brabois | M16: RUE DU MORVAN | N16: 54511 | O16: VANDOEUVRE LES NANCY | Q16: France | R16: 104 | S16: 240 | T16: 240 | V16: Yes | W16: =COUNTIFS('Clinical Trials HCO'!$A:$A, K16, 'Clinical Trials HCO'!$D:$D, "<>") -> 0 | AF16: Yes | AG16: Yes
B17: 533 | F17: =COUNTIF(HCPs!W:W,HCO_Data!K17) -> 1 | G17: =IF(COUNTIF('Testing Referrals'!B:B,HCO_Data!K17)>0,"Yes","") | H17: =COUNTIF('HCO referrals'!B:B,HCO_Data!K17)+COUNTIF('HCO referrals'!C:C,HCO_Data!K17) -> 0 | I17: 750300360 | J17: 544957847394321411 | K17: ID00153 | L17: HOPITAL PRIVE DES PEUPLIERS | M17: 8 PLACE ABBE GEORGES HENOCQUE | N17: 75013 | O17: PARIS | Q17: France | R17: 168 | S17: 235 | T17: 235 | V17: Yes | W17: =COUNTIFS('Clinical Trials HCO'!$A:$A, K17, 'Clinical Trials HCO'!$D:$D, "<>") -> 0 | AF17: Yes | AG17: Yes
B18: 44 | D18: Unicancer | F18: =COUNTIF(HCPs!W:W,HCO_Data!K18) -> 11 | G18: =IF(COUNTIF('Testing Referrals'!B:B,HCO_Data!K18)>0,"Yes","") -> Yes | H18: =COUNTIF('HCO referrals'!B:B,HCO_Data!K18)+COUNTIF('HCO referrals'!C:C,HCO_Data!K18) -> 3 | I18: 690000880 | K18: ID00029 | L18: Centre Léon Bérard | M18: 28 Prom. Léa et Napoléon Bullukian | N18: 69008 | O18: Lyon | P18: Auvergne-Rhône-Alpes | Q18: France | R18: 7 | S18: 232 | T18: 232 | V18: Yes | W18: =COUNTIFS('Clinical Trials HCO'!$A:$A, K18, 'Clinical Trials HCO'!$D:$D, "<>") -> 69 | AC18: Yes | AF18: Yes
B19: 385 | C19: The CHU's current uro-digestive oncology day hospital explicitly lists cancer du pancréas among the cancers managed, administers chemotherapy after RCP discussion, and coordinates surgery/radiotherapy/interventional radiology | F19: =COUNTIF(HCPs!W:W,HCO_Data!K19) -> 3 | G19: =IF(COUNTIF('Testing Referrals'!B:B,HCO_Data!K19)>0,"Yes","") -> Yes | H19: =COUNTIF('HCO referrals'!B:B,HCO_Data!K19)+COUNTIF('HCO referrals'!C:C,HCO_Data!K19) -> 4 | I19: 760000158 | K19: ID00017 | L19: Hôpital Charles Nicolle | M19: 1 RUE DE GERMONT | N19: 76031 | O19: ROUEN | Q19: France | R19: 30 | S19: 230 | T19: 230 | V19: Yes | W19: =COUNTIFS('Clinical Trials HCO'!$A:$A, K19, 'Clinical Trials HCO'!$D:$D, "<>") -> 12
B20: 270 | F20: =COUNTIF(HCPs!W:W,HCO_Data!K20) -> 2 | G20: =IF(COUNTIF('Testing Referrals'!B:B,HCO_Data!K20)>0,"Yes","") -> Yes | H20: =COUNTIF('HCO referrals'!B:B,HCO_Data!K20)+COUNTIF('HCO referrals'!C:C,HCO_Data!K20) -> 1 | I20: 940100027 | K20: ID00065 | L20: Hôpital Henri Mondor | M20: 51 AVENUE MAL DE LATTRE DE TASSIGNY | N20: 94010 | O20: CRETEIL | Q20: France | R20: 164 | S20: 230 | T20: 230 | V20: Yes | W20: =COUNTIFS('Clinical Trials HCO'!$A:$A, K20, 'Clinical Trials HCO'!$D:$D, "<>") -> 0 | AF20: Yes | AG20: Yes
B21: 218 | F21: =COUNTIF(HCPs!W:W,HCO_Data!K21) -> 2 | G21: =IF(COUNTIF('Testing Referrals'!B:B,HCO_Data!K21)>0,"Yes","") -> Yes | H21: =COUNTIF('HCO referrals'!B:B,HCO_Data!K21)+COUNTIF('HCO referrals'!C:C,HCO_Data!K21) -> 0 | I21: 860000223 | K21: ID00016 | L21: Hôpital de la Milétrie | M21: 2 RUE DE LA MILETRIE | N21: 86021 | O21: POITIERS | Q21: France | R21: 18 | S21: 229 | T21: 229 | V21: Yes | W21: =COUNTIFS('Clinical Trials HCO'!$A:$A, K21, 'Clinical Trials HCO'!$D:$D, "<>") -> 5 | AE21: Certified Comprehensive Cancer Centre
B22: 280 | C22: Hôpital Pitié-Salpêtrière is a major comprehensive pancreatic cancer referral and surgical centre within AP-HP. It operates a dedicated AP-HP-labelled rapid-diagnosis pancreas centre and its HPB surgical service reports more than 80 pancreatectomies for pancreatic cancer. | F22: =COUNTIF(HCPs!W:W,HCO_Data!K22) -> 7 | G22: =IF(COUNTIF('Testing Referrals'!B:B,HCO_Data!K22)>0,"Yes","") -> Yes | H22: =COUNTIF('HCO referrals'!B:B,HCO_Data!K22)+COUNTIF('HCO referrals'!C:C,HCO_Data!K22) -> 11 | I22: 750100125 | K22: ID00005 | L22: HU Pitié-Salpêtrière | M22: 47 BOULEVARD DE L HOPITAL | N22: 75651 | O22: PARIS | Q22: France | R22: 12 | S22: 227 | T22: 227 | V22: Yes | W22: =COUNTIFS('Clinical Trials HCO'!$A:$A, K22, 'Clinical Trials HCO'!$D:$D, "<>") -> 47 | AF22: Yes | AG22: Yes
B23: 656 | C23: Hôpital Saint-Éloi is a major pancreatic cancer centre within CHU de Montpellier, with pancreatic diagnosis, advanced endoscopy, pancreatic surgery and medical oncology all directly documented on the Saint-Éloi site. | F23: =COUNTIF(HCPs!W:W,HCO_Data!K23) -> 8 | G23: =IF(COUNTIF('Testing Referrals'!B:B,HCO_Data!K23)>0,"Yes","") -> Yes | H23: =COUNTIF('HCO referrals'!B:B,HCO_Data!K23)+COUNTIF('HCO referrals'!C:C,HCO_Data!K23) -> 4 | I23: 340782036 | K23: ID00004 | L23: Hôpital Saint-Eloi | M23: 80 AVENUE AUGUSTIN FLICHE | N23: 34295 | O23: MONTPELLIER | Q23: France | R23: 40 | S23: 225 | T23: 225 | V23: Yes | W23: =COUNTIFS('Clinical Trials HCO'!$A:$A, K23, 'Clinical Trials HCO'!$D:$D, "<>") -> 9 | AC23: Yes | AG23: Yes
B24: 219 | C24: The CHU HGE service explicitly manages pancreatic diseases and pancreatic cancer, provides digestive oncology, and is a regional expert centre for diagnostic/therapeutic/interventional echo-endoscopy. Its digestive surgery service explicitly covers pancreatic oncologic surgery. | F24: =COUNTIF(HCPs!W:W,HCO_Data!K24) -> 2 | G24: =IF(COUNTIF('Testing Referrals'!B:B,HCO_Data!K24)>0,"Yes","") -> Yes | H24: =COUNTIF('HCO referrals'!B:B,HCO_Data!K24)+COUNTIF('HCO referrals'!C:C,HCO_Data!K24) -> 2 | I24: 300782117 | K24: ID00073 | L24: CHU Carémeau | M24: PLACE DU PROFESSEUR ROBERT DEBRE | N24: 30029 | O24: NIMES | Q24: France | R24: 23 | S24: 224 | T24: 224 | V24: Yes | W24: =COUNTIFS('Clinical Trials HCO'!$A:$A, K24, 'Clinical Trials HCO'!$D:$D, "<>") -> 3 | AF24: Yes | AG24: Yes
B25: 272 | C25: Cochin has site-level pancreatic surgery, digestive oncology and specialised pancreaticobiliary endoscopy. A dedicated rapid diagnostic pathway links gastroenterology, surgery, pathology and imaging. | F25: =COUNTIF(HCPs!W:W,HCO_Data!K25) -> 11 | G25: =IF(COUNTIF('Testing Referrals'!B:B,HCO_Data!K25)>0,"Yes","") -> Yes | H25: =COUNTIF('HCO referrals'!B:B,HCO_Data!K25)+COUNTIF('HCO referrals'!C:C,HCO_Data!K25) -> 0 | I25: 750100166 | K25: ID00009 | L25: Hôpital Cochin | M25: 27 RUE DU FAUBOURG SAINT JACQUES | N25: 75679 | O25: PARIS | Q25: France | R25: 19 | S25: 221 | T25: 221 | V25: Yes | W25: =COUNTIFS('Clinical Trials HCO'!$A:$A, K25, 'Clinical Trials HCO'!$D:$D, "<>") -> 25 | AF25: Yes | AG25: Yes
B26: 342 | F26: =COUNTIF(HCPs!W:W,HCO_Data!K26) -> 6 | G26: =IF(COUNTIF('Testing Referrals'!B:B,HCO_Data!K26)>0,"Yes","") -> Yes | H26: =COUNTIF('HCO referrals'!B:B,HCO_Data!K26)+COUNTIF('HCO referrals'!C:C,HCO_Data!K26) -> 5 | I26: 630781268 | K26: ID00047 | L26: CHU Estaing | M26: 1 PLACE LUCIE AUBRAC | N26: 63003 | O26: CLERMONT FERRAND | Q26: France | R26: 26 | S26: 219 | T26: 219 | V26: Yes | W26: =COUNTIFS('Clinical Trials HCO'!$A:$A, K26, 'Clinical Trials HCO'!$D:$D, "<>") -> 12 | AF26: Yes | AG26: Yes
B27: 295 | F27: =COUNTIF(HCPs!W:W,HCO_Data!K27) -> 3 | G27: =IF(COUNTIF('Testing Referrals'!B:B,HCO_Data!K27)>0,"Yes","") -> Yes | H27: =COUNTIF('HCO referrals'!B:B,HCO_Data!K27)+COUNTIF('HCO referrals'!C:C,HCO_Data!K27) -> 0 | I27: 420785354 | J27: 544957037222560785 | K27: ID00042 | L27: Hôpital Nord | M27: AVENUE ALBERT RAIMOND | N27: 42277 | O27: SAINT PRIEST EN JAREZ | Q27: France | R27: 24 | S27: 214 | T27: 214 | V27: Yes | W27: =COUNTIFS('Clinical Trials HCO'!$A:$A, K27, 'Clinical Trials HCO'!$D:$D, "<>") -> 0 | AG27: Yes
B28: 227 | C28: Gastroenterology treats pancreatic malignancy and pancreatic disease. The surgery page explicitly includes pancreatic cancer. | F28: =COUNTIF(HCPs!W:W,HCO_Data!K28) -> 1 | G28: =IF(COUNTIF('Testing Referrals'!B:B,HCO_Data!K28)>0,"Yes","") | H28: =COUNTIF('HCO referrals'!B:B,HCO_Data!K28)+COUNTIF('HCO referrals'!C:C,HCO_Data!K28) -> 2 | I28: 310780259 | J28: 544958368821806083 | K28: ID00130 | L28: Clinique Pasteur Toulouse | M28: 45 AVENUE DE LOMBEZ | N28: 31076 | O28: TOULOUSE | Q28: France | R28: 44 | S28: 209 | T28: 209 | V28: Yes | W28: =COUNTIFS('Clinical Trials HCO'!$A:$A, K28, 'Clinical Trials HCO'!$D:$D, "<>") -> 5 | AF28: Yes | AG28: Yes
C29: HEGP has documented pancreatic cancer activity across medical oncology, digestive surgery and pancreaticobiliary gastroenterology/endoscopy. The oncology service also conducts clinical research. | F29: =COUNTIF(HCPs!W:W,HCO_Data!K29) -> 4 | G29: =IF(COUNTIF('Testing Referrals'!B:B,HCO_Data!K29)>0,"Yes","") -> Yes | H29: =COUNTIF('HCO referrals'!B:B,HCO_Data!K29)+COUNTIF('HCO referrals'!C:C,HCO_Data!K29) -> 2 | I29: 750803447 | J29: 608464600169464832 | K29: ID00010 | L29: Hôpital Européen Georges-Pompidou | O29: PARIS | Q29: France | R29: 8 | S29: 208 | T29: 208 | V29: Yes | W29: =COUNTIFS('Clinical Trials HCO'!$A:$A, K29, 'Clinical Trials HCO'!$D:$D, "<>") -> 24 | AF29: Yes
B30: 294 | F30: =COUNTIF(HCPs!W:W,HCO_Data!K30) -> 3 | G30: =IF(COUNTIF('Testing Referrals'!B:B,HCO_Data!K30)>0,"Yes","") -> Yes | H30: =COUNTIF('HCO referrals'!B:B,HCO_Data!K30)+COUNTIF('HCO referrals'!C:C,HCO_Data!K30) -> 2 | I30: 380000067 | K30: ID00036 | L30: Hôpital Albert Michallon | M30: BOULEVARD DE LA CHANTOURNE | N30: 38700 | O30: LA TRONCHE | Q30: France | R30: 16 | S30: 205 | T30: 205 | V30: Yes | W30: =COUNTIFS('Clinical Trials HCO'!$A:$A, K30, 'Clinical Trials HCO'!$D:$D, "<>") -> 0 | AF30: Yes
B31: 456 | C31: Institut Strauss explicitly lists pancreatic cancer among cancers treated and has a current pancreatic-specific oncologist and pancreatic clinical-trial activity. | D31: Unicancer | F31: =COUNTIF(HCPs!W:W,HCO_Data!K31) -> 5 | G31: =IF(COUNTIF('Testing Referrals'!B:B,HCO_Data!K31)>0,"Yes","") | H31: =COUNTIF('HCO referrals'!B:B,HCO_Data!K31)+COUNTIF('HCO referrals'!C:C,HCO_Data!K31) -> 5 | I31: 670020098 | K31: ID00081 | L31: ICANS Strasbourg | M31: 17 RUE ALBERT CALMETTE | N31: 67200 | O31: STRASBOURG | Q31: France | R31: 11 | S31: 205 | T31: 205 | V31: Yes | W31: =COUNTIFS('Clinical Trials HCO'!$A:$A, K31, 'Clinical Trials HCO'!$D:$D, "<>") -> 14 | AD31: Yes | AE31: Certified Comprehensive Cancer Centre | AF31: Yes | AG31: Yes
B32: 114 | C32: CHU explicitly states that its digestive cancer programme includes pancreatic cancer, with diagnosis, surgery, chemotherapy/targeted therapy and weekly digestive cancer RCP. Its digestive surgery service explicitly lists cancer du pancréas and describes itself as a digestive oncology expert/referral centre. | F32: =COUNTIF(HCPs!W:W,HCO_Data!K32) -> 6 | G32: =IF(COUNTIF('Testing Referrals'!B:B,HCO_Data!K32)>0,"Yes","") -> Yes | H32: =COUNTIF('HCO referrals'!B:B,HCO_Data!K32)+COUNTIF('HCO referrals'!C:C,HCO_Data!K32) -> 1 | I32: 210987558 | K32: ID00052 | L32: CHRU le Bocage | M32: 1 BOULEVARD JEANNE D ARC | N32: 21079 | O32: DIJON | Q32: France | R32: 39 | S32: 198 | T32: 198 | V32: Yes | W32: =COUNTIFS('Clinical Trials HCO'!$A:$A, K32, 'Clinical Trials HCO'!$D:$D, "<>") -> 0 | AF32: Yes | AG32: Yes
B33: 115 | F33: =COUNTIF(HCPs!W:W,HCO_Data!K33) -> 4 | G33: =IF(COUNTIF('Testing Referrals'!B:B,HCO_Data!K33)>0,"Yes","") -> Yes | H33: =COUNTIF('HCO referrals'!B:B,HCO_Data!K33)+COUNTIF('HCO referrals'!C:C,HCO_Data!K33) -> 0 | I33: 870000064 | K33: ID00039 | L33: Hôpital Dupuytren | M33: 2 AVENUE MARTIN LUTHER KING | N33: 87042 | O33: LIMOGES | Q33: France | R33: 46 | S33: 197 | T33: 197 | V33: Yes | W33: =COUNTIFS('Clinical Trials HCO'!$A:$A, K33, 'Clinical Trials HCO'!$D:$D, "<>") -> 0 | AF33: Yes | AG33: Yes
B34: 10 | D34: Unicancer | F34: =COUNTIF(HCPs!W:W,HCO_Data!K34) -> 5 | G34: =IF(COUNTIF('Testing Referrals'!B:B,HCO_Data!K34)>0,"Yes","") -> Yes | H34: =COUNTIF('HCO referrals'!B:B,HCO_Data!K34)+COUNTIF('HCO referrals'!C:C,HCO_Data!K34) -> 0 | I34: 210987731 | K34: ID00053 | L34: Centre Georges-François Leclerc | O34: DIJON | Q34: France | R34: 10 | S34: 195 | T34: 195 | V34: Yes | W34: =COUNTIFS('Clinical Trials HCO'!$A:$A, K34, 'Clinical Trials HCO'!$D:$D, "<>") -> 44 | AF34: Yes | AG34: Yes
B35: 18 | F35: =COUNTIF(HCPs!W:W,HCO_Data!K35) -> 5 | G35: =IF(COUNTIF('Testing Referrals'!B:B,HCO_Data!K35)>0,"Yes","") -> Yes | H35: =COUNTIF('HCO referrals'!B:B,HCO_Data!K35)+COUNTIF('HCO referrals'!C:C,HCO_Data!K35) -> 0 | I35: 690783154 | K35: ID00013 | L35: Hôpital Édouard Herriot | O35: LYON | Q35: France | R35: 49 | S35: 192 | T35: 192 | V35: Yes | W35: =COUNTIFS('Clinical Trials HCO'!$A:$A, K35, 'Clinical Trials HCO'!$D:$D, "<>") -> 36 | AG35: Yes
B36: 216 | C36: Digestive oncology is delivered locally through consultation, day-hospital and weekly hospitalisation. Have dedicated pancreatic surgery and pancreatic diseases consultation. | F36: =COUNTIF(HCPs!W:W,HCO_Data!K36) -> 5 | G36: =IF(COUNTIF('Testing Referrals'!B:B,HCO_Data!K36)>0,"Yes","") | H36: =COUNTIF('HCO referrals'!B:B,HCO_Data!K36)+COUNTIF('HCO referrals'!C:C,HCO_Data!K36) -> 1 | I36: 140000209 | K36: ID00104 | L36: Hôpital de la Côte de Nacre | M36: AVENUE COTE DE NACRE | N36: 14033 | O36: CAEN | Q36: France | R36: 36 | S36: 191 | T36: 191 | V36: Yes | W36: =COUNTIFS('Clinical Trials HCO'!$A:$A, K36, 'Clinical Trials HCO'!$D:$D, "<>") -> 6 | AF36: Yes | AG36: Yes
F37: =COUNTIF(HCPs!W:W,HCO_Data!K37) -> 2 | G37: =IF(COUNTIF('Testing Referrals'!B:B,HCO_Data!K37)>0,"Yes","") -> Yes | H37: =COUNTIF('HCO referrals'!B:B,HCO_Data!K37)+COUNTIF('HCO referrals'!C:C,HCO_Data!K37) -> 0 | I37: 800006124 | K37: ID00035 | L37: Hôpital Sud | M37: 1 Rue du Professeur Christian Cabrol | O37: Amiens | Q37: France | R37: 29 | S37: 190 | T37: 190 | V37: Yes | W37: =COUNTIFS('Clinical Trials HCO'!$A:$A, K37, 'Clinical Trials HCO'!$D:$D, "<>") -> 0
B38: 211 | F38: =COUNTIF(HCPs!W:W,HCO_Data!K38) -> 3 | G38: =IF(COUNTIF('Testing Referrals'!B:B,HCO_Data!K38)>0,"Yes","") -> Yes | H38: =COUNTIF('HCO referrals'!B:B,HCO_Data!K38)+COUNTIF('HCO referrals'!C:C,HCO_Data!K38) -> 2 | I38: 490000049 | K38: ID00076 | L38: CHU Hôtel-Dieu | M38: 4 RUE LARREY | N38: 49933 | O38: ANGERS | Q38: France | R38: 57 | S38: 182 | T38: 182 | V38: Yes | W38: =COUNTIFS('Clinical Trials HCO'!$A:$A, K38, 'Clinical Trials HCO'!$D:$D, "<>") -> 2 | AF38: Yes | AG38: Yes
B39: 541 | F39: =COUNTIF(HCPs!W:W,HCO_Data!K39) -> 2 | G39: =IF(COUNTIF('Testing Referrals'!B:B,HCO_Data!K39)>0,"Yes","") | H39: =COUNTIF('HCO referrals'!B:B,HCO_Data!K39)+COUNTIF('HCO referrals'!C:C,HCO_Data!K39) -> 0 | I39: 440041580 | J39: 544957509996119053 | K39: ID00154 | L39: HOPITAL PRIVE DU CONFLUENT | M39: 4 RUE ERIC TABARLY | N39: 44277 | O39: NANTES | Q39: France | R39: 37 | S39: 180 | T39: 180 | V39: Yes | W39: =COUNTIFS('Clinical Trials HCO'!$A:$A, K39, 'Clinical Trials HCO'!$D:$D, "<>") -> 0 | AF39: Yes | AG39: Yes
B40: 483 | C40: The European Hospital has established an emergency pathway dedicated to the rapid diagnosis and treatment of suspected tumors and cancer, including pancreatic cancer. | F40: =COUNTIF(HCPs!W:W,HCO_Data!K40) -> 7 | G40: =IF(COUNTIF('Testing Referrals'!B:B,HCO_Data!K40)>0,"Yes","") | H40: =COUNTIF('HCO referrals'!B:B,HCO_Data!K40)+COUNTIF('HCO referrals'!C:C,HCO_Data!K40) -> 0 | I40: 130043664 | K40: ID00123 | L40: Hôpital Européen | M40: 6 RUE DÉSIRÉE CLARY | N40: 13003 | O40: MARSEILLE | Q40: France | R40: 34 | S40: 176 | T40: 176 | V40: Yes | W40: =COUNTIFS('Clinical Trials HCO'!$A:$A, K40, 'Clinical Trials HCO'!$D:$D, "<>") -> 11
B41: 132 | F41: =COUNTIF(HCPs!W:W,HCO_Data!K41) -> 2 | G41: =IF(COUNTIF('Testing Referrals'!B:B,HCO_Data!K41)>0,"Yes","") | H41: =COUNTIF('HCO referrals'!B:B,HCO_Data!K41)+COUNTIF('HCO referrals'!C:C,HCO_Data!K41) -> 0 | I41: 640000162 | K41: ID00034 | L41: CHIC de Bayonne | M41: 13 AVENUE DE L'INTERNE JACQUES LOEB | N41: 64109 | O41: BAYONNE | Q41: France | R41: 35 | S41: 174 | T41: 174 | V41: Yes | W41: =COUNTIFS('Clinical Trials HCO'!$A:$A, K41, 'Clinical Trials HCO'!$D:$D, "<>") -> 10 | AC41: Yes | AF41: Yes | AG41: Yes
B42: 127 | F42: =COUNTIF(HCPs!W:W,HCO_Data!K42) -> 3 | G42: =IF(COUNTIF('Testing Referrals'!B:B,HCO_Data!K42)>0,"Yes","") | H42: =COUNTIF('HCO referrals'!B:B,HCO_Data!K42)+COUNTIF('HCO referrals'!C:C,HCO_Data!K42) -> 2 | I42: 740000237 | J42: 544957629626057753 | K42: ID00155 | L42: CH ANNECY-GENEVOIS SITE ANNECY | M42: 1 AVENUE DE L'HÔPITAL | N42: 74370 | O42: EPAGNY METZ TESSY | Q42: France | R42: 45 | S42: 170 | T42: 170 | V42: Yes | W42: =COUNTIFS('Clinical Trials HCO'!$A:$A, K42, 'Clinical Trials HCO'!$D:$D, "<>") -> 0 | AF42: Yes | AG42: Yes
B43: 41 | C43: Baclesse explicitly lists cancer du pancréas among the digestive cancers it treats and has a dedicated digestive cancer pathway covering oncology, surgery and endoscopic diagnosis. Its endoscopy service explicitly diagnoses pancreatic cancers, and the centre is currently recruiting pancreatic-cancer trials. | D43: Unicancer | F43: =COUNTIF(HCPs!W:W,HCO_Data!K43) -> 3 | G43: =IF(COUNTIF('Testing Referrals'!B:B,HCO_Data!K43)>0,"Yes","") -> Yes | H43: =COUNTIF('HCO referrals'!B:B,HCO_Data!K43)+COUNTIF('HCO referrals'!C:C,HCO_Data!K43) -> 1 | I43: 140000555 | K43: ID00069 | L43: Centre François Baclesse | M43: 3 Avenue du Général Harris | N43: 14000 | O43: Caen | P43: Normandie | Q43: France | R43: 27 | S43: 162 | T43: 162 | V43: Yes | W43: =COUNTIFS('Clinical Trials HCO'!$A:$A, K43, 'Clinical Trials HCO'!$D:$D, "<>") -> 10 | AF43: Yes | AG43: Yes
B44: 213 | F44: =COUNTIF(HCPs!W:W,HCO_Data!K44) -> 2 | G44: =IF(COUNTIF('Testing Referrals'!B:B,HCO_Data!K44)>0,"Yes","") -> Yes | H44: =COUNTIF('HCO referrals'!B:B,HCO_Data!K44)+COUNTIF('HCO referrals'!C:C,HCO_Data!K44) -> 0 | I44: 450002613 | K44: ID00058 | L44: Hôpital de la Source | M44: 14 AVENUE DE L'HOPITAL | N44: 45067 | O44: ORLEANS | Q44: France | R44: 59 | S44: 157 | T44: 157 | V44: Yes | W44: =COUNTIFS('Clinical Trials HCO'!$A:$A, K44, 'Clinical Trials HCO'!$D:$D, "<>") -> 0 | AF44: Yes | AG44: Yes
B45: 700 | F45: =COUNTIF(HCPs!W:W,HCO_Data!K45) -> 1 | G45: =IF(COUNTIF('Testing Referrals'!B:B,HCO_Data!K45)>0,"Yes","") | H45: =COUNTIF('HCO referrals'!B:B,HCO_Data!K45)+COUNTIF('HCO referrals'!C:C,HCO_Data!K45) -> 0 | I45: 170000087 | J45: 621138881315619840 | K45: ID00156 | L45: HOPITAL SAINT-LOUIS - LA ROCHELLE | M45: RUE DU DR SCHWEITZER | N45: 17019 | O45: LA ROCHELLE | Q45: France | R45: 51 | S45: 157 | T45: 157 | V45: Yes | W45: =COUNTIFS('Clinical Trials HCO'!$A:$A, K45, 'Clinical Trials HCO'!$D:$D, "<>") -> 0 | AF45: Yes | AG45: Yes
B46: 190 | F46: =COUNTIF(HCPs!W:W,HCO_Data!K46) -> 4 | G46: =IF(COUNTIF('Testing Referrals'!B:B,HCO_Data!K46)>0,"Yes","") | H46: =COUNTIF('HCO referrals'!B:B,HCO_Data!K46)+COUNTIF('HCO referrals'!C:C,HCO_Data!K46) -> 0 | I46: 590000618 | J46: 544957420120572947 | K46: ID00157 | L46: CH VALENCIENNES | M46: 114 AVENUE DESANDROUINS | N46: 59322 | O46: VALENCIENNES | Q46: France | R46: 87 | S46: 156 | T46: 156 | V46: Yes | W46: =COUNTIFS('Clinical Trials HCO'!$A:$A, K46, 'Clinical Trials HCO'!$D:$D, "<>") -> 0 | AF46: Yes | AG46: Yes
B47: 427 | C47: A participating centre in BACAP. The endoscopy unit performs echo-endoscopy and ERCP and oncology explicitly mentions cancer of the pancreas. Digestive cancer surgery takes place here. | F47: =COUNTIF(HCPs!W:W,HCO_Data!K47) -> 6 | G47: =IF(COUNTIF('Testing Referrals'!B:B,HCO_Data!K47)>0,"Yes","") -> Yes | H47: =COUNTIF('HCO referrals'!B:B,HCO_Data!K47)+COUNTIF('HCO referrals'!C:C,HCO_Data!K47) -> 3 | I47: 60789195 | K47: ID00024 | L47: Hôpital de l'Archet | M47: 151 ROUTE SAINT ANTOINE DE GINESTIERE | N47: 6202 | O47: NICE | Q47: France | R47: 73 | S47: 155 | T47: 155 | V47: Yes | W47: =COUNTIFS('Clinical Trials HCO'!$A:$A, K47, 'Clinical Trials HCO'!$D:$D, "<>") -> 6 | AC47: Yes | AF47: Yes | AG47: Yes
B48: 653 | F48: =COUNTIF(HCPs!W:W,HCO_Data!K48) -> 1 | G48: =IF(COUNTIF('Testing Referrals'!B:B,HCO_Data!K48)>0,"Yes","") | H48: =COUNTIF('HCO referrals'!B:B,HCO_Data!K48)+COUNTIF('HCO referrals'!C:C,HCO_Data!K48) -> 1 | I48: 510024979 | K48: ID00143 | L48: Polyclinique Reims-Bezannes | M48: 109 RUE LOUIS VICTOR DE BROGLIE | N48: 51430 | O48: BEZANNES | Q48: France | R48: 361 | S48: 153 | T48: 153 | V48: Yes | W48: =COUNTIFS('Clinical Trials HCO'!$A:$A, K48, 'Clinical Trials HCO'!$D:$D, "<>") -> 0 | AF48: Yes
B49: 205 | F49: =COUNTIF(HCPs!W:W,HCO_Data!K49) -> 1 | G49: =IF(COUNTIF('Testing Referrals'!B:B,HCO_Data!K49)>0,"Yes","") | H49: =COUNTIF('HCO referrals'!B:B,HCO_Data!K49)+COUNTIF('HCO referrals'!C:C,HCO_Data!K49) -> 0 | I49: 830000345 | K49: ID00150 | L49: CH Sainte-Musse | M49: 54 RUE HENRI SAINTE CLAIRE DEVILLE | N49: 83056 | O49: TOULON | Q49: France | R49: 47 | S49: 153 | T49: 153 | V49: Yes | W49: =COUNTIFS('Clinical Trials HCO'!$A:$A, K49, 'Clinical Trials HCO'!$D:$D, "<>") -> 0 | AF49: Yes
B50: 615 | D50: Unicancer | F50: =COUNTIF(HCPs!W:W,HCO_Data!K50) -> 2 | G50: =IF(COUNTIF('Testing Referrals'!B:B,HCO_Data!K50)>0,"Yes","") -> Yes | H50: =COUNTIF('HCO referrals'!B:B,HCO_Data!K50)+COUNTIF('HCO referrals'!C:C,HCO_Data!K50) -> 1 | I50: 540001286 | K50: ID00040 | L50: ICL de Lorraine | M50: 6 AVENUE DE BOURGOGNE | N50: 54519 | O50: VANDOEUVRE LES NANCY | Q50: France | R50: 20 | S50: 152 | T50: 152 | V50: Yes | W50: =COUNTIFS('Clinical Trials HCO'!$A:$A, K50, 'Clinical Trials HCO'!$D:$D, "<>") -> 0 | AD50: Yes | AE50: In the A&D process | AF50: Yes
B51: 195 | F51: =COUNTIF(HCPs!W:W,HCO_Data!K51) -> 2 | G51: =IF(COUNTIF('Testing Referrals'!B:B,HCO_Data!K51)>0,"Yes","") | H51: =COUNTIF('HCO referrals'!B:B,HCO_Data!K51)+COUNTIF('HCO referrals'!C:C,HCO_Data!K51) -> 0 | I51: 840001861 | J51: 544957278067885062 | K51: ID00158 | L51: CH. D'AVIGNON HENRI DUFFAUT | M51: 305 RUE RAOUL FOLLEREAU | N51: 84902 | O51: AVIGNON | Q51: France | R51: 78 | S51: 152 | T51: 152 | V51: Yes | W51: =COUNTIFS('Clinical Trials HCO'!$A:$A, K51, 'Clinical Trials HCO'!$D:$D, "<>") -> 0 | AF51: Yes | AG51: Yes
B52: 388 | F52: =COUNTIF(HCPs!W:W,HCO_Data!K52) -> 1 | G52: =IF(COUNTIF('Testing Referrals'!B:B,HCO_Data!K52)>0,"Yes","") | H52: =COUNTIF('HCO referrals'!B:B,HCO_Data!K52)+COUNTIF('HCO referrals'!C:C,HCO_Data!K52) -> 0 | I52: 560000127 | K52: ID00111 | L52: CH Bretagne-Atlantique | M52: 20 BOULEVARD GÉNÉRAL MAURICE GUILLAUDOT | N52: 56017 | O52: VANNES | Q52: France | R52: 62 | S52: 150 | T52: 150 | V52: Yes | W52: =COUNTIFS('Clinical Trials HCO'!$A:$A, K52, 'Clinical Trials HCO'!$D:$D, "<>") -> 0 | AF52: Yes | AG52: Yes
B53: 480 | F53: =COUNTIF(HCPs!W:W,HCO_Data!K53) -> 1 | G53: =IF(COUNTIF('Testing Referrals'!B:B,HCO_Data!K53)>0,"Yes","") | H53: =COUNTIF('HCO referrals'!B:B,HCO_Data!K53)+COUNTIF('HCO referrals'!C:C,HCO_Data!K53) -> 0 | I53: 680004546 | K53: ID00159 | L53: HOPITAL EMILE MULLER | M53: 20 RUE DU DR LAENNEC | N53: 68051 | O53: MULHOUSE | Q53: France | R53: 33 | S53: 149 | T53: 149 | V53: Yes | W53: =COUNTIFS('Clinical Trials HCO'!$A:$A, K53, 'Clinical Trials HCO'!$D:$D, "<>") -> 0 | AF53: Yes | AG53: Yes
B54: 252 | C54: Saint-Joseph has a structured pancreatic tumour centre incorporating endoscopy, biliary drainage, biopsy, pancreatic surgery, medical oncology, pathology and RCP. | E54: Yes | F54: =COUNTIF(HCPs!W:W,HCO_Data!K54) -> 7 | G54: =IF(COUNTIF('Testing Referrals'!B:B,HCO_Data!K54)>0,"Yes","") | H54: =COUNTIF('HCO referrals'!B:B,HCO_Data!K54)+COUNTIF('HCO referrals'!C:C,HCO_Data!K54) -> 1 | I54: 750000523 | K54: ID00045 | L54: Hôpital Paris Saint-Joseph | M54: 185 RUE RAYMOND LOSSERAND | N54: 75674 | O54: PARIS | Q54: France | R54: 66 | S54: 148 | T54: 148 | V54: Yes | W54: =COUNTIFS('Clinical Trials HCO'!$A:$A, K54, 'Clinical Trials HCO'!$D:$D, "<>") -> 0 | AF54: Yes
F55: =COUNTIF(HCPs!W:W,HCO_Data!K55) -> 0 | G55: =IF(COUNTIF('Testing Referrals'!B:B,HCO_Data!K55)>0,"Yes","") | H55: =COUNTIF('HCO referrals'!B:B,HCO_Data!K55)+COUNTIF('HCO referrals'!C:C,HCO_Data!K55) -> 0 | I55: 750150187 | K55: ID00160 | L55: MAISON MEDICALE JEANNE GARNIER | M55: 106 AV EMILE ZOLA | O55: PARIS | P55: PARIS | Q55: France | R55: 277 | S55: 148 | T55: 148 | V55: Yes | W55: =COUNTIFS('Clinical Trials HCO'!$A:$A, K55, 'Clinical Trials HCO'!$D:$D, "<>") -> 0
B56: 74 | C56: Digestive oncology service explicitly diagnoses and treats pancreatic cancer | F56: =COUNTIF(HCPs!W:W,HCO_Data!K56) -> 8 | G56: =IF(COUNTIF('Testing Referrals'!B:B,HCO_Data!K56)>0,"Yes","") -> Yes | H56: =COUNTIF('HCO referrals'!B:B,HCO_Data!K56)+COUNTIF('HCO referrals'!C:C,HCO_Data!K56) -> 0 | I56: 130783293 | K56: ID00032 | L56: Hôpital de la Timone Adulte | M56: 264 RUE SAINT PIERRE | N56: 13005 | O56: MARSEILLE | Q56: France | R56: 50 | S56: 146 | T56: 146 | V56: Yes | W56: =COUNTIFS('Clinical Trials HCO'!$A:$A, K56, 'Clinical Trials HCO'!$D:$D, "<>") -> 43 | AC56: Yes | AG56: Yes
B57: 403 | C57: Since the opening of the Institut de Cancérologie et d’Imagerie (ICI) at Cavale Blanche in April 2024, the major adult oncology and digestive-oncology pathway is concentrated at Cavale Blanche | F57: =COUNTIF(HCPs!W:W,HCO_Data!K57) -> 4 | G57: =IF(COUNTIF('Testing Referrals'!B:B,HCO_Data!K57)>0,"Yes","") -> Yes | H57: =COUNTIF('HCO referrals'!B:B,HCO_Data!K57)+COUNTIF('HCO referrals'!C:C,HCO_Data!K57) -> 2 | I57: 290004324 | K57: ID00054 | L57: Hôpital de la Cavale Blanche | M57: BOULEVARD TANGUY PRIGENT | N57: 29609 | O57: BREST | Q57: France | R57: 32 | S57: 146 | T57: 146 | V57: Yes | W57: =COUNTIFS('Clinical Trials HCO'!$A:$A, K57, 'Clinical Trials HCO'!$D:$D, "<>") -> 3 | AF57: Yes | AG57: Yes
B58: 217 | F58: =COUNTIF(HCPs!W:W,HCO_Data!K58) -> 2 | G58: =IF(COUNTIF('Testing Referrals'!B:B,HCO_Data!K58)>0,"Yes","") -> Yes | H58: =COUNTIF('HCO referrals'!B:B,HCO_Data!K58)+COUNTIF('HCO referrals'!C:C,HCO_Data!K58) -> 0 | I58: 440000271 | K58: ID00077 | L58: Hôpital Hôtel-Dieu | M58: 1 PLACE ALEXIS RICORDEAU | N58: 44093 | O58: NANTES | Q58: France | R58: 83 | S58: 146 | T58: 146 | V58: Yes | W58: =COUNTIFS('Clinical Trials HCO'!$A:$A, K58, 'Clinical Trials HCO'!$D:$D, "<>") -> 0 | AG58: Yes
F59: =COUNTIF(HCPs!W:W,HCO_Data!K59) -> 3 | G59: =IF(COUNTIF('Testing Referrals'!B:B,HCO_Data!K59)>0,"Yes","") | H59: =COUNTIF('HCO referrals'!B:B,HCO_Data!K59)+COUNTIF('HCO referrals'!C:C,HCO_Data!K59) -> 2 | I59: 570026682 | J59: 621085473363739649 | K59: ID00110 | L59: Hôpital de Mercy | M59: 1 Allée du Château | O59: Ars-Laquenexy | Q59: France | R59: 42 | S59: 146 | T59: 146 | V59: Yes | W59: =COUNTIFS('Clinical Trials HCO'!$A:$A, K59, 'Clinical Trials HCO'!$D:$D, "<>") -> 0
B60: 198 | F60: =COUNTIF(HCPs!W:W,HCO_Data!K60) -> 1 | G60: =IF(COUNTIF('Testing Referrals'!B:B,HCO_Data!K60)>0,"Yes","") | H60: =COUNTIF('HCO referrals'!B:B,HCO_Data!K60)+COUNTIF('HCO referrals'!C:C,HCO_Data!K60) -> 0 | I60: 850000142 | K60: ID00087 | L60: CHD de Vendée | M60: BOULEVARD STEPHANE MOREAU | N60: 85925 | O60: LA ROCHE SUR YON | Q60: France | R60: 56 | S60: 145 | T60: 145 | V60: Yes | W60: =COUNTIFS('Clinical Trials HCO'!$A:$A, K60, 'Clinical Trials HCO'!$D:$D, "<>") -> 0 | AG60: Yes
B61: 491 | F61: =COUNTIF(HCPs!W:W,HCO_Data!K61) -> 1 | G61: =IF(COUNTIF('Testing Referrals'!B:B,HCO_Data!K61)>0,"Yes","") | H61: =COUNTIF('HCO referrals'!B:B,HCO_Data!K61)+COUNTIF('HCO referrals'!C:C,HCO_Data!K61) -> 5 | I61: 590780284 | K61: ID00161 | L61: GCS GHICL HOPITAL ST PHILIBERT | M61: 115 RUE DU GRAND BUT | N61: 59160 | O61: LILLE | Q61: France | R61: 330 | S61: 145 | T61: 145 | V61: Yes | W61: =COUNTIFS('Clinical Trials HCO'!$A:$A, K61, 'Clinical Trials HCO'!$D:$D, "<>") -> 0 | AG61: Yes
B62: 197 | C62: Hautepierre Hospital is part of the Strasbourg University Hospitals (HUS). The Department of General, Hepatic, Endocrine, and Transplant Surgery (Professor Bachellier) is the leading center for liver and pancreatic surgery. More recently, the department published the world's largest series of patients with locally advanced pancreatic cancer (i.e., with vascular invasion) who underwent pancreatic resection with resection/reconstruction of the adjacent arterial and venous structures invaded by the cancer. | F62: =COUNTIF(HCPs!W:W,HCO_Data!K62) -> 3 | G62: =IF(COUNTIF('Testing Referrals'!B:B,HCO_Data!K62)>0,"Yes","") -> Yes | H62: =COUNTIF('HCO referrals'!B:B,HCO_Data!K62)+COUNTIF('HCO referrals'!C:C,HCO_Data!K62) -> 7 | I62: 670783273 | K62: ID00002 | L62: Hôpital de Hautepierre | M62: 1 AVENUE MOLIERE | N62: 67200 | O62: STRASBOURG | Q62: France | R62: 349 | S62: 144 | T62: 144 | V62: Yes | W62: =COUNTIFS('Clinical Trials HCO'!$A:$A, K62, 'Clinical Trials HCO'!$D:$D, "<>") -> 12 | AG62: Yes
B63: 208 | C63: Pancreatic cancer is treated by the CCDO Bretagne team | F63: =COUNTIF(HCPs!W:W,HCO_Data!K63) -> 3 | G63: =IF(COUNTIF('Testing Referrals'!B:B,HCO_Data!K63)>0,"Yes","") | H63: =COUNTIF('HCO referrals'!B:B,HCO_Data!K63)+COUNTIF('HCO referrals'!C:C,HCO_Data!K63) -> 0 | I63: 350000121 | K63: ID00121 | L63: CHP Saint-Grégoire | M63: 6 BOULEVARD DE LE BOUTIERE | N63: 35768 | O63: SAINT GREGOIRE | Q63: France | R63: 82 | S63: 139 | T63: 139 | V63: Yes | W63: =COUNTIFS('Clinical Trials HCO'!$A:$A, K63, 'Clinical Trials HCO'!$D:$D, "<>") -> 0 | AG63: Yes
B64: 497 | C64: Saint Joseph Hospital has developed a multidisciplinary approach to facilitate early, rapid and reliable diagnosis and treatment of pancreatic, liver and bile duct emergencies. | F64: =COUNTIF(HCPs!W:W,HCO_Data!K64) -> 5 | G64: =IF(COUNTIF('Testing Referrals'!B:B,HCO_Data!K64)>0,"Yes","") | H64: =COUNTIF('HCO referrals'!B:B,HCO_Data!K64)+COUNTIF('HCO referrals'!C:C,HCO_Data!K64) -> 0 | I64: 130785652 | K64: ID00122 | L64: HOPITAL SAINT JOSEPH | M64: 26 BOULEVARD DE LOUVAIN | N64: 13008 | O64: MARSEILLE | Q64: France | R64: 43 | S64: 138 | T64: 138 | V64: Yes | W64: =COUNTIFS('Clinical Trials HCO'!$A:$A, K64, 'Clinical Trials HCO'!$D:$D, "<>") -> 6 | AF64: Yes | AG64: Yes
B65: 674 | D65: Unicancer | F65: =COUNTIF(HCPs!W:W,HCO_Data!K65) -> 7 | G65: =IF(COUNTIF('Testing Referrals'!B:B,HCO_Data!K65)>0,"Yes","") | H65: =COUNTIF('HCO referrals'!B:B,HCO_Data!K65)+COUNTIF('HCO referrals'!C:C,HCO_Data!K65) -> 0 | I65: 440001113 | K65: ID00080 | L65: ICO Saint-Herblain | M65: BOULEVARD JACQUES MONOD | N65: 44805 | O65: SAINT HERBLAIN | Q65: France | R65: 53 | S65: 137 | T65: 137 | V65: Yes | W65: =COUNTIFS('Clinical Trials HCO'!$A:$A, K65, 'Clinical Trials HCO'!$D:$D, "<>") -> 0
B66: 214 | C66: Pontchaillou is the CHU site where the Centre Hépato-Digestif and hepatobiliary/digestive surgery service are located. The digestive medicine service explicitly treats cancer du pancréas, while the surgical service explicitly treats pancreatic cancers and describes itself as a referral service for the Grand Ouest. | F66: =COUNTIF(HCPs!W:W,HCO_Data!K66) -> 4 | G66: =IF(COUNTIF('Testing Referrals'!B:B,HCO_Data!K66)>0,"Yes","") -> Yes | H66: =COUNTIF('HCO referrals'!B:B,HCO_Data!K66)+COUNTIF('HCO referrals'!C:C,HCO_Data!K66) -> 4 | I66: 350000741 | K66: ID00056 | L66: Hôpital Pontchaillou | M66: 2 RUE HENRI LE GUILLOUX | N66: 35000 | O66: RENNES | Q66: France | R66: 374 | S66: 135 | T66: 135 | V66: Yes | W66: =COUNTIFS('Clinical Trials HCO'!$A:$A, K66, 'Clinical Trials HCO'!$D:$D, "<>") -> 9 | AG66: Yes
B67: 566 | F67: =COUNTIF(HCPs!W:W,HCO_Data!K67) -> 2 | G67: =IF(COUNTIF('Testing Referrals'!B:B,HCO_Data!K67)>0,"Yes","") | H67: =COUNTIF('HCO referrals'!B:B,HCO_Data!K67)+COUNTIF('HCO referrals'!C:C,HCO_Data!K67) -> 2 | I67: 310026927 | J67: 933134376886799711 | K67: ID00162 | L67: CL CAPIO LA CROIX DU SUD QUINT FONSEGR | M67: 52 CHEMIN DE RIBAUTE | N67: 31130 | O67: QUINT FONSEGRIVES | Q67: France | R67: 98 | S67: 135 | T67: 135 | V67: Yes | W67: =COUNTIFS('Clinical Trials HCO'!$A:$A, K67, 'Clinical Trials HCO'!$D:$D, "<>") -> 0 | AF67: Yes | AG67: Yes
B68: 568 | C68: Institut Bergonié is Bordeaux's CLCC and a regional referral centre for digestive oncology. Its pancreatic programme spans diagnosis/EUS, bilio-pancreatic intervention, systemic therapy, pancreatic surgery, pancreas-specific surgical RCP and molecular research. | D68: Unicancer | F68: =COUNTIF(HCPs!W:W,HCO_Data!K68) -> 6 | G68: =IF(COUNTIF('Testing Referrals'!B:B,HCO_Data!K68)>0,"Yes","") -> Yes | H68: =COUNTIF('HCO referrals'!B:B,HCO_Data!K68)+COUNTIF('HCO referrals'!C:C,HCO_Data!K68) -> 2 | I68: 330000662 | K68: ID00071 | L68: Institut Bergonié | M68: 229 COURS DE L'ARGONNE | N68: 33076 | O68: BORDEAUX | Q68: France | R68: 25 | S68: 134 | T68: 134 | V68: Yes | W68: =COUNTIFS('Clinical Trials HCO'!$A:$A, K68, 'Clinical Trials HCO'!$D:$D, "<>") -> 38 | AE68: In the A&D process
B69: 228 | C69: The clinic states that it is authorised fo provide pancreatic cancer chemotherapy. | F69: =COUNTIF(HCPs!W:W,HCO_Data!K69) -> 3 | G69: =IF(COUNTIF('Testing Referrals'!B:B,HCO_Data!K69)>0,"Yes","") | H69: =COUNTIF('HCO referrals'!B:B,HCO_Data!K69)+COUNTIF('HCO referrals'!C:C,HCO_Data!K69) -> 2 | I69: 660780784 | J69: 648642590089954305 | K69: ID00149 | L69: Clinique Saint-Pierre | M69: RUE JEAN GALLIA | N69: 66012 | O69: PERPIGNAN | Q69: France | R69: 81 | S69: 134 | T69: 134 | V69: Yes | W69: =COUNTIFS('Clinical Trials HCO'!$A:$A, K69, 'Clinical Trials HCO'!$D:$D, "<>") -> 0 | AG69: Yes
B70: 75 | C70: Hôpital Nord has a genuinely broad pancreas programme: digestive oncology, specialist pancreaticobiliary gastroenterology, interventional endoscopy and pancreatic surgery. | F70: =COUNTIF(HCPs!W:W,HCO_Data!K70) -> 5 | G70: =IF(COUNTIF('Testing Referrals'!B:B,HCO_Data!K70)>0,"Yes","") -> Yes | H70: =COUNTIF('HCO referrals'!B:B,HCO_Data!K70)+COUNTIF('HCO referrals'!C:C,HCO_Data!K70) -> 0 | I70: 130780521 | J70: 544957293041550346 | K70: ID00023 | L70: Hôpital Nord | M70: CHEMIN DES BOURRELY | N70: 13015 | O70: MARSEILLE | Q70: France | R70: 96 | S70: 133 | T70: 133 | V70: Yes | W70: =COUNTIFS('Clinical Trials HCO'!$A:$A, K70, 'Clinical Trials HCO'!$D:$D, "<>") -> 8 | AC70: Yes | AF70: Yes | AG70: Yes
B71: 265 | F71: =COUNTIF(HCPs!W:W,HCO_Data!K71) -> 2 | G71: =IF(COUNTIF('Testing Referrals'!B:B,HCO_Data!K71)>0,"Yes","") | H71: =COUNTIF('HCO referrals'!B:B,HCO_Data!K71)+COUNTIF('HCO referrals'!C:C,HCO_Data!K71) -> 0 | I71: 640000600 | K71: ID00028 | L71: CH de Pau | M71: 4 BOULEVARD HAUTERIVE | N71: 64046 | O71: PAU | Q71: France | R71: 61 | S71: 133 | T71: 133 | V71: Yes | W71: =COUNTIFS('Clinical Trials HCO'!$A:$A, K71, 'Clinical Trials HCO'!$D:$D, "<>") -> 4 | AC71: Yes | AF71: Yes | AG71: Yes
B72: 50 | C72: CEM explicitly lists cancer du pancréas among digestive cancers treated and states that its clinicians collaborate with CHU Rennes. It has highly current pancreatic clinical-trial activity. | D72: Unicancer | F72: =COUNTIF(HCPs!W:W,HCO_Data!K72) -> 2 | G72: =IF(COUNTIF('Testing Referrals'!B:B,HCO_Data!K72)>0,"Yes","") -> Yes | H72: =COUNTIF('HCO referrals'!B:B,HCO_Data!K72)+COUNTIF('HCO referrals'!C:C,HCO_Data!K72) -> 6 | I72: 350002812 | K72: ID00085 | L72: Centre Eugène Marquis | M72: Avenue de la Bataille Flandres-Dunkerque | N72: 35000 | O72: Rennes | P72: Bretagne | Q72: France | R72: 38 | S72: 133 | T72: 133 | V72: Yes | W72: =COUNTIFS('Clinical Trials HCO'!$A:$A, K72, 'Clinical Trials HCO'!$D:$D, "<>") -> 29 | AG72: Yes
B73: 543 | F73: =COUNTIF(HCPs!W:W,HCO_Data!K73) -> 1 | G73: =IF(COUNTIF('Testing Referrals'!B:B,HCO_Data!K73)>0,"Yes","") -> Yes | H73: =COUNTIF('HCO referrals'!B:B,HCO_Data!K73)+COUNTIF('HCO referrals'!C:C,HCO_Data!K73) -> 0 | I73: 790000087 | J73: 544956975977333791 | K73: ID00163 | L73: NIORT HOSPITAL CENTER | M73: 40 AVENUE CHARLES DE GAULLE | N73: 79021 | O73: NIORT | Q73: France | R73: 41 | S73: 133 | T73: 133 | V73: Yes | W73: =COUNTIFS('Clinical Trials HCO'!$A:$A, K73, 'Clinical Trials HCO'!$D:$D, "<>") -> 0 | AF73: Yes
B74: 638 | F74: =COUNTIF(HCPs!W:W,HCO_Data!K74) -> 1 | G74: =IF(COUNTIF('Testing Referrals'!B:B,HCO_Data!K74)>0,"Yes","") | H74: =COUNTIF('HCO referrals'!B:B,HCO_Data!K74)+COUNTIF('HCO referrals'!C:C,HCO_Data!K74) -> 0 | I74: 600100754 | J74: 544958003883803665 | K74: ID00164 | L74: POLYCLINIQUE SAINT CÔME | M74: 7 RUE JEAN-JACQUES BERNARD | N74: 60204 | O74: COMPIEGNE | Q74: France | R74: 93 | S74: 132 | T74: 132 | V74: Yes | W74: =COUNTIFS('Clinical Trials HCO'!$A:$A, K74, 'Clinical Trials HCO'!$D:$D, "<>") -> 0 | AF74: Yes | AG74: Yes
B75: 289 | F75: =COUNTIF(HCPs!W:W,HCO_Data!K75) -> 4 | G75: =IF(COUNTIF('Testing Referrals'!B:B,HCO_Data!K75)>0,"Yes","") -> Yes | H75: =COUNTIF('HCO referrals'!B:B,HCO_Data!K75)+COUNTIF('HCO referrals'!C:C,HCO_Data!K75) -> 0 | I75: 690784137 | K75: ID00022 | L75: Hôpital Lyon Sud | M75: 165 CHEMIN DU GRAND REVOYET | N75: 69310 | O75: PIERRE BENITE | Q75: France | R75: 52 | S75: 130 | T75: 130 | V75: Yes | W75: =COUNTIFS('Clinical Trials HCO'!$A:$A, K75, 'Clinical Trials HCO'!$D:$D, "<>") -> 21 | AF75: Yes | AG75: Yes
F76: =COUNTIF(HCPs!W:W,HCO_Data!K76) -> 2 | G76: =IF(COUNTIF('Testing Referrals'!B:B,HCO_Data!K76)>0,"Yes","") | H76: =COUNTIF('HCO referrals'!B:B,HCO_Data!K76)+COUNTIF('HCO referrals'!C:C,HCO_Data!K76) -> 0 | I76: 570026252 | J76: 544957777617880067 | K76: ID00165 | L76: HOPITAL ROBERT SCHUMAN DE VANTOUX -HPM | M76: R DU CHAMP MONTOY | O76: VANTOUX | P76: MOSELLE | Q76: France | R76: 60 | S76: 130 | T76: 130 | V76: Yes | W76: =COUNTIFS('Clinical Trials HCO'!$A:$A, K76, 'Clinical Trials HCO'!$D:$D, "<>") -> 0
B77: 343 | F77: =COUNTIF(HCPs!W:W,HCO_Data!K77) -> 2 | G77: =IF(COUNTIF('Testing Referrals'!B:B,HCO_Data!K77)>0,"Yes","") | H77: =COUNTIF('HCO referrals'!B:B,HCO_Data!K77)+COUNTIF('HCO referrals'!C:C,HCO_Data!K77) -> 2 | I77: 60780491 | J77: 938846044801338719 | K77: ID00166 | L77: ARNAULT TZANCK INSTITUTE | M77: 231 AVENUE DU DOCTEUR MAURICE DONAT | N77: 6721 | O77: SAINT LAURENT DU VAR | Q77: France | R77: 372 | S77: 129 | T77: 129 | V77: Yes | W77: =COUNTIFS('Clinical Trials HCO'!$A:$A, K77, 'Clinical Trials HCO'!$D:$D, "<>") -> 0 | AE77: In the A&D process
B78: 287 | C78: the hospital has a dedicated pancreatic adenocarcinoma pathway article naming pancreatic cancer care and multidisciplinary decision-making.The hospital performs EUS/écho-endoscopie, CPRE/ERCP. | F78: =COUNTIF(HCPs!W:W,HCO_Data!K78) -> 2 | G78: =IF(COUNTIF('Testing Referrals'!B:B,HCO_Data!K78)>0,"Yes","") | H78: =COUNTIF('HCO referrals'!B:B,HCO_Data!K78)+COUNTIF('HCO referrals'!C:C,HCO_Data!K78) -> 0 | I78: 680000684 | K78: ID00167 | L78: LOUIS PASTEUR HOSPITAL | M78: 39 AVENUE DE LA LIBERTE | N78: 68024 | O78: COLMAR | Q78: France | R78: 76 | S78: 129 | T78: 129 | V78: Yes | W78: =COUNTIFS('Clinical Trials HCO'!$A:$A, K78, 'Clinical Trials HCO'!$D:$D, "<>") -> 0 | AG78: Yes
B79: 246 | F79: =COUNTIF(HCPs!W:W,HCO_Data!K79) -> 2 | G79: =IF(COUNTIF('Testing Referrals'!B:B,HCO_Data!K79)>0,"Yes","") | H79: =COUNTIF('HCO referrals'!B:B,HCO_Data!K79)+COUNTIF('HCO referrals'!C:C,HCO_Data!K79) -> 0 | I79: 190000018 | J79: 544957153413170184 | K79: ID00168 | L79: DUBOIS BRIVE HOSPITAL CENTER | M79: 3 BOULEVARD DOCTEUR VERLHAC | N79: 19312 | O79: BRIVE LA GAILLARDE | Q79: France | R79: 72 | S79: 124 | T79: 124 | V79: Yes | W79: =COUNTIFS('Clinical Trials HCO'!$A:$A, K79, 'Clinical Trials HCO'!$D:$D, "<>") -> 0 | AF79: Yes | AG79: Yes
B80: 505 | F80: =COUNTIF(HCPs!W:W,HCO_Data!K80) -> 1 | G80: =IF(COUNTIF('Testing Referrals'!B:B,HCO_Data!K80)>0,"Yes","") | H80: =COUNTIF('HCO referrals'!B:B,HCO_Data!K80)+COUNTIF('HCO referrals'!C:C,HCO_Data!K80) -> 0 | I80: 440033819 | K80: ID00102 | L80: Santé Atlantique | M80: AVENUE CLAUDE BERNARD | N80: 44800 | O80: SAINT HERBLAIN | Q80: France | R80: 235 | S80: 123 | T80: 123 | V80: Yes | W80: =COUNTIFS('Clinical Trials HCO'!$A:$A, K80, 'Clinical Trials HCO'!$D:$D, "<>") -> 0 | AF80: Yes | AG80: Yes
B81: 716 | F81: =COUNTIF(HCPs!W:W,HCO_Data!K81) -> 0 | G81: =IF(COUNTIF('Testing Referrals'!B:B,HCO_Data!K81)>0,"Yes","") | H81: =COUNTIF('HCO referrals'!B:B,HCO_Data!K81)+COUNTIF('HCO referrals'!C:C,HCO_Data!K81) -> 2 | I81: 260000013 | K81: ID00169 | L81: VALENCIA CH | M81: 179 BOULEVARD MARECHAL JUIN | N81: 26953 | O81: VALENCE | Q81: France | R81: 89 | S81: 122 | T81: 122 | V81: Yes | W81: =COUNTIFS('Clinical Trials HCO'!$A:$A, K81, 'Clinical Trials HCO'!$D:$D, "<>") -> 0 | AF81: Yes
B82: 718 | F82: =COUNTIF(HCPs!W:W,HCO_Data!K82) -> 1 | G82: =IF(COUNTIF('Testing Referrals'!B:B,HCO_Data!K82)>0,"Yes","") | H82: =COUNTIF('HCO referrals'!B:B,HCO_Data!K82)+COUNTIF('HCO referrals'!C:C,HCO_Data!K82) -> 2 | I82: 620000653 | J82: 544957516941886487 | K82: ID00170 | L82: CH BOULOGNE-SUR-MER | M82: RUE JACQUES MONOD | N82: 62321 | O82: BOULOGNE SUR MER | Q82: France | R82: 74 | S82: 122 | T82: 122 | V82: Yes | W82: =COUNTIFS('Clinical Trials HCO'!$A:$A, K82, 'Clinical Trials HCO'!$D:$D, "<>") -> 0 | AF82: Yes | AG82: Yes
B83: 43 | C83: Jean Perrin provided chemotherapy, radiotherapy, pathology and molecular profiling. | D83: Unicancer | F83: =COUNTIF(HCPs!W:W,HCO_Data!K83) -> 1 | G83: =IF(COUNTIF('Testing Referrals'!B:B,HCO_Data!K83)>0,"Yes","") -> Yes | H83: =COUNTIF('HCO referrals'!B:B,HCO_Data!K83)+COUNTIF('HCO referrals'!C:C,HCO_Data!K83) -> 2 | I83: 630000479 | K83: ID00049 | L83: Centre Jean Perrin | M83: 58 Rue Montalembert | N83: 63011 | O83: Clermont-Ferrand | P83: Auvergne-Rhône-Alpes | Q83: France | R83: 86 | S83: 120 | T83: 120 | V83: Yes | W83: =COUNTIFS('Clinical Trials HCO'!$A:$A, K83, 'Clinical Trials HCO'!$D:$D, "<>") -> 11 | AF83: Yes
B84: 429 | F84: =COUNTIF(HCPs!W:W,HCO_Data!K84) -> 3 | G84: =IF(COUNTIF('Testing Referrals'!B:B,HCO_Data!K84)>0,"Yes","") -> Yes | H84: =COUNTIF('HCO referrals'!B:B,HCO_Data!K84)+COUNTIF('HCO referrals'!C:C,HCO_Data!K84) -> 2 | I84: 920000460 | K84: ID00044 | L84: Institut Curie Saint-Cloud | M84: 35 RUE DAILLY | N84: 92210 | O84: SAINT CLOUD | Q84: France | R84: 31 | S84: 119 | T84: 119 | V84: Yes | W84: =COUNTIFS('Clinical Trials HCO'!$A:$A, K84, 'Clinical Trials HCO'!$D:$D, "<>") -> 12 | AG84: Yes
B85: 302 | C85: private pancreatic cancer-capable centre rather than a formally documented major referral centre. Its oncology page explicitly lists digestive cancers including pancreas, with diagnosis by imaging, biopsies/anatomopathology and endoscopy | F85: =COUNTIF(HCPs!W:W,HCO_Data!K85) -> 2 | G85: =IF(COUNTIF('Testing Referrals'!B:B,HCO_Data!K85)>0,"Yes","") | H85: =COUNTIF('HCO referrals'!B:B,HCO_Data!K85)+COUNTIF('HCO referrals'!C:C,HCO_Data!K85) -> 0 | I85: 370007569 | K85: ID00171 | L85: PÔLE SANTÉ LÉONARD DE VINCI | M85: 1 AVENUE DU PROF ALEXANDRE MINKOWSKI | N85: 37175 | O85: CHAMBRAY LES TOURS | Q85: France | R85: 79 | S85: 119 | T85: 119 | V85: Yes | W85: =COUNTIFS('Clinical Trials HCO'!$A:$A, K85, 'Clinical Trials HCO'!$D:$D, "<>") -> 0 | AF85: Yes
B86: 516 | C86: private pancreatic cancer-capable centre within the Ramsay Santé Institut de Cancérologie Pôle Île-de-France Est. digestive/visceral surgery covers benign and cancerous diseases of the pancreas. interventional echo-endoscopy | F86: =COUNTIF(HCPs!W:W,HCO_Data!K86) -> 3 | G86: =IF(COUNTIF('Testing Referrals'!B:B,HCO_Data!K86)>0,"Yes","") | H86: =COUNTIF('HCO referrals'!B:B,HCO_Data!K86)+COUNTIF('HCO referrals'!C:C,HCO_Data!K86) -> 0 | I86: 940300270 | K86: ID00172 | L86: HOPITAL PRIVE ARMAND BRILLARD | M86: 3 AVENUE WATTEAU | N86: 94130 | O86: NOGENT SUR MARNE | Q86: France | R86: 180 | S86: 119 | T86: 119 | V86: Yes | W86: =COUNTIFS('Clinical Trials HCO'!$A:$A, K86, 'Clinical Trials HCO'!$D:$D, "<>") -> 0 | AF86: Yes | AG86: Yes
B87: 549 | F87: =COUNTIF(HCPs!W:W,HCO_Data!K87) -> 1 | G87: =IF(COUNTIF('Testing Referrals'!B:B,HCO_Data!K87)>0,"Yes","") | H87: =COUNTIF('HCO referrals'!B:B,HCO_Data!K87)+COUNTIF('HCO referrals'!C:C,HCO_Data!K87) -> 0 | I87: 560000135 | K87: ID00173 | L87: GHBS - HÔPITAL DU SCORFF | M87: 5 AVENUE DE CHOISEUL | N87: 56322 | O87: LORIENT | Q87: France | R87: 70 | S87: 116 | T87: 116 | V87: Yes | W87: =COUNTIFS('Clinical Trials HCO'!$A:$A, K87, 'Clinical Trials HCO'!$D:$D, "<>") -> 0 | AF87: Yes | AG87: Yes
B88: 34 | C88: Trocadéro plays a role in the diagnostic/endoscopic pancreatic pathway. | F88: =COUNTIF(HCPs!W:W,HCO_Data!K88) -> 2 | G88: =IF(COUNTIF('Testing Referrals'!B:B,HCO_Data!K88)>0,"Yes","") | H88: =COUNTIF('HCO referrals'!B:B,HCO_Data!K88)+COUNTIF('HCO referrals'!C:C,HCO_Data!K88) -> 0 | I88: 750300881 | K88: ID00027 | L88: Clinique du Trocadéro | M88: 62 Rue de la Tour | O88: PARIS | Q88: France | R88: 414 | S88: 114 | T88: 114 | V88: Yes | W88: =COUNTIFS('Clinical Trials HCO'!$A:$A, K88, 'Clinical Trials HCO'!$D:$D, "<>") -> 2 | AC88: Yes
B89: 321 | C89: Cancer.fr confirms chemotherapy and digestive cancer surgery, but these are generic cancer authorisations and do not establish pancreatic treatment specifically. | F89: =COUNTIF(HCPs!W:W,HCO_Data!K89) -> 0 | G89: =IF(COUNTIF('Testing Referrals'!B:B,HCO_Data!K89)>0,"Yes","") | H89: =COUNTIF('HCO referrals'!B:B,HCO_Data!K89)+COUNTIF('HCO referrals'!C:C,HCO_Data!K89) -> 0 | I89: 760780619 | K89: ID00174 | L89: SAINT-HILAIRE CLINIC ROUEN | M89: 2 PLACE SAINT-HILAIRE | N89: 76044 | O89: ROUEN | Q89: France | R89: 256 | S89: 114 | T89: 114 | V89: Yes | W89: =COUNTIFS('Clinical Trials HCO'!$A:$A, K89, 'Clinical Trials HCO'!$D:$D, "<>") -> 0 | AF89: Yes | AG89: Yes
B90: 317 | F90: =COUNTIF(HCPs!W:W,HCO_Data!K90) -> 1 | G90: =IF(COUNTIF('Testing Referrals'!B:B,HCO_Data!K90)>0,"Yes","") | H90: =COUNTIF('HCO referrals'!B:B,HCO_Data!K90)+COUNTIF('HCO referrals'!C:C,HCO_Data!K90) -> 0 | I90: 780300414 | K90: ID00175 | L90: PRIVATE HOSPITAL OF EUROPE | M90: 9 RUE DE SAINT GERMAIN | N90: 78560 | O90: LE PORT MARLY | Q90: France | R90: 129 | S90: 114 | T90: 114 | V90: Yes | W90: =COUNTIFS('Clinical Trials HCO'!$A:$A, K90, 'Clinical Trials HCO'!$D:$D, "<>") -> 0 | AF90: Yes | AG90: Yes
B91: 513 | C91: Nouvel Hôpital Civil is an important HUS pancreatic cancer centre providing specialised diagnosis, advanced endoscopy, multidisciplinary decision-making and pancreatic surgery. HUS explicitly documents EUS-guided biopsy and biliary stenting for pancreatic cancer, while the IHU confirms that pancreatic adenocarcinoma cases are discussed in a dedicated weekly RCP at NHC. | F91: =COUNTIF(HCPs!W:W,HCO_Data!K91) -> 3 | G91: =IF(COUNTIF('Testing Referrals'!B:B,HCO_Data!K91)>0,"Yes","") -> Yes | H91: =COUNTIF('HCO referrals'!B:B,HCO_Data!K91)+COUNTIF('HCO referrals'!C:C,HCO_Data!K91) -> 5 | I91: 670000025 | K91: ID00006 | L91: Nouvel Hôpital Civil | M91: 1 PLACE DE L'HOPITAL | N91: 67091 | O91: STRASBOURG | Q91: France | R91: 363 | S91: 112 | T91: 112 | V91: Yes | W91: =COUNTIFS('Clinical Trials HCO'!$A:$A, K91, 'Clinical Trials HCO'!$D:$D, "<>") -> 2 | AF91: Yes | AG91: Yes
B92: 530 | F92: =COUNTIF(HCPs!W:W,HCO_Data!K92) -> 1 | G92: =IF(COUNTIF('Testing Referrals'!B:B,HCO_Data!K92)>0,"Yes","") | H92: =COUNTIF('HCO referrals'!B:B,HCO_Data!K92)+COUNTIF('HCO referrals'!C:C,HCO_Data!K92) -> 0 | I92: 420011413 | K92: ID00128 | L92: Hôpital Privé de la Loire | M92: 39 BOULEVARD DE LA PALLE | N92: 42100 | O92: SAINT ETIENNE | Q92: France | R92: 84 | S92: 112 | T92: 112 | V92: Yes | W92: =COUNTIFS('Clinical Trials HCO'!$A:$A, K92, 'Clinical Trials HCO'!$D:$D, "<>") -> 0 | AF92: Yes | AG92: Yes
B93: 658 | F93: =COUNTIF(HCPs!W:W,HCO_Data!K93) -> 0 | G93: =IF(COUNTIF('Testing Referrals'!B:B,HCO_Data!K93)>0,"Yes","") | H93: =COUNTIF('HCO referrals'!B:B,HCO_Data!K93)+COUNTIF('HCO referrals'!C:C,HCO_Data!K93) -> 0 | I93: 60780517 | K93: ID00176 | L93: POLYCLINIQUE SAINT JEAN | M93: 81 AVENUE DU DOCTEUR MAURICE DONAT | N93: 6800 | O93: CAGNES SUR MER | Q93: France | R93: 67 | S93: 112 | T93: 112 | V93: Yes | W93: =COUNTIFS('Clinical Trials HCO'!$A:$A, K93, 'Clinical Trials HCO'!$D:$D, "<>") -> 0 | AF93: Yes | AG93: Yes
F94: =COUNTIF(HCPs!W:W,HCO_Data!K94) -> 0 | G94: =IF(COUNTIF('Testing Referrals'!B:B,HCO_Data!K94)>0,"Yes","") | H94: =COUNTIF('HCO referrals'!B:B,HCO_Data!K94)+COUNTIF('HCO referrals'!C:C,HCO_Data!K94) -> 0 | I94: 720000249 | K94: ID00140 | L94: Clinique Victor Hugo | O94: LE MANS | Q94: France | R94: 64 | S94: 111 | T94: 111 | V94: Yes | W94: =COUNTIFS('Clinical Trials HCO'!$A:$A, K94, 'Clinical Trials HCO'!$D:$D, "<>") -> 4
B95: 574 | C95: Part of the same organisation as CHU Orléans / Hôpital de la Source. Most specialists registered at the other location | F95: =COUNTIF(HCPs!W:W,HCO_Data!K95) -> 0 | G95: =IF(COUNTIF('Testing Referrals'!B:B,HCO_Data!K95)>0,"Yes","") | H95: =COUNTIF('HCO referrals'!B:B,HCO_Data!K95)+COUNTIF('HCO referrals'!C:C,HCO_Data!K95) -> 0 | I95: 450021449 | K95: ID00177 | L95: JEANNE D'ARC GIEN SITE - CHRU ORLÉANS | M95: 2 AVENUE JEAN VILLEJEAN | N95: 45500 | O95: GIEN | Q95: France | R95: 194 | S95: 111 | T95: 111 | V95: Yes | W95: =COUNTIFS('Clinical Trials HCO'!$A:$A, K95, 'Clinical Trials HCO'!$D:$D, "<>") -> 0 | AF95: Yes
B96: 283 | F96: =COUNTIF(HCPs!W:W,HCO_Data!K96) -> 5 | G96: =IF(COUNTIF('Testing Referrals'!B:B,HCO_Data!K96)>0,"Yes","") -> Yes | H96: =COUNTIF('HCO referrals'!B:B,HCO_Data!K96)+COUNTIF('HCO referrals'!C:C,HCO_Data!K96) -> 0 | I96: 490000155 | K96: ID00075 | L96: ICO Paul Papin | M96: 15 RUE ANDRE BOCQUEL | N96: 49055 | O96: ANGERS | Q96: France | R96: 55 | S96: 110 | T96: 110 | V96: Yes | W96: =COUNTIFS('Clinical Trials HCO'!$A:$A, K96, 'Clinical Trials HCO'!$D:$D, "<>") -> 13 | AF96: Yes
B97: 38 | C97: Godinot is a reference center in the management of pancreatic cancer, combining expertise in oncology, radiotherapy and surgery. Godinot is an active site in several pancreatic adenocarcinoma systemic-treatment trials, including ongoing metastatic pancreatic-cancer studies. | D97: Unicancer | F97: =COUNTIF(HCPs!W:W,HCO_Data!K97) -> 2 | G97: =IF(COUNTIF('Testing Referrals'!B:B,HCO_Data!K97)>0,"Yes","") -> Yes | H97: =COUNTIF('HCO referrals'!B:B,HCO_Data!K97)+COUNTIF('HCO referrals'!C:C,HCO_Data!K97) -> 0 | I97: 510000516 | K97: ID00060 | L97: Institut Jean Godinot | M97: 1 Rue du Général Koenig | N97: 51726 | O97: Reims | P97: Grand Est | Q97: France | R97: 21 | S97: 109 | T97: 109 | V97: Yes | W97: =COUNTIFS('Clinical Trials HCO'!$A:$A, K97, 'Clinical Trials HCO'!$D:$D, "<>") -> 8 | AD97: Yes | AE97: Certified Comprehensive Cancer Centre | AF97: Yes
B98: 307 | F98: =COUNTIF(HCPs!W:W,HCO_Data!K98) -> 1 | G98: =IF(COUNTIF('Testing Referrals'!B:B,HCO_Data!K98)>0,"Yes","") | H98: =COUNTIF('HCO referrals'!B:B,HCO_Data!K98)+COUNTIF('HCO referrals'!C:C,HCO_Data!K98) -> 0 | I98: 130786361 | J98: 934594198376549727 | K98: ID00152 | L98: Hôpital Privé de Provence | M98: 235 ALLEE NICOLAS DE STAEL | N98: 13595 | O98: AIX EN PROVENCE | Q98: France | R98: 95 | S98: 109 | T98: 109 | V98: Yes | W98: =COUNTIFS('Clinical Trials HCO'!$A:$A, K98, 'Clinical Trials HCO'!$D:$D, "<>") -> 0 | AG98: Yes
B99: 215 | F99: =COUNTIF(HCPs!W:W,HCO_Data!K99) -> 1 | G99: =IF(COUNTIF('Testing Referrals'!B:B,HCO_Data!K99)>0,"Yes","") -> Yes | H99: =COUNTIF('HCO referrals'!B:B,HCO_Data!K99)+COUNTIF('HCO referrals'!C:C,HCO_Data!K99) -> 0 | I99: 370004467 | K99: ID00057 | L99: Hôpital Trousseau | M99: AVENUE DE LA REPUBLIQUE | N99: 37170 | O99: CHAMBRAY LES TOURS | Q99: France | R99: 383 | S99: 108 | T99: 108 | V99: Yes | W99: =COUNTIFS('Clinical Trials HCO'!$A:$A, K99, 'Clinical Trials HCO'!$D:$D, "<>") -> 0 | AF99: Yes | AG99: Yes
B100: 163 | F100: =COUNTIF(HCPs!W:W,HCO_Data!K100) -> 1 | G100: =IF(COUNTIF('Testing Referrals'!B:B,HCO_Data!K100)>0,"Yes","") | H100: =COUNTIF('HCO referrals'!B:B,HCO_Data!K100)+COUNTIF('HCO referrals'!C:C,HCO_Data!K100) -> 0 | I100: 30000087 | K100: ID00097 | L100: CH de Vichy | M100: BOULEVARD DENIERE | N100: 3201 | O100: VICHY | Q100: France | R100: 153 | S100: 108 | T100: 108 | V100: Yes | W100: =COUNTIFS('Clinical Trials HCO'!$A:$A, K100, 'Clinical Trials HCO'!$D:$D, "<>") -> 0 | AF100: Yes | AG100: Yes
...

Sheet Clinical Trials HCO
A1: HCO ID | B1: HCO name | C1: Location | D1: Clinical Trials_link | E1: Clinical Trials_name | F1: Clinical Trials_Sponsor | G1: KRAS mutation | H1: Metastatic | I1: Unreseclatble | J1: PDAC or Pancreatic Adenocarcinoma | K1: Pancreatic ductal adenocarcinoma | L1: Pancreatic adenocarcinoma | M1: Pancreatic Cancer
B2: filter | D2: filter | E2: filter | F2: filter | G2: filter | H2: filter | I2: filter | J2: filter | K2: filter | L2: filter | M2: filter
A3: ID00071 | B3: Institut Bergonié | C3: Institut Bergonnie, Bordeaux, 33076, France | D3: https://clinicaltrials.gov/study/NCT02602067 | E3: 131Iodine-Tenatumomab Treatment in Tenascin-C Positive Cancer Patients | F3: sigma-tau i.f.r. S.p.A.
A4: ID00029 | B4: Centre Léon Bérard | C4: Centre Leon Berard, Lyon, 69373, France | D4: https://clinicaltrials.gov/study/NCT02602067 | E4: 131Iodine-Tenatumomab Treatment in Tenascin-C Positive Cancer Patients | F4: sigma-tau i.f.r. S.p.A.
C5: Ambroise Pare Hospital, Boulogne-Billancourt, Haut de Seine, 92100, France | D5: https://clinicaltrials.gov/study/NCT04294589 | E5: Evaluation of NETs in Patients With Solid Cancers Associated With a High Risk of Venous Thromboembolic Events | F5: Assistance Publique - Hôpitaux de Paris | M5: Yes
C6: Ambroise Paré-Hartmann, Neuilly, 92200, France | D6: https://clinicaltrials.gov/study/NCT05059444 | E6: ORACLE: Observation of ResiduAl Cancer With Liquid Biopsy Evaluation | F6: Guardant Health, Inc. | L6: Yes
C7: American Hospital of Paris, Neuilly-sur-Seine, F-92202, France | D7: https://clinicaltrials.gov/study/NCT00010088 | E7: Chemotherapy in Treating Patients With Locally Advanced or Metastatic Cancer of the Pancreas or Bile Duct | F7: GERCOR - Multidisciplinary Oncology Cooperative Group | H7: Yes | M7: Yes
A8: ID00001 | B8: Hôpital Beaujon | C8: Hôpital Beaujon APHP, Clichy, France, 92110, France | D8: https://clinicaltrials.gov/study/NCT01485679 | E8: 18 Fluoro-deoxy-glucose Positrons Emission Tomography Combined With Computed Tomography (18-FDG TEP-CT ) in the Diagnosis of the Degeneration of Intraductal Papillary Mucinous Tumor of the Pancreas | F8: Nantes University Hospital
A9: ID00012 | B9: Hôpital Claude Huriez | C9: Hôpital C Huriez, Lille, France, 59037, France | D9: https://clinicaltrials.gov/study/NCT01485679 | E9: 18 Fluoro-deoxy-glucose Positrons Emission Tomography Combined With Computed Tomography (18-FDG TEP-CT ) in the Diagnosis of the Degeneration of Intraductal Papillary Mucinous Tumor of the Pancreas | F9: Nantes University Hospital
C10: American Hospital of Paris, Neuilly-sur-Seine, F-92202, France | D10: https://clinicaltrials.gov/study/NCT00006117 | E10: Gemcitabine and Oxaliplatin in Treating Patients With Locally Advanced or Metastatic Pancreatic Cancer | F10: GERCOR - Multidisciplinary Oncology Cooperative Group | H10: Yes | M10: Yes
A11: ID00011 | B11: Institut Paoli-Calmettes | C11: Institut Paoli Calmettes, Marseille, France, 13273, France | D11: https://clinicaltrials.gov/study/NCT01485679 | E11: 18 Fluoro-deoxy-glucose Positrons Emission Tomography Combined With Computed Tomography (18-FDG TEP-CT ) in the Diagnosis of the Degeneration of Intraductal Papillary Mucinous Tumor of the Pancreas | F11: Nantes University Hospital
C12: American Hospital of Paris, Neuilly-sur-Seine, F-92202, France | D12: https://clinicaltrials.gov/study/NCT00075452 | E12: Gemcitabine With or Without Oxaliplatin in Treating Patients With Locally Advanced or Metastatic Unresectable Pancreatic Adenocarcinoma | F12: GERCOR - Multidisciplinary Oncology Cooperative Group | H12: Yes | I12: Yes | L12: Yes | M12: Yes
C13: Angers, 49933, France | D13: https://clinicaltrials.gov/study/NCT00652366 | E13: A Dose-Escalation to Rash Study of Tarceva (Erlotinib) Plus Gemcitabine in Patients With Metastatic Pancreatic Cancer | F13: Hoffmann-La Roche | H13: Yes | M13: Yes
C14: Angers, Maine-et-Loire, 49933, France | D14: https://clinicaltrials.gov/study/NCT01395017 | E14: Dasatinib Added to Gemcitabine for Subjects With Locally-advanced Pancreatic Cancer | F14: Otsuka Pharmaceutical Development & Commercialization, Inc. | M14: Yes
A15: ID00002 | B15: Hôpital de Hautepierre | C15: Hôpital de Hautepierre, Strasbourg, France, 67098, France | D15: https://clinicaltrials.gov/study/NCT01485679 | E15: 18 Fluoro-deoxy-glucose Positrons Emission Tomography Combined With Computed Tomography (18-FDG TEP-CT ) in the Diagnosis of the Degeneration of Intraductal Papillary Mucinous Tumor of the Pancreas | F15: Nantes University Hospital
C16: AP-HM, Marseille, 13005, France | D16: https://clinicaltrials.gov/study/NCT03906331 | E16: Expanded Access for the Treatment of Cancers With Rearranged During Transfection (RET) Activation | F16: Eli Lilly and Company | M16: Yes
A17: ID00018 | B17: Hôpital de Rangueil | C17: CHU Rangueil, Toulouse, 31059, France | D17: https://clinicaltrials.gov/study/NCT01485679 | E17: 18 Fluoro-deoxy-glucose Positrons Emission Tomography Combined With Computed Tomography (18-FDG TEP-CT ) in the Diagnosis of the Degeneration of Intraductal Papillary Mucinous Tumor of the Pancreas | F17: Nantes University Hospital
C18: APHM, Marseille, France | D18: https://clinicaltrials.gov/study/NCT05470738 | E18: PAncreas Borderline and Locally Advanced Snapshot Study | F18: University Hospital, Clermont-Ferrand | L18: Yes | M18: Yes
A19: ID00067 | B19: Hôpital Tenon | C19: APHP Tenon Hospital - Sorbonne, Paris, 75020, France | D19: https://clinicaltrials.gov/study/NCT05059444 | E19: ORACLE: Observation of ResiduAl Cancer With Liquid Biopsy Evaluation | F19: Guardant Health, Inc. | L19: Yes
A20: ID00012 | B20: Hôpital Claude Huriez | C20: Hopital Claude Huriez, Lille, Hauts-de-France, 59037, France | D20: https://clinicaltrials.gov/study/NCT03678883 | E20: 9-ING-41 in Patients With Advanced Cancers | F20: Actuate Therapeutics Inc. | L20: Yes | M20: Yes
C21: Assistance Publique - Hopitaux de Marseille (Ap-Hm, Marseille, 13009, France | D21: https://clinicaltrials.gov/study/NCT06177327 | E21: Hepato-pancreato-biliary Abnormalities in Fibrous Dysplasia of Bone/McCune Albright Syndrome | F21: Hospices Civils de Lyon
A22: ID00071 | B22: Institut Bergonié | C22: Institut Bergonie, Bordeaux, New Aquitaine, 33076, France | D22: https://clinicaltrials.gov/study/NCT03678883 | E22: 9-ING-41 in Patients With Advanced Cancers | F22: Actuate Therapeutics Inc. | L22: Yes | M22: Yes
C23: Assistance Publique - Hopitaux de Paris (Ap-Hp), Paris, 75010, France | D23: https://clinicaltrials.gov/study/NCT06177327 | E23: Hepato-pancreato-biliary Abnormalities in Fibrous Dysplasia of Bone/McCune Albright Syndrome | F23: Hospices Civils de Lyon
A24: ID00032 | B24: Hôpital de la Timone Adulte | C24: Hopital de la Timone, Marseille, 13005, France | D24: https://clinicaltrials.gov/study/NCT03678883 | E24: 9-ING-41 in Patients With Advanced Cancers | F24: Actuate Therapeutics Inc. | L24: Yes | M24: Yes
C25: Assistance Publique des Hôpitaux de Marseille, Marseille, 13000, France | D25: https://clinicaltrials.gov/study/NCT00789633 | E25: Masitinib in Combination With Gemcitabine for Treatment of Patients With Advanced/Metastatic Pancreatic Cancer | F25: AB Science | H25: Yes | M25: Yes
A26: ID00079 | B26: Centre Antoine Lacassagne | C26: Centre Antoine Lacassagne, Nice, Cedex 02, 06189, France | D26: https://clinicaltrials.gov/study/NCT00428220 | E26: A Continuation Study Using Sunitinib Malate For Patients Leaving Treatment On A Previous Sunitinib Study. | F26: Pfizer | H26: Yes
A27: ID00001 | B27: Hôpital Beaujon | C27: Hopital Beaujon, Clichy, Cedex, 92118, France | D27: https://clinicaltrials.gov/study/NCT00428220 | E27: A Continuation Study Using Sunitinib Malate For Patients Leaving Treatment On A Previous Sunitinib Study. | F27: Pfizer | H27: Yes
A28: ID00009 | B28: Hôpital Cochin | C28: Groupe Hospitalier Cochin, Cancer Quest AP-HP, Paris, Cedex, 75679, France | D28: https://clinicaltrials.gov/study/NCT00428220 | E28: A Continuation Study Using Sunitinib Malate For Patients Leaving Treatment On A Previous Sunitinib Study. | F28: Pfizer | H28: Yes
C29: Assistance Publique des Hôpitaux de Marseille, Marseille, Bouches du Rhône, 13385, France | D29: https://clinicaltrials.gov/study/NCT02858141 | E29: Onco-geriatric Database of Patients With Pancreatic Cancer | F29: Institut Paoli-Calmettes | M29: Yes
C30: Assistance Publique Hôpitaux de Marseille | D30: =_xlfn.XLOOKUP(E30,HCP_evidence!H:H,HCP_evidence!I:I) -> #N/A | E30: A multicenter, open-label, non-randomized, Phase 1/2 study to evaluate the safety, tolerability, and imaging characteristics of [68Ga]Ga-DPI-4452 and to evaluate the safety, tolerability, and efficacy of [177Lu]Lu-DPI-4452 in patients with locally advanced or unresectable metastatic solid tumors. | G30: {=_xlfn.XLOOKUP(E30,HCP_evidence!H:H,IF(HCP_evidence!M:M="Yes","Yes",""))} -> #N/A | H30: {=_xlfn.XLOOKUP(E30,HCP_evidence!H:H,IF(HCP_evidence!K:K="Yes","Yes",""))} -> #N/A | I30: {=_xlfn.XLOOKUP(E30,HCP_evidence!H:H,IF(HCP_evidence!J:J="Yes","Yes",""))} -> #N/A | J30: =IF(OR(K30="Yes",L30="Yes"),"Yes","") -> #REF! | K30: {=_xlfn.XLOOKUP(E30,HCP_evidence!H:H,IF(HCP_evidence!#REF!="Yes","Yes",""))} -> #REF! | L30: {=_xlfn.XLOOKUP(E30,HCP_evidence!H:H,IF(HCP_evidence!#REF!="Yes","Yes",""))} -> #REF! | M30: {=_xlfn.XLOOKUP(E30,HCP_evidence!H:H,IF(HCP_evidence!N:N="Yes","Yes",""))} -> #N/A
A31: ID00049 | B31: Centre Jean Perrin | C31: Centre Jean Perrin, Clermont-Ferrand, 63011, France | D31: https://clinicaltrials.gov/study/NCT00428220 | E31: A Continuation Study Using Sunitinib Malate For Patients Leaving Treatment On A Previous Sunitinib Study. | F31: Pfizer | H31: Yes
C32: Assistance Publique Hôpitaux de Marseille | D32: =_xlfn.XLOOKUP(E32,HCP_evidence!H:H,HCP_evidence!I:I) -> #N/A | E32: A Phase I, Open-Label, Multicenter Study to Evaluate the Safety, Tolerability, Dosimetry, and Preliminary Activity of [177Lu]Lu-DFC413, and the Safety and Imaging Properties of [68Ga]Ga-NNS309 in Patients With Solid Tumors | G32: {=_xlfn.XLOOKUP(E32,HCP_evidence!H:H,IF(HCP_evidence!M:M="Yes","Yes",""))} -> #N/A | H32: {=_xlfn.XLOOKUP(E32,HCP_evidence!H:H,IF(HCP_evidence!K:K="Yes","Yes",""))} -> #N/A | I32: {=_xlfn.XLOOKUP(E32,HCP_evidence!H:H,IF(HCP_evidence!J:J="Yes","Yes",""))} -> #N/A | J32: =IF(OR(K32="Yes",L32="Yes"),"Yes","") -> #REF! | K32: {=_xlfn.XLOOKUP(E32,HCP_evidence!H:H,IF(HCP_evidence!#REF!="Yes","Yes",""))} -> #REF! | L32: {=_xlfn.XLOOKUP(E32,HCP_evidence!H:H,IF(HCP_evidence!#REF!="Yes","Yes",""))} -> #REF! | M32: {=_xlfn.XLOOKUP(E32,HCP_evidence!H:H,IF(HCP_evidence!N:N="Yes","Yes",""))} -> #N/A
A33: ID00046 | B33: Centre Oscar Lambret | C33: Centre Oscar Lambret, Lille, 59020, France | D33: https://clinicaltrials.gov/study/NCT00428220 | E33: A Continuation Study Using Sunitinib Malate For Patients Leaving Treatment On A Previous Sunitinib Study. | F33: Pfizer | H33: Yes
A34: ID00029 | B34: Centre Léon Bérard | C34: Centre Leon Berard, Lyon, 69008, France | D34: https://clinicaltrials.gov/study/NCT00428220 | E34: A Continuation Study Using Sunitinib Malate For Patients Leaving Treatment On A Previous Sunitinib Study. | F34: Pfizer | H34: Yes
A35: ID00013 | B35: Hôpital Édouard Herriot | C35: Hopital Edouard Herriot, Lyon, 69437, France | D35: https://clinicaltrials.gov/study/NCT00428220 | E35: A Continuation Study Using Sunitinib Malate For Patients Leaving Treatment On A Previous Sunitinib Study. | F35: Pfizer | H35: Yes
A36: ID00032 | B36: Hôpital de la Timone Adulte | C36: Chu La Timone, Marseille, 13385, France | D36: https://clinicaltrials.gov/study/NCT00428220 | E36: A Continuation Study Using Sunitinib Malate For Patients Leaving Treatment On A Previous Sunitinib Study. | F36: Pfizer | H36: Yes
C37: Assistance Publique Hopitaux de Marseille Hopitaux Sud, Marseille, 13274, France | D37: https://clinicaltrials.gov/study/NCT00010088 | E37: Chemotherapy in Treating Patients With Locally Advanced or Metastatic Cancer of the Pancreas or Bile Duct | F37: GERCOR - Multidisciplinary Oncology Cooperative Group | H37: Yes | M37: Yes
C38: Assistance Publique Hopitaux de Marseille, Marseille, 13005, France | D38: https://clinicaltrials.gov/study/NCT02150408 | E38: Evaluation of PET-CT Using Somatostatin Agonists Labeled With Gallium68 in Neuroendocrine Tumors | F38: Assistance Publique Hopitaux De Marseille
C39: Aurélien DUPRE, Lyon, 69008, France | D39: https://clinicaltrials.gov/study/NCT07144917 | E39: Immunoparalysis After Pancreaticoduodenectomy | F39: Hospices Civils de Lyon | K39: Yes | L39: Yes
C40: Barthet, Marseille, 13000, France | D40: https://clinicaltrials.gov/study/NCT02330497 | E40: Efficacy and Safety of Radiofrequency Ablation in Pancreatic Neuroendocrine and Cystic Tumor | F40: Société Française d'Endoscopie Digestive | I40: Yes
C41: Besançon University Hospital Center | D41: =_xlfn.XLOOKUP(E41,HCP_evidence!H:H,HCP_evidence!I:I) -> https://www.sante.fr/essais-cliniques/2023-508356-19-00/etude-de-phase-ii-multicentrique-ouverte-randomisee-a-trois-bras-visant-a-evaluer-l-efficacite-et-la-securite-d-emploi-du-ttx-030-associe-a-une-chimiotherapie-avec-ou-sans-budigalimab-par-rapport-a-la-chimiotherapie-seule-dans-le-traitement-de-patients-n-ayant-jamais-recu-de-traitement-contre-un-adenocarcinome-pancreatique-metastatique | E41: A Phase II, Multicenter, Open-Label, Three-Arm Randomized Study to Evaluate the Efficacy and Safety of TTX-030 in Combination with Chemotherapy, With or Without Budigalimab, Compared to Chemotherapy Alone, in the Treatment of Treatment-Naïve Patients for Metastatic Pancreatic Adenocarcinoma | G41: {=_xlfn.XLOOKUP(E41,HCP_evidence!H:H,IF(HCP_evidence!M:M="Yes","Yes",""))} | H41: {=_xlfn.XLOOKUP(E41,HCP_evidence!H:H,IF(HCP_evidence!K:K="Yes","Yes",""))} -> Yes | I41: {=_xlfn.XLOOKUP(E41,HCP_evidence!H:H,IF(HCP_evidence!J:J="Yes","Yes",""))} | J41: =IF(OR(K41="Yes",L41="Yes"),"Yes","") -> #REF! | K41: {=_xlfn.XLOOKUP(E41,HCP_evidence!H:H,IF(HCP_evidence!#REF!="Yes","Yes",""))} -> #REF! | L41: {=_xlfn.XLOOKUP(E41,HCP_evidence!H:H,IF(HCP_evidence!#REF!="Yes","Yes",""))} -> #REF! | M41: {=_xlfn.XLOOKUP(E41,HCP_evidence!H:H,IF(HCP_evidence!N:N="Yes","Yes",""))}
C42: Besançon University Hospital Center | D42: =_xlfn.XLOOKUP(E42,HCP_evidence!H:H,HCP_evidence!I:I) -> #N/A | E42: C5721001 - Phase II Open-label Study of Tisotumab Vedotin in the Treatment of Locally Advanced or Metastatic Solid Tumors | G42: {=_xlfn.XLOOKUP(E42,HCP_evidence!H:H,IF(HCP_evidence!M:M="Yes","Yes",""))} -> #N/A | H42: {=_xlfn.XLOOKUP(E42,HCP_evidence!H:H,IF(HCP_evidence!K:K="Yes","Yes",""))} -> #N/A | I42: {=_xlfn.XLOOKUP(E42,HCP_evidence!H:H,IF(HCP_evidence!J:J="Yes","Yes",""))} -> #N/A | J42: =IF(OR(K42="Yes",L42="Yes"),"Yes","") -> #REF! | K42: {=_xlfn.XLOOKUP(E42,HCP_evidence!H:H,IF(HCP_evidence!#REF!="Yes","Yes",""))} -> #REF! | L42: {=_xlfn.XLOOKUP(E42,HCP_evidence!H:H,IF(HCP_evidence!#REF!="Yes","Yes",""))} -> #REF! | M42: {=_xlfn.XLOOKUP(E42,HCP_evidence!H:H,IF(HCP_evidence!N:N="Yes","Yes",""))} -> #N/A
C43: Besançon University Hospital Center | D43: =_xlfn.XLOOKUP(E43,HCP_evidence!H:H,HCP_evidence!I:I) -> https://www.sante.fr/essais-cliniques/2023-505889-29-01/essai-de-phase-ii-evaluant-l-efficacite-et-la-securite-du-traitement-par-folfirinox3-chez-des-patients-atteints-d-un-cancer-du-pancreas-localement-avance-ou-metastatique-inoperable-en-premiere-ligne-de-chimiotherapie | E43: Phase II trial evaluating the efficacy and safety of FOLFIRINOX3 therapy in patients with inoperable locally advanced or metastatic pancreatic cancer in first-line chemotherapy. | G43: {=_xlfn.XLOOKUP(E43,HCP_evidence!H:H,IF(HCP_evidence!M:M="Yes","Yes",""))} | H43: {=_xlfn.XLOOKUP(E43,HCP_evidence!H:H,IF(HCP_evidence!K:K="Yes","Yes",""))} -> Yes | I43: {=_xlfn.XLOOKUP(E43,HCP_evidence!H:H,IF(HCP_evidence!J:J="Yes","Yes",""))} -> Yes | J43: =IF(OR(K43="Yes",L43="Yes"),"Yes","") -> #REF! | K43: {=_xlfn.XLOOKUP(E43,HCP_evidence!H:H,IF(HCP_evidence!#REF!="Yes","Yes",""))} -> #REF! | L43: {=_xlfn.XLOOKUP(E43,HCP_evidence!H:H,IF(HCP_evidence!#REF!="Yes","Yes",""))} -> #REF! | M43: {=_xlfn.XLOOKUP(E43,HCP_evidence!H:H,IF(HCP_evidence!N:N="Yes","Yes",""))} -> Yes
C44: Besançon, 25030, France | D44: https://clinicaltrials.gov/study/NCT00652366 | E44: A Dose-Escalation to Rash Study of Tarceva (Erlotinib) Plus Gemcitabine in Patients With Metastatic Pancreatic Cancer | F44: Hoffmann-La Roche | H44: Yes | M44: Yes
C45: Besançon, 25030, France | D45: https://clinicaltrials.gov/study/NCT01214720 | E45: A Study of Avastin (Bevacizumab) Added to a Chemotherapeutic Regimen in Patients With Metastatic Pancreatic Cancer | F45: Hoffmann-La Roche | H45: Yes | M45: Yes
A46: ID00053 | B46: Centre Georges-François Leclerc | C46: Centr Georges François Leclerc | D46: =_xlfn.XLOOKUP(E46,HCP_evidence!H:H,HCP_evidence!I:I) -> #N/A | E46: A multicenter, open-label, non-randomized, Phase 1/2 study to evaluate the safety, tolerability, and imaging characteristics of [68Ga]Ga-DPI-4452 and to evaluate the safety, tolerability, and efficacy of [177Lu]Lu-DPI-4452 in patients with locally advanced or unresectable metastatic solid tumors. | G46: {=_xlfn.XLOOKUP(E46,HCP_evidence!H:H,IF(HCP_evidence!M:M="Yes","Yes",""))} -> #N/A | H46: {=_xlfn.XLOOKUP(E46,HCP_evidence!H:H,IF(HCP_evidence!K:K="Yes","Yes",""))} -> #N/A | I46: {=_xlfn.XLOOKUP(E46,HCP_evidence!H:H,IF(HCP_evidence!J:J="Yes","Yes",""))} -> #N/A | J46: =IF(OR(K46="Yes",L46="Yes"),"Yes","") -> #REF! | K46: {=_xlfn.XLOOKUP(E46,HCP_evidence!H:H,IF(HCP_evidence!#REF!="Yes","Yes",""))} -> #REF! | L46: {=_xlfn.XLOOKUP(E46,HCP_evidence!H:H,IF(HCP_evidence!#REF!="Yes","Yes",""))} -> #REF! | M46: {=_xlfn.XLOOKUP(E46,HCP_evidence!H:H,IF(HCP_evidence!N:N="Yes","Yes",""))} -> #N/A
C47: Besançon, 25030, France | D47: https://clinicaltrials.gov/study/NCT01395017 | E47: Dasatinib Added to Gemcitabine for Subjects With Locally-advanced Pancreatic Cancer | F47: Otsuka Pharmaceutical Development & Commercialization, Inc. | M47: Yes
A48: ID00033 | B48: CH de Béthune | C48: Béthune hospital center, Béthune, 62408, France | D48: https://clinicaltrials.gov/study/NCT06128343 | E48: Anatomical-Clinical Base of Adenocarcinoma Pancreatic | F48: University Hospital, Toulouse | L48: Yes
A49: ID00011 | B49: Institut Paoli-Calmettes | C49: Institut Paoli Calmettes, Marseille, France | D49: https://clinicaltrials.gov/study/NCT05143970 | E49: A Phase 1 First-In-Human Study of the Anti-CD73 IPH5301 Alone or in Combination With Chemotherapy and Trastuzumab in Patients With Advanced Solid Tumors | F49: Institut Paoli-Calmettes | H49: Yes | M49: Yes
A50: ID00053 | B50: Centre Georges-François Leclerc | C50: Centre Georges Francois Leclerc, Dijon, 21079, France | D50: https://clinicaltrials.gov/study/NCT01478685 | E50: A Phase 1 Study of CC-486 as a Single Agent and in Combination With Carboplatin or ABI-007 in Subjects With Relapsed or Refractory Solid Tumors | F50: Celgene
A51: ID00043 | B51: Institut Curie | C51: Institut Curie, Paris, 75005, France | D51: https://clinicaltrials.gov/study/NCT01478685 | E51: A Phase 1 Study of CC-486 as a Single Agent and in Combination With Carboplatin or ABI-007 in Subjects With Relapsed or Refractory Solid Tumors | F51: Celgene
C52: Bezier Ch, Béziers, 34525, France | D52: https://clinicaltrials.gov/study/NCT02352337 | E52: First-line Metastatic Pancreatic Cancer : FOLFIRINOX +/- LV5FU2 in Maintenance Versus Firgem | F52: Federation Francophone de Cancerologie Digestive | H52: Yes | L52: Yes | M52: Yes
A53: ID00043 | B53: Institut Curie | C53: Institut Curie | D53: =_xlfn.XLOOKUP(E53,HCP_evidence!H:H,HCP_evidence!I:I) -> https://www.sante.fr/essais-cliniques/2022-501854-12-01/a-phase-1b-study-to-evaluate-the-safety-tolerability-and-preliminary-efficacy-of-a-heterologous-prime-boost-vaccination-atp150-atp152-atp162-vsv-gp154-and-ezabenlimab-bi-754091-in-patients-with-pancreatic-ductal-adenocarcinoma | E53: A Phase 1b Study to Evaluate the Safety, Tolerability and Preliminary Efficacy of a Heterologous Prime Boost Vaccination (ATP150/ATP152/ATP162, VSV-GP154 and Ezabenlimab (BI 754091) in Patients with Pancreatic Ductal Adenocarcinoma | G53: {=_xlfn.XLOOKUP(E53,HCP_evidence!H:H,IF(HCP_evidence!M:M="Yes","Yes",""))} -> Yes | H53: {=_xlfn.XLOOKUP(E53,HCP_evidence!H:H,IF(HCP_evidence!K:K="Yes","Yes",""))} -> Yes | I53: {=_xlfn.XLOOKUP(E53,HCP_evidence!H:H,IF(HCP_evidence!J:J="Yes","Yes",""))} -> Yes | J53: =IF(OR(K53="Yes",L53="Yes"),"Yes","") -> #REF! | K53: {=_xlfn.XLOOKUP(E53,HCP_evidence!H:H,IF(HCP_evidence!#REF!="Yes","Yes",""))} -> #REF! | L53: {=_xlfn.XLOOKUP(E53,HCP_evidence!H:H,IF(HCP_evidence!#REF!="Yes","Yes",""))} -> #REF! | M53: {=_xlfn.XLOOKUP(E53,HCP_evidence!H:H,IF(HCP_evidence!N:N="Yes","Yes",""))}
C54: Blanc-Bisson Christele, Bordeaux, 33076, France | D54: https://clinicaltrials.gov/study/NCT06118125 | E54: Delay to Diagnosis in Digestive Cancerology by the General Practitioner Related to Covid-19 Pandemic Confinement | F54: University of Bordeaux
C55: Bordeaux, 33000, France | D55: https://clinicaltrials.gov/study/NCT01214720 | E55: A Study of Avastin (Bevacizumab) Added to a Chemotherapeutic Regimen in Patients With Metastatic Pancreatic Cancer | F55: Hoffmann-La Roche | H55: Yes | M55: Yes
C56: Bordeaux, France | D56: https://clinicaltrials.gov/study/NCT02119663 | E56: A Study of Ruxolitinib in Pancreatic Cancer Patients | F56: Incyte Corporation | H56: Yes | M56: Yes
C57: Bordeaux, France | D57: https://clinicaltrials.gov/study/NCT01494506 | E57: Study of MM-398 With or Without 5-FU/LV, Versus 5-FU/LV in Patients With Metastatic Pancreatic Cancer | F57: Merrimack Pharmaceuticals | H57: Yes | M57: Yes
C58: Boulogne-Billancourt, 92104, France | D58: https://clinicaltrials.gov/study/NCT01214720 | E58: A Study of Avastin (Bevacizumab) Added to a Chemotherapeutic Regimen in Patients With Metastatic Pancreatic Cancer | F58: Hoffmann-La Roche | H58: Yes | M58: Yes
A59: ID00055 | B59: Hôpital Morvan | C59: Brest Hopital Augustin Morvan, Institut de Cancero-Hemato, Brest, Brest Cedex, 29609, France | D59: https://clinicaltrials.gov/study/NCT02246127 | E59: Sequentiality of Everolimus and STZ-5FU in Advanced Pancreatic Neuroendocrine Tumor | F59: Grupo Espanol de Tumores Neuroendocrinos
A60: ID00005 | B60: HU Pitié-Salpêtrière | C60: Hôpital Universitaire Pitié Salpêtrière (Adults only), Paris, Île-de-France Region, 75651, France | D60: https://clinicaltrials.gov/study/NCT03394365 | E60: A Phase 3 Study of Tabelecleucel for Participants With Epstein-Barr Virus-Associated Post-Transplant Lymphoproliferative Disease After Failure With Rituximab or Rituximab and Chemotherapy | F60: Pierre Fabre Medicament
C61: Brest, 29609, France | D61: https://clinicaltrials.gov/study/NCT00652366 | E61: A Dose-Escalation to Rash Study of Tarceva (Erlotinib) Plus Gemcitabine in Patients With Metastatic Pancreatic Cancer | F61: Hoffmann-La Roche | H61: Yes | M61: Yes
C62: Brest, France | D62: https://clinicaltrials.gov/study/NCT02119663 | E62: A Study of Ruxolitinib in Pancreatic Cancer Patients | F62: Incyte Corporation | H62: Yes | M62: Yes
C63: C. H. De Saumur, Saumur, 49403, France | D63: https://clinicaltrials.gov/study/NCT00075452 | E63: Gemcitabine With or Without Oxaliplatin in Treating Patients With Locally Advanced or Metastatic Unresectable Pancreatic Adenocarcinoma | F63: GERCOR - Multidisciplinary Oncology Cooperative Group | H63: Yes | I63: Yes | L63: Yes | M63: Yes
C64: C. H. Du Mans, Le Mans, 72037, France | D64: https://clinicaltrials.gov/study/NCT00075452 | E64: Gemcitabine With or Without Oxaliplatin in Treating Patients With Locally Advanced or Metastatic Unresectable Pancreatic Adenocarcinoma | F64: GERCOR - Multidisciplinary Oncology Cooperative Group | H64: Yes | I64: Yes | L64: Yes | M64: Yes
C65: C.H. Bourg En Bresse, Bourg-en-Bresse, 01012, France | D65: https://clinicaltrials.gov/study/NCT00303758 | E65: Combination Chemotherapy in Treating Patients With Metastatic Pancreatic Cancer That Cannot Be Removed By Surgery | F65: Federation Francophone de Cancerologie Digestive | H65: Yes | M65: Yes
C66: C.H. Senlis, Senlis, 60300, France | D66: https://clinicaltrials.gov/study/NCT00010088 | E66: Chemotherapy in Treating Patients With Locally Advanced or Metastatic Cancer of the Pancreas or Bile Duct | F66: GERCOR - Multidisciplinary Oncology Cooperative Group | H66: Yes | M66: Yes
C67: C.H. Senlis, Senlis, 60309, France | D67: https://clinicaltrials.gov/study/NCT00010062 | E67: Fluorouracil Plus Radiation Therapy Following Surgery in Treating Patients With Pancreatic Cancer | F67: GERCOR - Multidisciplinary Oncology Cooperative Group | M67: Yes
C68: C.H. Senlis, Senlis, 60309, France | D68: https://clinicaltrials.gov/study/NCT00268411 | E68: Gemcitabine and Oxaliplatin in Treating Patients With Metastatic Pancreatic Cancer | F68: GERCOR - Multidisciplinary Oncology Cooperative Group | H68: Yes | M68: Yes
A69: ID00053 | B69: Centre Georges-François Leclerc | C69: Centr Georges François Leclerc | D69: =_xlfn.XLOOKUP(E69,HCP_evidence!H:H,HCP_evidence!I:I) -> #N/A | E69: A Phase I, Open-Label, Multicenter Study to Evaluate the Safety, Tolerability, Dosimetry, and Preliminary Activity of [177Lu]Lu-DFC413, and the Safety and Imaging Properties of [68Ga]Ga-NNS309 in Patients With Solid Tumors | G69: {=_xlfn.XLOOKUP(E69,HCP_evidence!H:H,IF(HCP_evidence!M:M="Yes","Yes",""))} -> #N/A | H69: {=_xlfn.XLOOKUP(E69,HCP_evidence!H:H,IF(HCP_evidence!K:K="Yes","Yes",""))} -> #N/A | I69: {=_xlfn.XLOOKUP(E69,HCP_evidence!H:H,IF(HCP_evidence!J:J="Yes","Yes",""))} -> #N/A | J69: =IF(OR(K69="Yes",L69="Yes"),"Yes","") -> #REF! | K69: {=_xlfn.XLOOKUP(E69,HCP_evidence!H:H,IF(HCP_evidence!#REF!="Yes","Yes",""))} -> #REF! | L69: {=_xlfn.XLOOKUP(E69,HCP_evidence!H:H,IF(HCP_evidence!#REF!="Yes","Yes",""))} -> #REF! | M69: {=_xlfn.XLOOKUP(E69,HCP_evidence!H:H,IF(HCP_evidence!N:N="Yes","Yes",""))} -> #N/A
C70: C.H. Senlis, Senlis, 60309, France | D70: https://clinicaltrials.gov/study/NCT00075452 | E70: Gemcitabine With or Without Oxaliplatin in Treating Patients With Locally Advanced or Metastatic Unresectable Pancreatic Adenocarcinoma | F70: GERCOR - Multidisciplinary Oncology Cooperative Group | H70: Yes | I70: Yes | L70: Yes | M70: Yes
C71: C.H.G. Beauvais, Beauvais, 60021, France | D71: https://clinicaltrials.gov/study/NCT00010088 | E71: Chemotherapy in Treating Patients With Locally Advanced or Metastatic Cancer of the Pancreas or Bile Duct | F71: GERCOR - Multidisciplinary Oncology Cooperative Group | H71: Yes | M71: Yes
A72: ID00053 | B72: Centre Georges-François Leclerc | C72: Centr Georges François Leclerc | D72: =_xlfn.XLOOKUP(E72,HCP_evidence!H:H,HCP_evidence!I:I) -> https://www.sante.fr/essais-cliniques/2023-508356-19-00/etude-de-phase-ii-multicentrique-ouverte-randomisee-a-trois-bras-visant-a-evaluer-l-efficacite-et-la-securite-d-emploi-du-ttx-030-associe-a-une-chimiotherapie-avec-ou-sans-budigalimab-par-rapport-a-la-chimiotherapie-seule-dans-le-traitement-de-patients-n-ayant-jamais-recu-de-traitement-contre-un-adenocarcinome-pancreatique-metastatique | E72: A Phase II, Multicenter, Open-Label, Three-Arm Randomized Study to Evaluate the Efficacy and Safety of TTX-030 in Combination with Chemotherapy, With or Without Budigalimab, Compared to Chemotherapy Alone, in the Treatment of Treatment-Naïve Patients for Metastatic Pancreatic Adenocarcinoma | G72: {=_xlfn.XLOOKUP(E72,HCP_evidence!H:H,IF(HCP_evidence!M:M="Yes","Yes",""))} | H72: {=_xlfn.XLOOKUP(E72,HCP_evidence!H:H,IF(HCP_evidence!K:K="Yes","Yes",""))} -> Yes | I72: {=_xlfn.XLOOKUP(E72,HCP_evidence!H:H,IF(HCP_evidence!J:J="Yes","Yes",""))} | J72: =IF(OR(K72="Yes",L72="Yes"),"Yes","") -> #REF! | K72: {=_xlfn.XLOOKUP(E72,HCP_evidence!H:H,IF(HCP_evidence!#REF!="Yes","Yes",""))} -> #REF! | L72: {=_xlfn.XLOOKUP(E72,HCP_evidence!H:H,IF(HCP_evidence!#REF!="Yes","Yes",""))} -> #REF! | M72: {=_xlfn.XLOOKUP(E72,HCP_evidence!H:H,IF(HCP_evidence!N:N="Yes","Yes",""))}
C73: C.H.G. Beauvais, Beauvais, 60021, France | D73: https://clinicaltrials.gov/study/NCT00268411 | E73: Gemcitabine and Oxaliplatin in Treating Patients With Metastatic Pancreatic Cancer | F73: GERCOR - Multidisciplinary Oncology Cooperative Group | H73: Yes | M73: Yes
C74: C.H.G. Beauvais, Beauvais, 60021, France | D74: https://clinicaltrials.gov/study/NCT00064207 | E74: Gemcitabine and Radiation Therapy Compared With Gemcitabine Alone in Treating Patients Who Have Undergone Surgery for Pancreatic Cancer | F74: European Organisation for Research and Treatment of Cancer - EORTC | M74: Yes
C75: C.H.G. Beauvais, Beauvais, 60021, France | D75: https://clinicaltrials.gov/study/NCT00075452 | E75: Gemcitabine With or Without Oxaliplatin in Treating Patients With Locally Advanced or Metastatic Unresectable Pancreatic Adenocarcinoma | F75: GERCOR - Multidisciplinary Oncology Cooperative Group | H75: Yes | I75: Yes | L75: Yes | M75: Yes
A76: ID00028 | B76: CH de Pau | C76: C.H.G. De Pau, Pau, 64000, France | D76: https://clinicaltrials.gov/study/NCT00064207 | E76: Gemcitabine and Radiation Therapy Compared With Gemcitabine Alone in Treating Patients Who Have Undergone Surgery for Pancreatic Cancer | F76: European Organisation for Research and Treatment of Cancer - EORTC | M76: Yes
C77: C.H.U. de Nimes - Groupe Hospitals-Universitaire Caremeau, Nîmes, 30029, France | D77: https://clinicaltrials.gov/study/NCT00064207 | E77: Gemcitabine and Radiation Therapy Compared With Gemcitabine Alone in Treating Patients Who Have Undergone Surgery for Pancreatic Cancer | F77: European Organisation for Research and Treatment of Cancer - EORTC | M77: Yes
C78: C.H.U. de Nimes - Groupe Hospitals-Universitaire Caremeau, Nîmes, 30029, France | D78: https://clinicaltrials.gov/study/NCT00634725 | E78: Gemcitabine With or Without Capecitabine and/or Radiation Therapy or Gemcitabine With or Without Erlotinib in Treating Patients With Locally Advanced Pancreatic Cancer That Cannot Be Removed by Surgery | F78: GERCOR - Multidisciplinary Oncology Cooperative Group | M78: Yes
C79: C.H.U. Poitiers, Poitiers, 86000, France | D79: https://clinicaltrials.gov/study/NCT07236177 | E79: B-GLUCANCER2 : A Pilot Study Evaluating a New Method for Cancer Detection by Measuring the Activity of Different Glycosidase Enzymes in the Plasma of Patients With a Localized Cancer. | F79: Poitiers University Hospital | M79: Yes
A80: ID00071 | B80: Institut Bergonié | C80: Institut Bergonié, Bordeaux, 33076, France | D80: https://clinicaltrials.gov/study/NCT02539537 | E80: A Randomized Phase III Trial Comparing Folfirinox to Gemcitabine in Locally Advanced Pancreatic Carcinoma | F80: UNICANCER | M80: Yes
C81: Cabinet Medical, Challes-les-Eaux, 73190, France | D81: https://clinicaltrials.gov/study/NCT02264665 | E81: OPALINE : A Study Of Morbidity And Mortality At 2 Years | F81: Pfizer | H81: Yes | I81: Yes
C82: Cabinet Medical, Vannes, 56000, France | D82: https://clinicaltrials.gov/study/NCT02264665 | E82: OPALINE : A Study Of Morbidity And Mortality At 2 Years | F82: Pfizer | H82: Yes | I82: Yes
C83: Caen, France | D83: https://clinicaltrials.gov/study/NCT00841191 | E83: A Safety, Efficacy and Pharmacokinetic Study of Siltuximab (CNTO 328) in Participants With Solid Tumors | F83: Centocor, Inc. | G83: Yes
A84: ID00026 | B84: ICM Montpellier | C84: Cancer Institute of Montpellier, Montpellier, 34298, France | D84: https://clinicaltrials.gov/study/NCT06128551 | E84: Study of Elironrasib and Daraxonrasib as Monotherapies and Combination Therapy in Participants With Advanced KRAS G12C Mutant Solid Tumors | F84: Revolution Medicines, Inc. | G84: Yes | K84: Yes
A85: ID00051 | B85: CHRU Jean Minjoz | C85: Center Hospitalier Regional Universitaire de Besancon - Site Jean Minjoz, Besançon, Bourgogne-Franche-Comté, 25030, France | D85: https://clinicaltrials.gov/study/NCT03678883 | E85: 9-ING-41 in Patients With Advanced Cancers | F85: Actuate Therapeutics Inc. | L85: Yes | M85: Yes
C86: Center Hospitalier Universitaire d' Angers, Angers, 49033, France | D86: https://clinicaltrials.gov/study/NCT01964430 | E86: Nab-paclitaxel and Gemcitabine vs Gemcitabine Alone as Adjuvant Therapy for Patients With Resected Pancreatic Cancer (the "Apact" Study) | F86: Celgene | M86: Yes
C87: Center Hospitalier Universitaire d' Angers, Angers, 49100, France | D87: https://clinicaltrials.gov/study/NCT04389632 | E87: A Study of Sigvotatug Vedotin in Advanced Solid Tumors | F87: Seagen, a wholly owned subsidiary of Pfizer | L87: Yes
C88: Centre Alexis Vautrin, Vandœuvre-lès-Nancy, 54511, France | D88: https://clinicaltrials.gov/study/NCT00112658 | E88: Combination Chemotherapy as First-Line Therapy in Treating Patients With Metastatic Pancreatic Cancer | F88: UNICANCER | H88: Yes | M88: Yes
C89: Centre Alexis Vautrin, Vandœuvre-lès-Nancy, 54511, France | D89: https://clinicaltrials.gov/study/NCT01689584 | E89: COsegregation of VARiants in Panel of Genes | F89: Institut Curie
A90: ID00046 | B90: Centre Oscar Lambret | C90: Centre Oscar Lambret, Lille, 59020, France | D90: https://clinicaltrials.gov/study/NCT02539537 | E90: A Randomized Phase III Trial Comparing Folfirinox to Gemcitabine in Locally Advanced Pancreatic Carcinoma | F90: UNICANCER | M90: Yes
C91: Centre Alexis Vautrin, Vandœuvre-lès-Nancy, 54511, France | D91: https://clinicaltrials.gov/study/NCT00004884 | E91: Docetaxel and Gemcitabine Compared With Docetaxel and Cisplatin in Treating Patients With Metastatic or Locally Advanced Pancreatic Cancer | F91: European Organisation for Research and Treatment of Cancer - EORTC | H91: Yes | M91: Yes
A92: ID00013 | B92: Hôpital Édouard Herriot | C92: Hôpital Edouard Herriot - Lyon, Lyon, 69437, France | D92: https://clinicaltrials.gov/study/NCT02539537 | E92: A Randomized Phase III Trial Comparing Folfirinox to Gemcitabine in Locally Advanced Pancreatic Carcinoma | F92: UNICANCER | M92: Yes
C93: Centre Alexis Vautrin, Vandœuvre-lès-Nancy, 54511, France | D93: https://clinicaltrials.gov/study/NCT00064207 | E93: Gemcitabine and Radiation Therapy Compared With Gemcitabine Alone in Treating Patients Who Have Undergone Surgery for Pancreatic Cancer | F93: European Organisation for Research and Treatment of Cancer - EORTC | M93: Yes
C94: Centre Alexis Vautrin, Vandœuvre-lès-Nancy, 54511, France | D94: https://clinicaltrials.gov/study/NCT00112697 | E94: Radiation Therapy and Docetaxel With Either Fluorouracil or Cisplatin as First-Line Therapy in Treating Patients With Metastatic Pancreatic Cancer That Cannot Be Removed By Surgery | F94: UNICANCER | H94: Yes | M94: Yes
A95: ID00032 | B95: Hôpital de la Timone Adulte | C95: Hôpital De La Timone, Marseille, 13365, France | D95: https://clinicaltrials.gov/study/NCT02539537 | E95: A Randomized Phase III Trial Comparing Folfirinox to Gemcitabine in Locally Advanced Pancreatic Carcinoma | F95: UNICANCER | M95: Yes
C96: Centre Alexis Vautrin, Vandœuvre-lès-Nancy, France | D96: https://clinicaltrials.gov/study/NCT01526135 | E96: Trial Comparing Adjuvant Chemotherapy With Gemcitabine Versus mFolfirinox to Treat Resected Pancreatic Adenocarcinoma | F96: UNICANCER | L96: Yes
A97: ID00079 | B97: Centre Antoine Lacassagne | C97: Centre Antoine Lassagne, Nice, France | D97: https://clinicaltrials.gov/study/NCT02352337 | E97: First-line Metastatic Pancreatic Cancer : FOLFIRINOX +/- LV5FU2 in Maintenance Versus Firgem | F97: Federation Francophone de Cancerologie Digestive | H97: Yes | L97: Yes | M97: Yes
C98: Centre Cario - Hpca Saint Brieuc, Plérin, France | D98: https://clinicaltrials.gov/study/NCT02827201 | E98: FIrst Line Treatment of Metastatic Pancreatic Cancer: Sequential Nab-paclitaxel + Gemcitabine/FOLFIRI.3 VS Nab-paclitaxel + Gemcitabine | F98: Federation Francophone de Cancerologie Digestive | H98: Yes | M98: Yes
A99: ID00079 | B99: Centre Antoine Lacassagne | C99: Centre Antoine Lacassagne, Nice, France | D99: https://clinicaltrials.gov/study/NCT02539537 | E99: A Randomized Phase III Trial Comparing Folfirinox to Gemcitabine in Locally Advanced Pancreatic Carcinoma | F99: UNICANCER | M99: Yes
C100: Centre Cario HPCA, Plérin, 22190, France | D100: https://clinicaltrials.gov/study/NCT03693677 | E100: First Line Metastatic Pancreatic Cancer : 5FU/LV+Nal-IRI, Gemcitabine+Nab-paclitaxel or a Sequential Regimen of 2 Months 5FU/LV+Nal-IRI | F100: Federation Francophone de Cancerologie Digestive | H100: Yes | M100: Yes
...

Sheet HCO referrals
A1: Path_ID | B1: From_Hospital_ID | C1: To_Hospital_ID | D1: Connection_Type | E1: Strength | F1: Source
A2: =B2&"-"&C2&"-"&SUBSTITUTE(D2," ", "-") -> ID00043-ID00038-Collaboration | B2: ID00043 | C2: ID00038 | D2: Collaboration | E2: 1 | F2: https://curie.fr/symptomes-et-diagnostic-du-cancer-du-pancreas#content
A3: =B3&"-"&C3&"-"&SUBSTITUTE(D3," ", "-") -> ID00038-ID00043-Collaboration | B3: ID00038 | C3: ID00043 | D3: Collaboration | E3: 1 | F3: https://curie.fr/symptomes-et-diagnostic-du-cancer-du-pancreas#content
A4: =B4&"-"&C4&"-"&SUBSTITUTE(D4," ", "-") -> ID00002-ID00006-Referral | B4: ID00002 | C4: ID00006 | D4: Referral | E4: 1 | F4: https://www.chru-strasbourg.fr/service/gastro-enterologie/
A5: =B5&"-"&C5&"-"&SUBSTITUTE(D5," ", "-") -> ID00006-ID00002-Surgery | B5: ID00006 | C5: ID00002 | D5: Surgery | E5: 1 | F5: https://www.chru-strasbourg.fr/service/gastro-enterologie/
A6: =B6&"-"&C6&"-"&SUBSTITUTE(D6," ", "-") -> ID00004-ID00026-Collaboration | B6: ID00004 | C6: ID00026 | D6: Collaboration | E6: 1
A7: =B7&"-"&C7&"-"&SUBSTITUTE(D7," ", "-") -> ID00026-ID00004-Collaboration | B7: ID00026 | C7: ID00004 | D7: Collaboration | E7: 1
A8: =B8&"-"&C8&"-"&SUBSTITUTE(D8," ", "-") -> ID00004-ID00012-Collaboration | B8: ID00004 | C8: ID00012 | D8: Collaboration | E8: 1 | F8: https://www.chu-montpellier.fr/fr/information-transversale/actualites/autogreffe-dilots-de-langerhans-une-procedure-exceptionnelle-promu-a-un-fort-developpement-7253
A9: =B9&"-"&C9&"-"&SUBSTITUTE(D9," ", "-") -> ID00012-ID00004-Collaboration | B9: ID00012 | C9: ID00004 | D9: Collaboration | E9: 1 | F9: https://www.chu-montpellier.fr/fr/information-transversale/actualites/autogreffe-dilots-de-langerhans-une-procedure-exceptionnelle-promu-a-un-fort-developpement-7253
A10: =B10&"-"&C10&"-"&SUBSTITUTE(D10," ", "-") -> ID00089-ID00005-Collaboration | B10: ID00089 | C10: ID00005 | D10: Collaboration | E10: 1 | F10: https://www.aphp.fr/pitie-salpetriere/service-d-oncologie-medicale
A11: =B11&"-"&C11&"-"&SUBSTITUTE(D11," ", "-") -> ID00005-ID00089-Collaboration | B11: ID00005 | C11: ID00089 | D11: Collaboration | E11: 1 | F11: https://www.aphp.fr/pitie-salpetriere/service-d-oncologie-medicale
A12: =B12&"-"&C12&"-"&SUBSTITUTE(D12," ", "-") -> ID00090-ID00005-Collaboration | B12: ID00090 | C12: ID00005 | D12: Collaboration | E12: 1 | F12: https://www.aphp.fr/pitie-salpetriere/service-d-oncologie-medicale
A13: =B13&"-"&C13&"-"&SUBSTITUTE(D13," ", "-") -> ID00005-ID00090-Collaboration | B13: ID00005 | C13: ID00090 | D13: Collaboration | E13: 1 | F13: https://www.aphp.fr/pitie-salpetriere/service-d-oncologie-medicale
A14: =B14&"-"&C14&"-"&SUBSTITUTE(D14," ", "-") -> ID00065-ID00005-Referral | B14: ID00065 | C14: ID00005 | D14: Referral | E14: 1 | F14: https://www.aphp.fr/registre-des-essais-cliniques/tepirm-dans-levaluation-de-la-reponse-au-traitement-neoadjuvant-de
A15: =B15&"-"&C15&"-"&SUBSTITUTE(D15," ", "-") -> ID00008-ID00005-Referral | B15: ID00008 | C15: ID00005 | D15: Referral | E15: 1 | F15: https://www.aphp.fr/registre-des-essais-cliniques/tepirm-dans-levaluation-de-la-reponse-au-traitement-neoadjuvant-de
A16: =B16&"-"&C16&"-"&SUBSTITUTE(D16," ", "-") -> ID00001-ID00005-Referral | B16: ID00001 | C16: ID00005 | D16: Referral | E16: 1 | F16: https://www.aphp.fr/registre-des-essais-cliniques/tepirm-dans-levaluation-de-la-reponse-au-traitement-neoadjuvant-de
A17: =B17&"-"&C17&"-"&SUBSTITUTE(D17," ", "-") -> ID00066-ID00005-Referral | B17: ID00066 | C17: ID00005 | D17: Referral | E17: 1 | F17: https://www.aphp.fr/registre-des-essais-cliniques/tepirm-dans-levaluation-de-la-reponse-au-traitement-neoadjuvant-de
A18: =B18&"-"&C18&"-"&SUBSTITUTE(D18," ", "-") -> ID00045-ID00005-Referral | B18: ID00045 | C18: ID00005 | D18: Referral | E18: 1 | F18: https://www.aphp.fr/registre-des-essais-cliniques/tepirm-dans-levaluation-de-la-reponse-au-traitement-neoadjuvant-de
A19: =B19&"-"&C19&"-"&SUBSTITUTE(D19," ", "-") -> ID00082-ID00005-Referral | B19: ID00082 | C19: ID00005 | D19: Referral | E19: 1 | F19: https://www.aphp.fr/registre-des-essais-cliniques/tepirm-dans-levaluation-de-la-reponse-au-traitement-neoadjuvant-de
... A29: =B29&"-"&C29&"-"&SUBSTITUTE(D29," ", "-") -> ID00048-ID00047-Referral | B29: ID00048 | C29: ID00047 | D29: Referral | E29: 1 | F29: https://www.chu-clermontferrand.fr/liste-services/unite-de-bilan-et-oncologie-digestive-ubod
A30: =B30&"-"&C30&"-"&SUBSTITUTE(D30," ", "-") -> ID00048-ID00049-Referral | B30: ID00048 | C30: ID00049 | D30: Referral | E30: 1
A31: =B31&"-"&C31&"-"&SUBSTITUTE(D31," ", "-") -> ID00047-ID00049-Referral | B31: ID00047 | C31: ID00049 | D31: Referral | E31: 1
A32: =B32&"-"&C32&"-"&SUBSTITUTE(D32," ", "-") -> ID00067-ID00066-Referral | B32: ID00067 | C32: ID00066 | D32: Referral | E32: 1
A33: =B33&"-"&C33&"-"&SUBSTITUTE(D33," ", "-") -> ID00081-ID00002-Referral | B33: ID00081 | C33: ID00002 | D33: Referral | E33: 1
A34: =B34&"-"&C34&"-"&SUBSTITUTE(D34," ", "-") -> ID00081-ID00006-Referral | B34: ID00081 | C34: ID00006 | D34: Referral | E34: 1
A35: =B35&"-"&C35&"-"&SUBSTITUTE(D35," ", "-") -> ID00002-ID00081-Referral | B35: ID00002 | C35: ID00081 | D35: Referral | E35: 1
A36: =B36&"-"&C36&"-"&SUBSTITUTE(D36," ", "-") -> ID00006-ID00081-Referral | B36: ID00006 | C36: ID00081 | D36: Referral | E36: 1
A37: =B37&"-"&C37&"-"&SUBSTITUTE(D37," ", "-") -> ID00085-ID00056-Collaboration | B37: ID00085 | C37: ID00056 | D37: Collaboration | E37: 1
A38: =B38&"-"&C38&"-"&SUBSTITUTE(D38," ", "-") -> ID00056-ID00085-Collaboration | B38: ID00056 | C38: ID00085 | D38: Collaboration | E38: 1
A39: =B39&"-"&C39&"-"&SUBSTITUTE(D39," ", "-") -> ID00132-ID00085-Collaboration | B39: ID00132 | C39: ID00085 | D39: Collaboration | E39: 1 | F39: https://www.afihge.org/offre-dinstallation-a-rennes-clinique-la-sagesse/
A40: =B40&"-"&C40&"-"&SUBSTITUTE(D40," ", "-") -> ID00085-ID00132-Collaboration | B40: ID00085 | C40: ID00132 | D40: Collaboration | E40: 1 | F40: https://www.afihge.org/offre-dinstallation-a-rennes-clinique-la-sagesse/
A41: =B41&"-"&C41&"-"&SUBSTITUTE(D41," ", "-") -> ID00132-ID00056-Collaboration | B41: ID00132 | C41: ID00056 | D41: Collaboration | E41: 1 | F41: https://www.afihge.org/offre-dinstallation-a-rennes-clinique-la-sagesse/
A42: =B42&"-"&C42&"-"&SUBSTITUTE(D42," ", "-") -> ID00056-ID00132-Collaboration | B42: ID00056 | C42: ID00132 | D42: Collaboration | E42: 1 | F42: https://www.afihge.org/offre-dinstallation-a-rennes-clinique-la-sagesse/
A43: =B43&"-"&C43&"-"&SUBSTITUTE(D43," ", "-") -> ID00024-ID00079-Collaboration | B43: ID00024 | C43: ID00079 | D43: Collaboration | E43: 1
A44: =B44&"-"&C44&"-"&SUBSTITUTE(D44," ", "-") -> ID00079-ID00024-Collaboration | B44: ID00079 | C44: ID00024 | D44: Collaboration | E44: 1 | F44: https://www.chu-nice.fr/patients-visiteurs/prise-en-charge-cancer/
A45: =B45&"-"&C45&"-"&SUBSTITUTE(D45," ", "-") -> ID00025-ID00024-Surgery | B45: ID00025 | C45: ID00024 | D45: Surgery | E45: 1 | F45: https://www.chu-nice.fr/patients-visiteurs/prise-en-charge-cancer/
A46: =B46&"-"&C46&"-"&SUBSTITUTE(D46," ", "-") -> ID00069-ID00104-Surgery | B46: ID00069 | C46: ID00104 | D46: Surgery | E46: 1
A47: =B47&"-"&C47&"-"&SUBSTITUTE(D47," ", "-") -> ID00101-ID00112-Collaboration | B47: ID00101 | C47: ID00112 | D47: Collaboration | E47: 1
A48: =B48&"-"&C48&"-"&SUBSTITUTE(D48," ", "-") -> ID00112-ID00101-Collaboration | B48: ID00112 | C48: ID00101 | D48: Collaboration | E48: 1
A49: =B49&"-"&C49&"-"&SUBSTITUTE(D49," ", "-") -> ID00073-ID00145-Collaboration | B49: ID00073 | C49: ID00145 | D49: Collaboration | E49: 1
A50: =B50&"-"&C50&"-"&SUBSTITUTE(D50," ", "-") -> ID00145-ID00073-Collaboration | B50: ID00145 | C50: ID00073 | D50: Collaboration | E50: 1
A51: =B51&"-"&C51&"-"&SUBSTITUTE(D51," ", "-") -> ID00017-ID00083-Collaboration | B51: ID00017 | C51: ID00083 | D51: Collaboration | E51: 1
A52: =B52&"-"&C52&"-"&SUBSTITUTE(D52," ", "-") -> ID00083-ID00017-Collaboration | B52: ID00083 | C52: ID00017 | D52: Collaboration | E52: 1
A53: =B53&"-"&C53&"-"&SUBSTITUTE(D53," ", "-") -> ID00017-ID00083-Referral | B53: ID00017 | C53: ID00083 | D53: Referral | E53: 1
A54: =B54&"-"&C54&"-"&SUBSTITUTE(D54," ", "-") -> ID00083-ID00017-Referral | B54: ID00083 | C54: ID00017 | D54: Referral | E54: 1
A55: =B55&"-"&C55&"-"&SUBSTITUTE(D55," ", "-") -> ID00055-ID00054-Surgery | B55: ID00055 | C55: ID00054 | D55: Surgery | E55: 1
A56: =B56&"-"&C56&"-"&SUBSTITUTE(D56," ", "-") -> ID00055-ID00054-Referral | B56: ID00055 | C56: ID00054 | D56: Referral | E56: 1
A57: =B57&"-"&C57&"-"&SUBSTITUTE(D57," ", "-") -> ID00149-ID00099-Collaboration | B57: ID00149 | C57: ID00099 | D57: Collaboration | E57: 1
... A69: =B69&"-"&C69&"-"&SUBSTITUTE(D69," ", "-") -> ID00051-ID00324-Collaboration | B69: ID00051 | C69: ID00324 | D69: Collaboration | E69: 1
A70: =B70&"-"&C70&"-"&SUBSTITUTE(D70," ", "-") -> ID00326-ID00068-Collaboration | B70: ID00326 | C70: ID00068 | D70: Collaboration | E70: 1 | F70: https://www.oncopacacorse.org/structures/hopital-prive-toulon-hyeres-saint-jean/
A71: =B71&"-"&C71&"-"&SUBSTITUTE(D71," ", "-") -> ID00068-ID00326-Collaboration | B71: ID00068 | C71: ID00326 | D71: Collaboration | E71: 1 | F71: https://www.oncopacacorse.org/structures/hopital-prive-toulon-hyeres-saint-jean/
A72: =B72&"-"&C72&"-"&SUBSTITUTE(D72," ", "-") -> ID00327-ID00052-Surgery | B72: ID00327 | C72: ID00052 | D72: Surgery | E72: 1 | F72: https://emploi.fhf.fr/emploi/343086
A73: =B73&"-"&C73&"-"&SUBSTITUTE(D73," ", "-") -> ID00327-ID00010-Collaboration | B73: ID00327 | C73: ID00010 | D73: Collaboration | E73: 1 | F73: https://www.ch-sens.fr/oncologie-medicale-hospitalisation-de-jour
A74: =B74&"-"&C74&"-"&SUBSTITUTE(D74," ", "-") -> ID00010-ID00327-Collaboration | B74: ID00010 | C74: ID00327 | D74: Collaboration | E74: 1 | F74: https://www.ch-sens.fr/oncologie-medicale-hospitalisation-de-jour
A75: =B75&"-"&C75&"-"&SUBSTITUTE(D75," ", "-") -> ID00059-ID00014-Collaboration | B75: ID00059 | C75: ID00014 | D75: Collaboration | E75: 1
A76: =B76&"-"&C76&"-"&SUBSTITUTE(D76," ", "-") -> ID00014-ID00059-Collaboration | B76: ID00014 | C76: ID00059 | D76: Collaboration | E76: 1
A77: =B77&"-"&C77&"-"&SUBSTITUTE(D77," ", "-") -> ID00318-ID00079-Collaboration | B77: ID00318 | C77: ID00079 | D77: Collaboration | E77: 1
A78: =B78&"-"&C78&"-"&SUBSTITUTE(D78," ", "-") -> ID00079-ID00318-Collaboration | B78: ID00079 | C78: ID00318 | D78: Collaboration | E78: 1
A79: =B79&"-"&C79&"-"&SUBSTITUTE(D79," ", "-") -> ID00322-ID00036-Collaboration | B79: ID00322 | C79: ID00036 | D79: Collaboration | E79: 1 | F79: https://www.chu-grenoble.fr/patients-et-accompagnants/offre-de-soin/hepato-gastroenterologie-voiron
A80: =B80&"-"&C80&"-"&SUBSTITUTE(D80," ", "-") -> ID00036-ID00322-Collaboration | B80: ID00036 | C80: ID00322 | D80: Collaboration | E80: 1 | F80: https://www.chu-grenoble.fr/patients-et-accompagnants/offre-de-soin/hepato-gastroenterologie-voiron
A81: =B81&"-"&C81&"-"&SUBSTITUTE(D81," ", "-") -> ID00079-ID00166-Collaboration | B81: ID00079 | C81: ID00166 | D81: Collaboration | E81: 1
A82: =B82&"-"&C82&"-"&SUBSTITUTE(D82," ", "-") -> ID00166-ID00079-Collaboration | B82: ID00166 | C82: ID00079 | D82: Collaboration | E82: 1
A83: =B83&"-"&C83&"-"&SUBSTITUTE(D83," ", "-") -> ID00313-ID00333-Surgery | B83: ID00313 | C83: ID00333 | D83: Surgery | E83: 1
A84: =B84&"-"&C84&"-"&SUBSTITUTE(D84," ", "-") -> ID00313-ID00007-Collaboration | B84: ID00313 | C84: ID00007 | D84: Collaboration | E84: 1 | F84: https://www.ch-argenteuil.fr/service/oncologie-medicale/#sactivites
A85: =B85&"-"&C85&"-"&SUBSTITUTE(D85," ", "-") -> ID00007-ID00313-Collaboration | B85: ID00007 | C85: ID00313 | D85: Collaboration | E85: 1 | F85: https://www.ch-argenteuil.fr/service/oncologie-medicale/#sactivites
A86: =B86&"-"&C86&"-"&SUBSTITUTE(D86," ", "-") -> ID00313-ID00044-Collaboration | B86: ID00313 | C86: ID00044 | D86: Collaboration | E86: 1 | F86: https://www.ch-argenteuil.fr/service/oncologie-medicale/#sactivites
A87: =B87&"-"&C87&"-"&SUBSTITUTE(D87," ", "-") -> ID00044-ID00313-Collaboration | B87: ID00044 | C87: ID00313 | D87: Collaboration | E87: 1 | F87: https://www.ch-argenteuil.fr/service/oncologie-medicale/#sactivites
A88: =B88&"-"&C88&"-"&SUBSTITUTE(D88," ", "-") -> ID00313-ID00043-Collaboration | B88: ID00313 | C88: ID00043 | D88: Collaboration | E88: 1 | F88: https://www.ch-argenteuil.fr/service/oncologie-medicale/#sactivites
A89: =B89&"-"&C89&"-"&SUBSTITUTE(D89," ", "-") -> ID00043-ID00313-Collaboration | B89: ID00043 | C89: ID00313 | D89: Collaboration | E89: 1 | F89: https://www.ch-argenteuil.fr/service/oncologie-medicale/#sactivites
A90: =B90&"-"&C90&"-"&SUBSTITUTE(D90," ", "-") -> ID00313-ID00067-Collaboration | B90: ID00313 | C90: ID00067 | D90: Collaboration | E90: 1 | F90: https://www.ch-argenteuil.fr/service/oncologie-medicale/#sactivites
A91: =B91&"-"&C91&"-"&SUBSTITUTE(D91," ", "-") -> ID00067-ID00313-Collaboration | B91: ID00067 | C91: ID00313 | D91: Collaboration | E91: 1 | F91: https://www.ch-argenteuil.fr/service/oncologie-medicale/#sactivites
A92: =B92&"-"&C92&"-"&SUBSTITUTE(D92," ", "-") -> ID00142-ID00143-Referral | B92: ID00142 | C92: ID00143 | D92: Referral | E92: 1
A93: =B93&"-"&C93&"-"&SUBSTITUTE(D93," ", "-") -> ID00314-ID00076-Collaboration | B93: ID00314 | C93: ID00076 | D93: Collaboration | E93: 1 | F93: https://www.caducee.net/annonces-medicales/emploi-medecin/praticien-contractuel/p14.html
A94: =B94&"-"&C94&"-"&SUBSTITUTE(D94," ", "-") -> ID00076-ID00314-Collaboration | B94: ID00076 | C94: ID00314 | D94: Collaboration | E94: 1 | F94: https://www.caducee.net/annonces-medicales/emploi-medecin/praticien-contractuel/p14.html
A95: =B95&"-"&C95&"-"&SUBSTITUTE(D95," ", "-") -> ID00314-ID00085-Collaboration | B95: ID00314 | C95: ID00085 | D95: Collaboration | E95: 1
A96: =B96&"-"&C96&"-"&SUBSTITUTE(D96," ", "-") -> ID00085-ID00314-Collaboration | B96: ID00085 | C96: ID00314 | D96: Collaboration | E96: 1
A97: =B97&"-"&C97&"-"&SUBSTITUTE(D97," ", "-") -> ID00314-ID00601-Collaboration | B97: ID00314 | C97: ID00601 | D97: Collaboration | E97: 1
A98: =B98&"-"&C98&"-"&SUBSTITUTE(D98," ", "-") -> ID00601-ID00314-Collaboration | B98: ID00601 | C98: ID00314 | D98: Collaboration | E98: 1
A99: =B99&"-"&C99&"-"&SUBSTITUTE(D99," ", "-") -> ID00315-ID00301-Collaboration | B99: ID00315 | C99: ID00301 | D99: Collaboration | E99: 1
A100: =B100&"-"&C100&"-"&SUBSTITUTE(D100," ", "-") -> ID00301-ID00315-Collaboration | B100: ID00301 | C100: ID00315 | D100: Collaboration | E100: 1
A101: =B101&"-"&C101&"-"&SUBSTITUTE(D101," ", "-") -> ID00315-ID00913-Collaboration | B101: ID00315 | C101: ID00913 | D101: Collaboration | E101: 1
A102: =B102&"-"&C102&"-"&SUBSTITUTE(D102," ", "-") -> ID00913-ID00315-Collaboration | B102: ID00913 | C102: ID00315 | D102: Collaboration | E102: 1
A103: =B103&"-"&C103&"-"&SUBSTITUTE(D103," ", "-") -> ID00126-ID00002-Collaboration | B103: ID00126 | C103: ID00002 | D103: Collaboration | E103: 1
A104: =B104&"-"&C104&"-"&SUBSTITUTE(D104," ", "-") -> ID00002-ID00126-Collaboration | B104: ID00002 | C104: ID00126 | D104: Collaboration | E104: 1
A105: =B105&"-"&C105&"-"&SUBSTITUTE(D105," ", "-") -> ID00314-ID00309-Collaboration | B105: ID00314 | C105: ID00309 | D105: Collaboration | E105: 1
A106: =B106&"-"&C106&"-"&SUBSTITUTE(D106," ", "-") -> ID00309-ID00314-Collaboration | B106: ID00309 | C106: ID00314 | D106: Collaboration | E106: 1
A107: =B107&"-"&C107&"-"&SUBSTITUTE(D107," ", "-") -> ID00170-ID00932-Referral | B107: ID00170 | C107: ID00932 | D107: Referral | E107: 1 | F107: https://www.ch-boulogne.fr/medecins-specialites/par-services/oncologie-medicale
A108: =B108&"-"&C108&"-"&SUBSTITUTE(D108," ", "-") -> ID00932-ID00170-Referral | B108: ID00932 | C108: ID00170 | D108: Referral | E108: 1
A109: =B109&"-"&C109&"-"&SUBSTITUTE(D109," ", "-") -> ID00110-ID00394-Collaboration | B109: ID00110 | C109: ID00394 | D109: Collaboration | E109: 1 | F109: https://www.onco-grandest.fr/annuaire-des-rcp/
A110: =B110&"-"&C110&"-"&SUBSTITUTE(D110," ", "-") -> ID00394-ID00110-Collaboration | B110: ID00394 | C110: ID00110 | D110: Collaboration | E110: 1
A111: =B111&"-"&C111&"-"&SUBSTITUTE(D111," ", "-") -> ID00304-ID00047-Collaboration | B111: ID00304 | C111: ID00047 | D111: Collaboration | E111: 1 | F111: https://www.chu-clermontferrand.fr/le-centre-hospitalier-de-montlucon-neris-les-bains-et-le-chru-en-direction-commune
A112: =B112&"-"&C112&"-"&SUBSTITUTE(D112," ", "-") -> ID00047-ID00304-Collaboration | B112: ID00047 | C112: ID00304 | D112: Collaboration | E112: 1 | F112: https://www.chu-clermontferrand.fr/le-centre-hospitalier-de-montlucon-neris-les-bains-et-le-chru-en-direction-commune
A113: =B113&"-"&C113&"-"&SUBSTITUTE(D113," ", "-") -> ID00305-ID00453-Collaboration | B113: ID00305 | C113: ID00453 | D113: Collaboration | E113: 1
A114: =B114&"-"&C114&"-"&SUBSTITUTE(D114," ", "-") -> ID00453-ID00305-Collaboration | B114: ID00453 | C114: ID00305 | D114: Collaboration | E114: 1
A115: =B115&"-"&C115&"-"&SUBSTITUTE(D115," ", "-") -> ID00019-ID00018-Collaboration | B115: ID00019 | C115: ID00018 | D115: Collaboration | E115: 1
A116: =B116&"-"&C116&"-"&SUBSTITUTE(D116," ", "-") -> ID00018-ID00019-Collaboration | B116: ID00018 | C116: ID00019 | D116: Collaboration | E116: 1
A117: =B117&"-"&C117&"-"&SUBSTITUTE(D117," ", "-") -> ID00302-ID00117-Surgery | B117: ID00302 | C117: ID00117 | D117: Surgery | E117: 1 | F117: https://onco-nouvelle-aquitaine.fr/annuaire/3c-bordeaux-nord/
A118: =B118&"-"&C118&"-"&SUBSTITUTE(D118," ", "-") -> ID00071-ID00302-Collaboration | B118: ID00071 | C118: ID00302 | D118: Collaboration | E118: 1 | F118: https://onco-nouvelle-aquitaine.fr/annuaire/3c-institut-bergonie/
A119: =B119&"-"&C119&"-"&SUBSTITUTE(D119," ", "-") -> ID00302-ID00071-Collaboration | B119: ID00302 | C119: ID00071 | D119: Collaboration | E119: 1 | F119: https://onco-nouvelle-aquitaine.fr/annuaire/3c-institut-bergonie/
A120: =B120&"-"&C120&"-"&SUBSTITUTE(D120," ", "-") -> ID00161-ID00046-MDT | B120: ID00161 | C120: ID00046 | D120: MDT | E120: 1 | F120: https://www.centreoscarlambret.fr/membres/archer
...

Sheet HCPs
B1: HCP Tier | C1: RevMeds Tiering | D1: HCP Information + Bio | J1: HCP Details | V1: HCO Details | AD1: Publications | AL1: Clinical Trials | AR1: Speaking | AS1: Associations, Key Centers/Departments
A2: Order of placement | D2: Pancreatic Cancer | E2: Pancreatic surgery | F2: PDAC OR Pancreatic Adenocarcinoma | G2: Tumour profiling/precision medicine/personalized tumor therapy | H2: Tumour board participation | I2: Role | J2: Rationale | K2: HCP_VeevaID | L2: BioLink | M2: Full name | N2: Pubmed_Name | O2: HCO Count | P2: Hospital/ Non-hospital | Q2: Head of Department | R2: Primary Specialty Group | S2: Spec 1 | T2: Spec 2 | U2: Spec 3 | V2: VeevaID | W2: GDS_HCO_ID | X2: HCO name | Y2: Address | Z2: Zipcode | AA2: Region | AB2: City | AC2: Country | AD2: No. Unique Guidelines | AE2: No. Unique Publications | AF2: KRAS AND pancreatic cancer | AG2: PDAC OR Pancreatic Adenocarcinoma | AH2: Pancreatic Cancer | AI2: Molecular Oncology (e.g. profiling) | AJ2: Personalized medicine | AK2: Next generation Sequencing | AL2: No. of Unique Clinical Trials | AM2: PDAC OR Pancreatic Adenocarcinoma | AN2: KRAS mutation | AO2: Pancreatic Cancer | AP2: Unresectable | AQ2: Metastatic | AR2: No. Speaking Events | AS2: BACAP Partner | AT2: Espoir Pancreas Patient Association | AU2: Societe Francaise Pancreas | AV2: ARCAD Foundation | AW2: Genetics and Cancer Group | AX2: FRAP (French Research Network against Pancreatic Adenocarcinoma) | AY2: French Association for Research on Pancreatic Cancer | AZ2: Pancreatic Cancer Europe | BA2: Groupe Prodige pancréas (cancer) | BB2: SOS Pancreas | BC2: PANDAURA (PDAC) Steering Committee
A3: filter | B3: filter | C3: filter | D3: filter | E3: filter | F3: filter | G3: filter | H3: filter | J3: filter | K3: filter | M3: filter | N3: filter | O3: filter | P3: filter | Q3: filter | R3: filter | S3: filter | T3: filter | U3: filter | V3: filter | W3: filter | X3: filter | Y3: filter | Z3: filter | AA3: filter | AB3: filter | AC3: filter | AD3: filter | AE3: filter | AF3: filter | AG3: filter | AH3: filter | AI3: filter | AJ3: filter | AK3: filter | AL3: filter | AM3: filter | AN3: filter | AO3: filter | AP3: filter | AQ3: filter | AR3: filter | AS3: filter | AT3: filter | AU3: filter | AV3: filter | AW3: filter | AX3: filter | AY3: filter | AZ3: filter | BA3: filter | BB3: filter | BC3: filter
B4: KOL | C4: Tier 2 | I4: Head of pancreatic cancer consultation | J4: Leads the Hepatobiliary and pancreatic surgery consultation | K4: 608464719287698474 | M4: Safi Dokmak | N4: Safi Dokmak | Q4: =IF(COUNTIFS(HCP_evidence!$A:$A, M4, HCP_evidence!$AB:$AB, "<>")>0, "Yes", "") | R4: Abdominal Surgery | S4: Abdominal Surgery | W4: ID00001 | X4: Hôpital Beaujon | AC4: France
A5: 125 | B5: KOL | C5: Tier 3 | I5: Head of department treating pancreatic cancer | J5: Member of the research committee of Societe Francaise Pancreas. Head of the Pancreatology and Digestive Oncology department. Head of the rapid pancreatic diagnostic center. | K5: 608464741240685595 | M5: Vinciane Rebours | N5: Vinciane Rebours | Q5: =IF(COUNTIFS(HCP_evidence!$A:$A, M5, HCP_evidence!$AB:$AB, "<>")>0, "Yes", "") -> Yes | R5: Gastroenterology | S5: Gastroenterology | W5: ID00001 | X5: Hôpital Beaujon | AC5: France | AU5: Yes | AW5: =IF(COUNTIFS(HCP_evidence!$A:$A, M5, HCP_evidence!$AH:$AH, "<>")>0, "Yes", "")
A6: 114 | B6: KOL | C6: Tier 2 | J6: Clinical Trial Coordinator. Member of the research committee of Societe Francaise Pancreas. Works in Pancreatology and Digestive Oncology department where pancreatic cancer is treated. Contact clinical trial | K6: 928415955849642527 | M6: Louis de Mestier | N6: Louis de Mestier | Q6: =IF(COUNTIFS(HCP_evidence!$A:$A, M6, HCP_evidence!$AB:$AB, "<>")>0, "Yes", "") | S6: Gastroenterology | T6: Gastroenterology | W6: ID00001 | X6: Hôpital Beaujon | AC6: France | AU6: Yes | AW6: =IF(COUNTIFS(HCP_evidence!$A:$A, M6, HCP_evidence!$AH:$AH, "<>")>0, "Yes", "")
J7: Works in the department of Pancreatology and Digestive Oncology specialised in pancreatic diseases. | K7: 608464692167328773 | M7: Philippe Levy | Q7: =IF(COUNTIFS(HCP_evidence!$A:$A, M7, HCP_evidence!$AB:$AB, "<>")>0, "Yes", "") | R7: Gastroenterology | S7: Gastroenterology | W7: ID00001 | X7: Hôpital Beaujon | AC7: France
J8: Works in Pancreatology and Digestive Oncology department where pancreatic cancer is treated | K8: 608464694037988405 | M8: Nelly Muller | N8: Nelly Muller | Q8: =IF(COUNTIFS(HCP_evidence!$A:$A, M8, HCP_evidence!$AB:$AB, "<>")>0, "Yes", "") | R8: Gastroenterology | S8: Gastroenterology | W8: ID00001 | X8: Hôpital Beaujon
J9: Contact person clinical trial, Accreditation coordinator of Summary Initial_managemen of pancreatic adenocarcinoma cases | K9: 608464718608221216 | M9: Alain Sauvanet | N9: Alain Sauvanet | Q9: =IF(COUNTIFS(HCP_evidence!$A:$A, M9, HCP_evidence!$AB:$AB, "<>")>0, "Yes", "") | R9: General Surgery | S9: General Surgery | T9: Surgical Oncology | W9: ID00001 | X9: Hôpital Beaujon | AC9: France | AW9: =IF(COUNTIFS(HCP_evidence!$A:$A, M9, HCP_evidence!$AH:$AH, "<>")>0, "Yes", "")
J10: Works in Pancreatology and Digestive Oncology department where pancreatic cancer is treated | K10: 626077793276412929 | M10: Olivia Hentic-Dhome | N10: Olivia Hentic | Q10: =IF(COUNTIFS(HCP_evidence!$A:$A, M10, HCP_evidence!$AB:$AB, "<>")>0, "Yes", "") | R10: Gastroenterology | S10: Gastroenterology | W10: ID00001 | X10: Hôpital Beaujon
A11: 124 | J11: Member of the research committee of Societe Francaise Pancreas. Works in Pancreatology and Digestive Oncology department where pancreatic cancer is treated | K11: 626078955694212106 | M11: Frédérique Maire | N11: Frédérique Maire | Q11: =IF(COUNTIFS(HCP_evidence!$A:$A, M11, HCP_evidence!$AB:$AB, "<>")>0, "Yes", "") | R11: Gastroenterology | S11: Gastroenterology | W11: ID00001 | X11: Hôpital Beaujon | AC11: France | AU11: Yes | AW11: =IF(COUNTIFS(HCP_evidence!$A:$A, M11, HCP_evidence!$AH:$AH, "<>")>0, "Yes", "")
J12: Works in Pancreatology and Digestive Oncology department where pancreatic cancer is treated | K12: 928864656003170847 | M12: Lucie Boyer-Laurent | Q12: =IF(COUNTIFS(HCP_evidence!$A:$A, M12, HCP_evidence!$AB:$AB, "<>")>0, "Yes", "") | R12: Gastroenterology | S12: Gastroenterology | W12: ID00001 | X12: Hôpital Beaujon
J13: Works in Pancreatology and Digestive Oncology department where pancreatic cancer is treated | K13: 929531961162596895 | M13: Caroline Lacombe | N13: Caroline Lacombe | Q13: =IF(COUNTIFS(HCP_evidence!$A:$A, M13, HCP_evidence!$AB:$AB, "<>")>0, "Yes", "") | R13: Gastroenterology | S13: Gastroenterology | W13: ID00001 | X13: Hôpital Beaujon
I14: Head of department treating pancreatic cancer | J14: Head of HPB and liver-transplant surgery where pancreatic cancer is treated | K14: 929771110830178848 | M14: Mickael Lesurtel | N14: Mickaël Lesurtel | Q14: =IF(COUNTIFS(HCP_evidence!$A:$A, M14, HCP_evidence!$AB:$AB, "<>")>0, "Yes", "") -> Yes | S14: Abdominal Surgery | T14: Abdominal Surgery | U14: Hepatobiliary Surgery | W14: ID00001 | X14: Hôpital Beaujon
A15: 52 | J15: Doctor participating in the BACAP project. Member of the research committee of Societe Francaise Pancreas. Coordinator/Director of the French Research Network against Pancreatic Adenocarcinoma. Member of the French Association for Research on Pancreatic Cancer | K15: 932572189908077919 | M15: Jérôme Cros | N15: Jérome Cros | Q15: =IF(COUNTIFS(HCP_evidence!$A:$A, M15, HCP_evidence!$AB:$AB, "<>")>0, "Yes", "") | R15: Anatomic/Clinical Pathology | S15: Anatomic/Clinical Pathology | W15: ID00001 | X15: Hôpital Beaujon | AC15: France | AS15: Yes | AU15: Yes | AW15: =IF(COUNTIFS(HCP_evidence!$A:$A, M15, HCP_evidence!$AH:$AH, "<>")>0, "Yes", "") | AX15: Yes | AY15: Yes | AZ15: Yes
J16: Works in Pancreatology and Digestive Oncology department where pancreatic cancer is treated | K16: 932692518688329062 | M16: Grégoire Salin | Q16: =IF(COUNTIFS(HCP_evidence!$A:$A, M16, HCP_evidence!$AB:$AB, "<>")>0, "Yes", "") | R16: Gastroenterology | S16: Gastroenterology | W16: ID00001 | X16: Hôpital Beaujon
J17: Works in Pancreatology and Digestive Oncology department where pancreatic cancer is treated | K17: 933656547897249144 | M17: Johanna Pokossy-Epée | N17: Johanna Pokossy Epée | Q17: =IF(COUNTIFS(HCP_evidence!$A:$A, M17, HCP_evidence!$AB:$AB, "<>")>0, "Yes", "") | R17: Gastroenterology | S17: Gastroenterology | W17: ID00001 | X17: Hôpital Beaujon
A18: 206 | J18: Works in Pancreatology and Digestive Oncology department where pancreatic cancer is treated. Principal investigator clinical trial. | K18: 934035450624806267 | M18: Anne Laure Vedie | Q18: =IF(COUNTIFS(HCP_evidence!$A:$A, M18, HCP_evidence!$AB:$AB, "<>")>0, "Yes", "") | R18: Gastroenterology | S18: Gastroenterology | W18: ID00001 | X18: Hôpital Beaujon | AC18: France | AW18: =IF(COUNTIFS(HCP_evidence!$A:$A, M18, HCP_evidence!$AH:$AH, "<>")>0, "Yes", "")
I19: Head of department treating pancreatic cancer | J19: His service performs EUS and CPRE and treats pancreatic/biliary tumours. | K19: 608464748220007427 | M19: Frédéric Prat | Q19: =IF(COUNTIFS(HCP_evidence!$A:$A, M19, HCP_evidence!$AB:$AB, "<>")>0, "Yes", "") -> Yes | W19: ID00001 | X19: Hôpital Beaujon
J20: Surgeon | K20: 626078047526732817 | L20: https://www.aphp.fr/dr-aussilhou-beatrice | M20: Béatrice Aussilhou | Q20: =IF(COUNTIFS(HCP_evidence!$A:$A, M20, HCP_evidence!$AB:$AB, "<>")>0, "Yes", "") | S20: General Surgery | W20: ID00001 | X20: Hôpital Beaujon
B21: KOL | C21: Tier 3 | J21: Head of pancreatic surgery where pancreatic cancer is treated. | K21: 621591526744540233 | M21: Philippe Bachellier | N21: Philippe Bachellier | Q21: =IF(COUNTIFS(HCP_evidence!$A:$A, M21, HCP_evidence!$AB:$AB, "<>")>0, "Yes", "") -> Yes | R21: Abdominal Surgery | S21: Abdominal Surgery | W21: ID00002 | X21: Hôpital de Hautepierre | AC21: France
J22: Head of department of HPB and liver Transplanation where pancreatic cancer surgery takes place. Principal investigator clinical trial. | K22: 626077832879031297 | M22: Pietro Addeo | N22: Pietro F Addeo | Q22: =IF(COUNTIFS(HCP_evidence!$A:$A, M22, HCP_evidence!$AB:$AB, "<>")>0, "Yes", "") -> Yes | R22: Abdominal Surgery | W22: ID00002 | X22: Hôpital de Hautepierre | AC22: France
E23: Yes | J23: Visceral and digestive surgeon where pancreatic surgery takes place. | K23: 626078475119248391 | L23: https://www.elsan.care/fr/pole-sante-sud/nos-actualites/cancer-du-pancreas-les-drs-rosso-et-amariutei-mis-lhonneur-dans-une?layout=pole-sante-sud | M23: Edoardo E Rosso | N23: Edoardo E Rosso | Q23: =IF(COUNTIFS(HCP_evidence!$A:$A, M23, HCP_evidence!$AB:$AB, "<>")>0, "Yes", "") | R23: General Surgery | S23: General Surgery | T23: Abdominal Surgery | W23: ID00003 | X23: Clinique d'Alençon | AC23: France
J24: Officially performs interventional digestive endoscopy and echo-endoscopy and has additional training in hepatobiliary tumours. | K24: 621591754444915751 | L24: https://clinique-alencon.lna-sante.com/praticiens/dr-christophe-pilette/ | M24: Christophe Pilette | Q24: =IF(COUNTIFS(HCP_evidence!$A:$A, M24, HCP_evidence!$AB:$AB, "<>")>0, "Yes", "") | W24: ID00003 | X24: Clinique d'Alençon
A25: 85 | J25: Doctor participating in the BACAP project. Reviewer of the guideline on PDAC | K25: 560999771142095885 | M25: Jean-Michel Fabre | N25: Jean-Michel Fabre | Q25: =IF(COUNTIFS(HCP_evidence!$A:$A, M25, HCP_evidence!$AB:$AB, "<>")>0, "Yes", "") | R25: Abdominal Surgery | S25: Abdominal Surgery | T25: Surgical Oncology | W25: ID00004 | X25: Hôpital Saint-Eloi | AC25: France | AS25: Yes | AW25: =IF(COUNTIFS(HCP_evidence!$A:$A, M25, HCP_evidence!$AH:$AH, "<>")>0, "Yes", "")
A26: 83 | B26: KOL | C26: Tier 2 | J26: Lead investigator in the BACAP project. Head of department treating pancreatic cancer. Contact person clinical trial. | K26: 626077447430882330 | L26: https://www.icm.unicancer.fr/fr/annuaire-professionnels/eric-assenat | M26: Eric Assénat | N26: Eric Assénat | Q26: =IF(COUNTIFS(HCP_evidence!$A:$A, M26, HCP_evidence!$AB:$AB, "<>")>0, "Yes", "") -> Yes | R26: Gastroenterology | S26: Gastroenterology | W26: ID00004 | X26: Hôpital Saint-Eloi | AC26: France | AS26: Yes | AW26: =IF(COUNTIFS(HCP_evidence!$A:$A, M26, HCP_evidence!$AH:$AH, "<>")>0, "Yes", "")
A27: 86 | J27: Doctor participating in the BACAP project. Head of Digestive, oncological and minimally invasive surgery where pancreatic cancer surgery takes place. Study director clinical trial. Reviewer of the guideline on PDAC | K27: 626079488337265677 | M27: François-Régis Souche | N27: François-Régis Souche | Q27: =IF(COUNTIFS(HCP_evidence!$A:$A, M27, HCP_evidence!$AB:$AB, "<>")>0, "Yes", "") -> Yes | R27: Abdominal Surgery | S27: Abdominal Surgery | T27: Surgical Oncology | W27: ID00004 | X27: Hôpital Saint-Eloi | AC27: France | AS27: Yes | AW27: =IF(COUNTIFS(HCP_evidence!$A:$A, M27, HCP_evidence!$AH:$AH, "<>")>0, "Yes", "")
A28: 84 | J28: Doctor participating in the BACAP project | K28: 812891185000498177 | M28: Marie Dupuy | N28: Marie Dupuy | Q28: =IF(COUNTIFS(HCP_evidence!$A:$A, M28, HCP_evidence!$AB:$AB, "<>")>0, "Yes", "") | R28: Gastroenterology | S28: Gastroenterology | T28: Medical Oncology | W28: ID00004 | X28: Hôpital Saint-Eloi | AC28: France | AS28: Yes | AW28: =IF(COUNTIFS(HCP_evidence!$A:$A, M28, HCP_evidence!$AH:$AH, "<>")>0, "Yes", "")
A29: 87 | J29: Doctor participating in the BACAP project. Part of the team of Digestive, oncological and minimally invasive surgery where pancreatic cancer surgery takes place. Contact clinical trial | K29: 934912060921744735 | M29: Thomas Bardol | N29: Thomas Bardol | Q29: =IF(COUNTIFS(HCP_evidence!$A:$A, M29, HCP_evidence!$AB:$AB, "<>")>0, "Yes", "") | R29: Abdominal Surgery | S29: Abdominal Surgery | T29: Surgical Oncology | W29: ID00004 | X29: Hôpital Saint-Eloi | AC29: France | AS29: Yes | AW29: =IF(COUNTIFS(HCP_evidence!$A:$A, M29, HCP_evidence!$AH:$AH, "<>")>0, "Yes", "")
J30: In Veeva in Italy but works in France. Performed surgery on a pancratic cancer patient. | M30: Fabrizio Panaro | N30: Fabrizio Panaro | Q30: =IF(COUNTIFS(HCP_evidence!$A:$A, M30, HCP_evidence!$AB:$AB, "<>")>0, "Yes", "") | R30: General Surgery | S30: General Surgery | T30: Surgical Oncology | W30: ID00004 | X30: Hôpital Saint-Eloi | AC30: France
J31: Head of Liver, biliary, pancreatic surgery and transplantation where pancreatic cancer surgery takes place. | K31: 626077434747307011 | M31: Francis Navarro | N31: Francis Navarro | Q31: =IF(COUNTIFS(HCP_evidence!$A:$A, M31, HCP_evidence!$AB:$AB, "<>")>0, "Yes", "") -> Yes | W31: ID00004 | X31: Hôpital Saint-Eloi
J32: Reviewer of the guideline on PDAC | K32: 626077656407884831 | M32: Jean-Christophe Valats | Q32: =IF(COUNTIFS(HCP_evidence!$A:$A, M32, HCP_evidence!$AB:$AB, "<>")>0, "Yes", "") | W32: ID00004 | X32: Hôpital Saint-Eloi
A33: 190 | B33: KOL | C33: Tier 1 | I33: Head of department treating pancreatic cancer | J33: Clinical Trial Coordinator, principal investigator clinical trial. Head of the digestive oncology unit where pancreatic cancer is treated. Member of the ARCAD pancreatic working-group steering committee. Faculty on the 2025–26 inter-university pancreatology programme, specifically teaching metastatic pancreatic cancer chemotherapy. | K33: 608464684726633482 | M33: Jean-Baptiste Bachet | N33: Jean-Baptiste Bachet | Q33: =IF(COUNTIFS(HCP_evidence!$A:$A, M33, HCP_evidence!$AB:$AB, "<>")>0, "Yes", "") -> Yes | R33: Gastroenterology | S33: Gastroenterology | T33: Addiction Medicine | W33: ID00005 | X33: HU Pitié-Salpêtrière | AC33: France | AW33: =IF(COUNTIFS(HCP_evidence!$A:$A, M33, HCP_evidence!$AH:$AH, "<>")>0, "Yes", "")
B34: KOL | C34: Tier 2 | I34: Works in department where pancreatic cancer is treated | J34: Reference person for the rapid pancreas diagnostic centre. Principal investigator clinical trial. Reviewer of the guideline on PDAC | K34: 626079256501306386 | M34: Sébastien Gaujoux | N34: Sébastien Gaujoux | Q34: =IF(COUNTIFS(HCP_evidence!$A:$A, M34, HCP_evidence!$AB:$AB, "<>")>0, "Yes", "") -> Yes | R34: Abdominal Surgery | S34: Abdominal Surgery | T34: Surgical Oncology | W34: ID00005 | X34: HU Pitié-Salpêtrière | AC34: France
I35: Head of department treating pancreatic cancer | J35: Head of Hepatology and Gastroenterology Department where consultations for pancreatic tumours take place. | K35: 608464720000730120 | M35: Dominique Thabut | Q35: =IF(COUNTIFS(HCP_evidence!$A:$A, M35, HCP_evidence!$AB:$AB, "<>")>0, "Yes", "") -> Yes | W35: ID00005 | X35: HU Pitié-Salpêtrière
I36: Head of department treating pancreatic cancer | J36: Head of HEPATO-BILIO-PANCREATIC SURGERY AND LIVER TRANSPLANTATION where pancreatic cancer surgery takes place. | K36: 608464732516533274 | M36: Olivier Scatton | Q36: =IF(COUNTIFS(HCP_evidence!$A:$A, M36, HCP_evidence!$AB:$AB, "<>")>0, "Yes", "") -> Yes | W36: ID00005 | X36: HU Pitié-Salpêtrière
A37: 98 | J37: Doctor participating in the BACAP project | K37: 626077110695380003 | M37: Florence Renaud | N37: Florence Renaud | Q37: =IF(COUNTIFS(HCP_evidence!$A:$A, M37, HCP_evidence!$AB:$AB, "<>")>0, "Yes", "") | R37: Anatomic/Clinical Pathology | S37: Anatomic/Clinical Pathology | W37: ID00005 | X37: HU Pitié-Salpêtrière | AC37: France | AS37: Yes | AW37: =IF(COUNTIFS(HCP_evidence!$A:$A, M37, HCP_evidence!$AH:$AH, "<>")>0, "Yes", "")
A38: 109 | I38: Works in department where pancreatic cancer is treated | J38: Honorary Members of ESPOIR, Contact clinical trial | K38: 932488783055359327 | M38: Paul Gougis | Q38: =IF(COUNTIFS(HCP_evidence!$A:$A, M38, HCP_evidence!$AB:$AB, "<>")>0, "Yes", "") | R38: Medical Oncology | S38: Medical Oncology | W38: ID00005 | X38: HU Pitié-Salpêtrière | AC38: France | AT38: Yes | AW38: =IF(COUNTIFS(HCP_evidence!$A:$A, M38, HCP_evidence!$AH:$AH, "<>")>0, "Yes", "")
A39: 144 | I39: Works in department where pancreatic cancer is treated | J39: Co-author with Bachet of current 2026 pancreatic cancer publication; works in digestive oncology. Works in department where pancreatic cancer is diagnosed. | K39: 929850130490262047 | M39: Leo Mas | N39: Léo Mas | Q39: =IF(COUNTIFS(HCP_evidence!$A:$A, M39, HCP_evidence!$AB:$AB, "<>")>0, "Yes", "") | W39: ID00005 | X39: HU Pitié-Salpêtrière | AC39: France | AW39: =IF(COUNTIFS(HCP_evidence!$A:$A, M39, HCP_evidence!$AH:$AH, "<>")>0, "Yes", "")
B40: KOL | C40: Tier 3 | I40: Head of department treating pancreatic cancer | J40: Head of visceral and digestive surgery where pancreatic cancer surgery takes place. Lead of the study CANCER PROFILE - PREDICTIVE AND PERSONALIZED MEDICINE OF PANCREATIC CANCER | K40: 626080317844767747 | L40: https://www.chru-strasbourg.fr/praticien/pessaux-patrick/ | M40: Patrick Pessaux | N40: Patrick Pessaux | Q40: =IF(COUNTIFS(HCP_evidence!$A:$A, M40, HCP_evidence!$AB:$AB, "<>")>0, "Yes", "") -> Yes | S40: Abdominal Surgery | W40: ID00006 | X40: Nouvel Hôpital Civil | AC40: France
A41: 122 | I41: Head of department treating pancreatic cancer | J41: Member of the research committee of Societe Francaise Pancreas. Medical director of Hepatogastroenterology where pancreatic cancer is diagnosed. | K41: 802041905075471361 | M41: Pierre Mayer | N41: Pierre Mayer | Q41: =IF(COUNTIFS(HCP_evidence!$A:$A, M41, HCP_evidence!$AB:$AB, "<>")>0, "Yes", "") -> Yes | R41: Gastroenterology | S41: Gastroenterology | W41: ID00006 | X41: Nouvel Hôpital Civil | AC41: France | AU41: Yes | AW41: =IF(COUNTIFS(HCP_evidence!$A:$A, M41, HCP_evidence!$AH:$AH, "<>")>0, "Yes", "")
I42: Works in department where pancreatic cancer is treated | J42: Works in department where pancreatic cancer surgery takes place. First author on international pancreatic carcinoma outcome-standard work with Pessaux | K42: 932692518697897340 | L42: https://www.chru-strasbourg.fr/praticien/cherkaoui-zineb/ | M42: Zineb Cherkaoui | N42: Zineb Cherkaoui | Q42: =IF(COUNTIFS(HCP_evidence!$A:$A, M42, HCP_evidence!$AB:$AB, "<>")>0, "Yes", "") | W42: ID00006 | X42: Nouvel Hôpital Civil
B43: KOL | C43: Tier 1 | D43: Yes | I43: Head of department treating pancreatic cancer | J43: Michel Ducreux is head of the gastro-digestive committee at Gustave Roussy where pancreatic cancer is treated. | K43: 560996104489927694 | L43: https://www.gustaveroussy.fr/fr/michel-ducreux | M43: Michel Ducreux | N43: Michel Ducreux | Q43: =IF(COUNTIFS(HCP_evidence!$A:$A, M43, HCP_evidence!$AB:$AB, "<>")>0, "Yes", "") -> Yes | R43: Gastroenterology | S43: Gastroenterology | T43: Medical Oncology | W43: ID00007 | X43: Institut Gustave Roussy | AC43: France | AV43: Scientific Council | AW43: =IF(COUNTIFS(HCP_evidence!$A:$A, M43, HCP_evidence!$AH:$AH, "<>")>0, "Yes", "")
B44: KOL | C44: Tier 1 | I44: Works in department where pancreatic cancer is treated | J44: Works in the digestive department where pancreatic cancer is treated. Principal investigator | K44: 560999896677614593 | M44: Antoine Hollebecque | N44: Antoine Hollebecque | Q44: =IF(COUNTIFS(HCP_evidence!$A:$A, M44, HCP_evidence!$AB:$AB, "<>")>0, "Yes", "") | R44: Medical Oncology | S44: Medical Oncology | W44: ID00007 | X44: Institut Gustave Roussy | AC44: France | AW44: =IF(COUNTIFS(HCP_evidence!$A:$A, M44, HCP_evidence!$AH:$AH, "<>")>0, "Yes", "")
A45: 112 | B45: KOL | C45: Tier 2 | I45: Works in department where pancreatic cancer is treated | J45: Member of the research committee of Societe Francaise Pancreas. Works in the digestive team where pancreatic cancer is treated. | K45: 930284396249481759 | M45: Alice Boilève | N45: Alice Boilève | Q45: =IF(COUNTIFS(HCP_evidence!$A:$A, M45, HCP_evidence!$AB:$AB, "<>")>0, "Yes", "") | R45: Medical Oncology | S45: Medical Oncology | W45: ID00007 | X45: Institut Gustave Roussy | AC45: France | AU45: Yes | AW45: =IF(COUNTIFS(HCP_evidence!$A:$A, M45, HCP_evidence!$AH:$AH, "<>")>0, "Yes", "") | BA45: Yes
I46: Works in department where pancreatic cancer is treated | J46: Part of the team for digestive cancers where pancreatic cancer is treated. Contact person clinical trial. | K46: 626079383320282133 | M46: Maximiliano Gelli | N46: Maximiliano Gelli | Q46: =IF(COUNTIFS(HCP_evidence!$A:$A, M46, HCP_evidence!$AB:$AB, "<>")>0, "Yes", "") | R46: General Surgery | S46: General Surgery | T46: Surgical Oncology | U46: Transplant Surgery | W46: ID00007 | X46: Institut Gustave Roussy | AC46: France
I47: Works in department where pancreatic cancer is treated | J47: Works in the digestive department where pancreatic canceris treated | K47: 879720844534760448 | M47: Cristina Smolenschi | N47: Cristina Smolenschi | Q47: =IF(COUNTIFS(HCP_evidence!$A:$A, M47, HCP_evidence!$AB:$AB, "<>")>0, "Yes", "") | R47: Medical Oncology | W47: ID00007 | X47: Institut Gustave Roussy | AC47: France
I48: Head of department treating pancreatic cancer | J48: Heads the department that explicitly operates hepatobiliary-pancreatic cancers. | K48: 560997242077447169 | M48: Charles Honoré | Q48: =IF(COUNTIFS(HCP_evidence!$A:$A, M48, HCP_evidence!$AB:$AB, "<>")>0, "Yes", "") | W48: ID00007 | X48: Institut Gustave Roussy
I49: Works in department where pancreatic cancer is treated | J49: Endoscopist in the department of digestive cancer who perform EUS. Pancreatic cancer is treated in this department | K49: 626077559947281409 | M49: Hichem Belkhodja | Q49: =IF(COUNTIFS(HCP_evidence!$A:$A, M49, HCP_evidence!$AB:$AB, "<>")>0, "Yes", "") | W49: ID00007 | X49: Institut Gustave Roussy
I50: Works in department where pancreatic cancer is treated | J50: Endoscopist in the department of digestive cancer who perform EUS. Pancreatic cancer is treated in this department | K50: 626079453667148805 | M50: Simona Cosconea Cioac | Q50: =IF(COUNTIFS(HCP_evidence!$A:$A, M50, HCP_evidence!$AB:$AB, "<>")>0, "Yes", "") | W50: ID00007 | X50: Institut Gustave Roussy
J51: Reviewer guideline pancreatic cancer. | K51: 626077268535428097 | M51: Léonor Benhaim | Q51: =IF(COUNTIFS(HCP_evidence!$A:$A, M51, HCP_evidence!$AB:$AB, "<>")>0, "Yes", "") | W51: ID00007 | X51: Institut Gustave Roussy
A52: 105 | B52: KOL | C52: Tier 1 | I52: Head of department treating pancreatic cancer | J52: Honorary Members of ESPOIR. Author of the Pancreatic cancer guide for ARCAD. Head of the rapid pancreas diagnostic centre. Principal investigator clinical trial. | K52: 608464695648601124 | M52: Pascal Hammel | N52: Pascal Hammel | Q52: =IF(COUNTIFS(HCP_evidence!$A:$A, M52, HCP_evidence!$AB:$AB, "<>")>0, "Yes", "") -> Yes | R52: Gastroenterology | S52: Gastroenterology | W52: ID00008 | X52: Hôpital Paul Brousse | AC52: France | AT52: Yes | AW52: =IF(COUNTIFS(HCP_evidence!$A:$A, M52, HCP_evidence!$AH:$AH, "<>")>0, "Yes", "")
A53: 111 | B53: KOL | C53: Tier 1 | D53: Yes | I53: Works in department where pancreatic cancer is treated | J53: Member of the research committee of Societe Francaise Pancreas. Head of department of digestive oncology where pancreatic cancer is treated. Principal investigator clinical trial. Reviewer of the guideline on PDAC, Contact clinical trial | K53: 931299959855776303 | L53: https://curie.fr/personne/cindy-neuzillet | M53: Cindy Neuzillet | N53: Cindy Neuzillet | Q53: =IF(COUNTIFS(HCP_evidence!$A:$A, M53, HCP_evidence!$AB:$AB, "<>")>0, "Yes", "") -> Yes | R53: Gastroenterology | S53: Gastroenterology | W53: ID00008 | X53: Hôpital Paul Brousse | AC53: France | AU53: Yes | AW53: =IF(COUNTIFS(HCP_evidence!$A:$A, M53, HCP_evidence!$AH:$AH, "<>")>0, "Yes", "") | AZ53: Yes
J54: Contact person clinical trial | K54: 931916314406421023 | M54: Daniel Pietrasz | N54: Daniel Pietrasz | Q54: =IF(COUNTIFS(HCP_evidence!$A:$A, M54, HCP_evidence!$AB:$AB, "<>")>0, "Yes", "") | W54: ID00008 | X54: Hôpital Paul Brousse | AC54: France
A55: 212 | J55: Pancreatic cancer is treated in this departement | K55: 608464737851687954 | L55: https://www.aphp.fr/pr-sa-cunha-antonio | M55: Antonio Sa Cunha | Q55: =IF(COUNTIFS(HCP_evidence!$A:$A, M55, HCP_evidence!$AB:$AB, "<>")>0, "Yes", "") | W55: ID00008 | X55: Hôpital Paul Brousse | AC55: France | AW55: =IF(COUNTIFS(HCP_evidence!$A:$A, M55, HCP_evidence!$AH:$AH, "<>")>0, "Yes", "")
A56: 188 | B56: KOL | C56: Tier 3 | I56: Head of department treating pancreatic cancer | J56: Head of the department of Gastroenterology and Digestive Oncology Department where pancreatic cancer is treated. Reviewer of the guideline on PDAC. Explicitly named in Cochin's gastroenterology and pancreatology team for pancreatic lesions. | K56: 608464719388361742 | M56: Romain Coriat | N56: Romain Coriat | Q56: =IF(COUNTIFS(HCP_evidence!$A:$A, M56, HCP_evidence!$AB:$AB, "<>")>0, "Yes", "") -> Yes | R56: Gastroenterology | S56: Gastroenterology | W56: ID00009 | X56: Hôpital Cochin | AC56: France | AW56: =IF(COUNTIFS(HCP_evidence!$A:$A, M56, HCP_evidence!$AH:$AH, "<>")>0, "Yes", "")
E57: Yes | I57: Head of department treating pancreatic cancer | J57: Heads the Department of Digestive, Hepatobiliary and Endocrine Surgery Cochin Hospital APHP Center where pancreatic cancer is treated. Reference point for the rapid pancreas diagnostic centre. Principal investigator clinical trial. Explicitly named in Cochin's pancreatic-lesion rapid-diagnosis team as a pancreatic digestive surgeon. | K57: 929771110843875895 | M57: Ugo Marchese | N57: Ugo Marchese | Q57: =IF(COUNTIFS(HCP_evidence!$A:$A, M57, HCP_evidence!$AB:$AB, "<>")>0, "Yes", "") -> Yes | R57: Abdominal Surgery | S57: Abdominal Surgery | T57: Hepatobiliary Surgery | W57: ID00009 | X57: Hôpital Cochin | AC57: France
A58: 143 | I58: Works in department where pancreatic cancer is treated | J58: Member of the teaching committee of Societe Francaise Pancreas | K58: 930132905685287455 | M58: Anna Pellat | N58: Anna Pellat | Q58: =IF(COUNTIFS(HCP_evidence!$A:$A, M58, HCP_evidence!$AB:$AB, "<>")>0, "Yes", "") | R58: Gastroenterology | S58: Gastroenterology | W58: ID00009 | X58: Hôpital Cochin | AC58: France | AU58: Yes | AW58: =IF(COUNTIFS(HCP_evidence!$A:$A, M58, HCP_evidence!$AH:$AH, "<>")>0, "Yes", "")
E59: Yes | I59: Works in department where pancreatic cancer is treated | J59: Works in the Department of Digestive, Hepatobiliary and Endocrine Surgery Cochin Hospital APHP Center where pancreatic cancer is treated | K59: 934035450795920741 | M59: Stylianos Tzedakis | N59: Stylianos Tzedakis | Q59: =IF(COUNTIFS(HCP_evidence!$A:$A, M59, HCP_evidence!$AB:$AB, "<>")>0, "Yes", "") | R59: Abdominal Surgery | S59: Abdominal Surgery | T59: Hepatobiliary Surgery | W59: ID00009 | X59: Hôpital Cochin
I60: Pathologist involved in pancreatic cancer | J60: Reviewer of the guideline on PDAC | K60: 608464659460146194 | M60: Benoît Terris | Q60: =IF(COUNTIFS(HCP_evidence!$A:$A, M60, HCP_evidence!$AB:$AB, "<>")>0, "Yes", "") | W60: ID00009 | X60: Hôpital Cochin
I61: Works in department where pancreatic cancer is treated | J61: Specifically named in the pancreatic pathway's interventional endoscopy team. | K61: 626078431347491844 | M61: Arthur Belle | Q61: =IF(COUNTIFS(HCP_evidence!$A:$A, M61, HCP_evidence!$AB:$AB, "<>")>0, "Yes", "") | W61: ID00009 | X61: Hôpital Cochin
I62: Works in department where pancreatic cancer is treated | J62: Explicitly named among Cochin's pancreatic digestive surgeons in the pancreatic rapid-diagnosis pathway. | K62: 560996976485729292 | M62: Bertrand Dousset | Q62: =IF(COUNTIFS(HCP_evidence!$A:$A, M62, HCP_evidence!$AB:$AB, "<>")>0, "Yes", "") | W62: ID00009 | X62: Hôpital Cochin
I63: Works in department where pancreatic cancer is treated | J63: Explicitly named among Cochin's pancreatic digestive surgeons in the pancreatic rapid-diagnosis pathway. | K63: 626077826788901892 | M63: Pierre-Philippe Massault | Q63: =IF(COUNTIFS(HCP_evidence!$A:$A, M63, HCP_evidence!$AB:$AB, "<>")>0, "Yes", "") | W63: ID00009 | X63: Hôpital Cochin
I64: Works in department where pancreatic cancer is treated | J64: Explicitly named in Cochin's gastroenterology and pancreatology team for pancreatic lesions. | K64: 608464691152307237 | M64: Marion Dhooge | Q64: =IF(COUNTIFS(HCP_evidence!$A:$A, M64, HCP_evidence!$AB:$AB, "<>")>0, "Yes", "") | W64: ID00009 | X64: Hôpital Cochin
I65: Works in department where pancreatic cancer is treated | J65: Principal investigator clinical trial | K65: 626078472359396386 | M65: Catherine Brezault-Bonnet | Q65: =IF(COUNTIFS(HCP_evidence!$A:$A, M65, HCP_evidence!$AB:$AB, "<>")>0, "Yes", "") | W65: ID00009 | X65: Hôpital Cochin
A66: 191 | B66: KOL | C66: Tier 2 | I66: Head of department treating pancreatic cancer | J66: Clinical Trial Coordinator. Prepared the guide Pancreatic Cancer in Questions published by thr ARCAD Foundation for Espoir Pancreas. heads the service explicitly treating pancreatic cancer. Principal investagator clinical trial | K66: 608464618649568260 | L66: https://www.aphp.fr/pr-taieb-julien | M66: Julien Taieb | N66: Julien Taïeb | Q66: =IF(COUNTIFS(HCP_evidence!$A:$A, M66, HCP_evidence!$AB:$AB, "<>")>0, "Yes", "") -> Yes | R66: Gastroenterology | S66: Gastroenterology | V66: 608464600169464832 | W66: ID00010 | X66: Hôpital Européen Georges-Pompidou | AC66: France | AW66: =IF(COUNTIFS(HCP_evidence!$A:$A, M66, HCP_evidence!$AH:$AH, "<>")>0, "Yes", "")
I67: Head of department treating pancreatic cancer | J67: Heads the surgical service explicitly treating pancreatic cancer. | K67: 846225154492072962 | M67: Mehdi Karoui | Q67: =IF(COUNTIFS(HCP_evidence!$A:$A, M67, HCP_evidence!$AB:$AB, "<>")>0, "Yes", "") -> Yes | V67: 608464600169464832 | W67: ID00010 | X67: Hôpital Européen Georges-Pompidou
I68: Head of department treating pancreatic cancer | J68: Heads the service specialising in pancreatic and biliary disease, including pancreatic cancer. | K68: 560999511573398537 | M68: Christophe Cellier | Q68: =IF(COUNTIFS(HCP_evidence!$A:$A, M68, HCP_evidence!$AB:$AB, "<>")>0, "Yes", "") -> Yes | V68: 608464600169464832 | W68: ID00010 | X68: Hôpital Européen Georges-Pompidou
I69: Head of department treating pancreatic cancer | J69: Contact person clinical trial. Head of department treating pancreatic cancer. | K69: 626077336273437711 | M69: Faiza Khemissa | Q69: =IF(COUNTIFS(HCP_evidence!$A:$A, M69, HCP_evidence!$AB:$AB, "<>")>0, "Yes", "") -> Yes | AC69: France
D70: Yes | J70: Part of the team treating pancreatic cancer | K70: 560997480154530817 | L70: https://www.institutpaolicalmettes.fr/annuaire_soignants/dr-fabrice-caillol/ | M70: Fabrice Caillol | N70: Fabrice Caillol | Q70: =IF(COUNTIFS(HCP_evidence!$A:$A, M70, HCP_evidence!$AB:$AB, "<>")>0, "Yes", "") | R70: Gastroenterology | S70: Gastroenterology | W70: ID00011 | X70: Institut Paoli-Calmettes
D71: Yes | I71: Part of the team for pancreatic cancer | J71: Part of the team treating pancreatic cancer | K71: 560997702226150424 | L71: https://www.institutpaolicalmettes.fr/annuaire_soignants/dr-jacques-ewald/ | M71: Jacques Ewald | N71: Jacques Ewald | Q71: =IF(COUNTIFS(HCP_evidence!$A:$A, M71, HCP_evidence!$AB:$AB, "<>")>0, "Yes", "") | R71: Abdominal Surgery | S71: Abdominal Surgery | W71: ID00011 | X71: Institut Paoli-Calmettes
D72: Yes | J72: Part of the team treating pancreatic cancer | K72: 561000070623790083 | L72: https://www.institutpaolicalmettes.fr/annuaire_soignants/dr-carole-tarpin/ | M72: Carole Tarpin | Q72: =IF(COUNTIFS(HCP_evidence!$A:$A, M72, HCP_evidence!$AB:$AB, "<>")>0, "Yes", "") | R72: Medical Oncology | S72: Medical Oncology | W72: ID00011 | X72: Institut Paoli-Calmettes
D73: Yes | J73: Part of the team treating pancreatic cancer | K73: 621591892789838872 | L73: https://www.institutpaolicalmettes.fr/annuaire_soignants/iangonantsoa-jemima-maniry/ | M73: Jémima Quellier | Q73: =IF(COUNTIFS(HCP_evidence!$A:$A, M73, HCP_evidence!$AB:$AB, "<>")>0, "Yes", "") | R73: Medical Oncology | S73: Medical Oncology | W73: ID00011 | X73: Institut Paoli-Calmettes
B74: KOL | C74: Tier 2 | D74: Yes | I74: Head of department treating pancreatic cancer | J74: Head of the Department of Oncological Surgery 1 where pancreatic cancer is treated. Scientific committee pancreatic cancer congress | K74: 560999587666461705 | L74: https://www.institutpaolicalmettes.fr/annuaire_soignants/pr-olivier-turrini/ | M74: Olivier Turrini | N74: Olivier Turrini | Q74: =IF(COUNTIFS(HCP_evidence!$A:$A, M74, HCP_evidence!$AB:$AB, "<>")>0, "Yes", "") -> Yes | R74: Abdominal Surgery | S74: Abdominal Surgery | T74: Surgical Oncology | W74: ID00011 | X74: Institut Paoli-Calmettes | AC74: France
D75: Yes | J75: Part of the team treating pancreatic cancer | K75: 626078855811056656 | L75: https://www.institutpaolicalmettes.fr/annuaire_soignants/dr-jean-philippe-ratone/ | M75: Jean-Philippe Ratone | Q75: =IF(COUNTIFS(HCP_evidence!$A:$A, M75, HCP_evidence!$AB:$AB, "<>")>0, "Yes", "") | R75: Gastroenterology | S75: Gastroenterology | W75: ID00011 | X75: Institut Paoli-Calmettes
B76: KOL | C76: Tier 1 | J76: Co-president of the French Association for Research on Pancreatic Cancer. Principal investigator clinical trial. | K76: 936332391593282911 | M76: Jean Emmanuel Mitry | N76: Emmanuel Mitry | Q76: =IF(COUNTIFS(HCP_evidence!$A:$A, M76, HCP_evidence!$AB:$AB, "<>")>0, "Yes", "") | R76: Gastroenterology | S76: Gastroenterology | W76: ID00011 | X76: Institut Paoli-Calmettes | AC76: France | AW76: =IF(COUNTIFS(HCP_evidence!$A:$A, M76, HCP_evidence!$AH:$AH, "<>")>0, "Yes", "") | AY76: Yes | AZ76: Yes | BA76: Yes
B77: KOL | C77: Tier 1 | J77: Reviewer guideline pancreatic cancer. | K77: 626078629821957128 | M77: Christelle De La Fouchardiere | N77: Christelle de la Fouchardière | Q77: =IF(COUNTIFS(HCP_evidence!$A:$A, M77, HCP_evidence!$AB:$AB, "<>")>0, "Yes", "") | S77: Medical Oncology | W77: ID00011 | X77: Institut Paoli-Calmettes | AC77: France | BC77: Yes
B78: KOL | C78: Tier 2 | J78: Inactive in Veeva. President pancreatic cancer congress. Principal investagator clinical trial | K78: 560999742176232449 | M78: Jean Robert Delpero | N78: Jean-Robert Delpero | Q78: =IF(COUNTIFS(HCP_evidence!$A:$A, M78, HCP_evidence!$AB:$AB, "<>")>0, "Yes", "") | S78: Gastroenterology | W78: ID00011 | X78: Institut Paoli-Calmettes | AC78: France
D79: Yes | I79: Part of the team for pancreatic cancer | J79: He practices as a general medical oncologist, particularly involved in hepatobiliary and pancreatic cancers, breast cancer, and lung cancer. Since 2017, he has been head of the Medical Oncology 1 departmentwhere pancreatic cancer is treated. Part of the team treating pancreatic cancer | K79: 929771110846038584 | L79: https://www.institutpaolicalmettes.fr/annuaire_soignants/dr-simon-launay/ | M79: Simon Launay | N79: Simon Launay | Q79: =IF(COUNTIFS(HCP_evidence!$A:$A, M79, HCP_evidence!$AB:$AB, "<>")>0, "Yes", "") -> Yes | W79: ID00011 | X79: Institut Paoli-Calmettes
D80: Yes | I80: Part of the team for pancreatic cancer | J80: Part of the team treating pancreatic cancer | K80: 930331340686230047 | L80: https://www.institutpaolicalmettes.fr/annuaire_soignants/dr-anais-palen/ | M80: Anais Palen | N80: Anaïs Palen | Q80: =IF(COUNTIFS(HCP_evidence!$A:$A, M80, HCP_evidence!$AB:$AB, "<>")>0, "Yes", "") | R80: Abdominal Surgery | S80: Abdominal Surgery | W80: ID00011 | X80: Institut Paoli-Calmettes
A81: 113 | J81: Clinical Trial Coordinator. Member of the research committee of Societe Francaise Pancreas. Deputy Coordinator/Director of the French Research Network against Pancreatic Adenocarcinoma. Principal investigator clinical trial. | K81: 930760642037154335 | M81: Brice Chanez | N81: Brice Chanez | Q81: =IF(COUNTIFS(HCP_evidence!$A:$A, M81, HCP_evidence!$AB:$AB, "<>")>0, "Yes", "") | R81: Medical Oncology | S81: Medical Oncology | W81: ID00011 | X81: Institut Paoli-Calmettes | AC81: France | AU81: Yes | AW81: =IF(COUNTIFS(HCP_evidence!$A:$A, M81, HCP_evidence!$AH:$AH, "<>")>0, "Yes", "") | AX81: Yes | AZ81: Yes
D82: Yes | I82: Part of the team for pancreatic cancer | J82: Part of the team treating pancreatic cancer. Principal investigator clinical trial. | K82: 931955619700933151 | L82: https://www.institutpaolicalmettes.fr/annuaire_soignants/dr-jonathan-garnier/ | M82: Jonathan Garnier | N82: Jonathan Garnier | Q82: =IF(COUNTIFS(HCP_evidence!$A:$A, M82, HCP_evidence!$AB:$AB, "<>")>0, "Yes", "") | S82: Abdominal Surgery | W82: ID00011 | X82: Institut Paoli-Calmettes
D83: Yes | J83: Part of the team treating pancreatic cancer. A gastroenterology specialist at the Paoli-Calmettes Institute, Dr. Mezzina specializes in endoscopic ultrasound and interventional endoscopy. His work at the Institute is dedicated to the practice of advanced endoscopic techniques, essential for the precise diagnosis and treatment of digestive oncological diseases. | K83: 947939478952941727 | L83: https://www.institutpaolicalmettes.fr/annuaire_soignants/dr-nicolo-mezzina-2/ | M83: Nicolo Mezzina | Q83: =IF(COUNTIFS(HCP_evidence!$A:$A, M83, HCP_evidence!$AB:$AB, "<>")>0, "Yes", "") | R83: Gastroenterology | S83: Gastroenterology | W83: ID00011 | X83: Institut Paoli-Calmettes
D84: Yes | J84: Working group Summary Initial_managemen of pancreatic adenocarcinoma cases | K84: 560999396699800579 | L84: https://www.scilit.com/scholars/13884039 | M84: Erwan Bories | Q84: =IF(COUNTIFS(HCP_evidence!$A:$A, M84, HCP_evidence!$AB:$AB, "<>")>0, "Yes", "") | W84: ID00152 | X84: Hôpital Privé de Provence
J85: President pancreatic cancer congress. | K85: 560999429306319875 | M85: Patrice Viens | Q85: =IF(COUNTIFS(HCP_evidence!$A:$A, M85, HCP_evidence!$AB:$AB, "<>")>0, "Yes", "") | W85: ID00011 | X85: Institut Paoli-Calmettes
J86: Scientific committee pancreatic cancer congress | K86: 626127782627263489 | M86: Patricia Niccoli | Q86: =IF(COUNTIFS(HCP_evidence!$A:$A, M86, HCP_evidence!$AB:$AB, "<>")>0, "Yes", "") | W86: ID00011 | X86: Institut Paoli-Calmettes
J87: Not a clear bio | K87: 691807269641274369 | M87: Cécile Bannier-Braticevic | Q87: =IF(COUNTIFS(HCP_evidence!$A:$A, M87, HCP_evidence!$AB:$AB, "<>")>0, "Yes", "") | W87: ID00011 | X87: Institut Paoli-Calmettes
A88: 99 | J88: Doctor participating in the BACAP project | K88: 626077471271306245 | M88: Emmanuelle Leteurtre | N88: Emmanuelle Leteurtre | Q88: =IF(COUNTIFS(HCP_evidence!$A:$A, M88, HCP_evidence!$AB:$AB, "<>")>0, "Yes", "") | R88: Anatomic/Clinical Pathology | S88: Anatomic/Clinical Pathology | W88: ID00012 | X88: Hôpital Claude Huriez | AC88: France | AS88: Yes | AW88: =IF(COUNTIFS(HCP_evidence!$A:$A, M88, HCP_evidence!$AH:$AH, "<>")>0, "Yes", "")
A89: 94 | J89: Lead investigator in the BACAP project. Principal investigator clinical trial. | K89: 626078758201213962 | M89: Stéphanie Truant | N89: Stéphanie Truant | Q89: =IF(COUNTIFS(HCP_evidence!$A:$A, M89, HCP_evidence!$AB:$AB, "<>")>0, "Yes", "") | R89: Abdominal Surgery | S89: Abdominal Surgery | T89: Hepatobiliary Surgery | U89: Surgical Oncology | W89: ID00012 | X89: Hôpital Claude Huriez | AC89: France | AS89: Yes | AW89: =IF(COUNTIFS(HCP_evidence!$A:$A, M89, HCP_evidence!$AH:$AH, "<>")>0, "Yes", "")
A90: 95 | J90: Lead investigator in the BACAP project. Principal investigator clinical trial. | K90: 626079034958169101 | M90: Guillaume Piessen | N90: Guillaume Piessen | Q90: =IF(COUNTIFS(HCP_evidence!$A:$A, M90, HCP_evidence!$AB:$AB, "<>")>0, "Yes", "") | R90: Abdominal Surgery | S90: Abdominal Surgery | T90: Surgical Oncology | W90: ID00012 | X90: Hôpital Claude Huriez | AC90: France | AS90: Yes | AW90: =IF(COUNTIFS(HCP_evidence!$A:$A, M90, HCP_evidence!$AH:$AH, "<>")>0, "Yes", "")
A91: 118 | B91: KOL | C91: Tier 1 | J91: Member of the research committee of Societe Francaise Pancreas. Deputy Coordinator/Director of the French Research Network against Pancreatic Adenocarcinoma. Contact clinical trial. | K91: 929085751782670879 | M91: Anthony Turpin | N91: Anthony Turpin | Q91: =IF(COUNTIFS(HCP_evidence!$A:$A, M91, HCP_evidence!$AB:$AB, "<>")>0, "Yes", "") | R91: Oncology | S91: Oncology | W91: ID00012 | X91: Hôpital Claude Huriez | AC91: France | AU91: Yes | AW91: =IF(COUNTIFS(HCP_evidence!$A:$A, M91, HCP_evidence!$AH:$AH, "<>")>0, "Yes", "") | AX91: Yes | BA91: Yes
A92: 96 | J92: Doctor participating in the BACAP project | K92: 669645584298165255 | M92: Guillaume Millet | Q92: =IF(COUNTIFS(HCP_evidence!$A:$A, M92, HCP_evidence!$AB:$AB, "<>")>0, "Yes", "") | R92: Abdominal Surgery | S92: Abdominal Surgery | T92: Surgical Oncology | W92: ID00012 | X92: Hôpital Claude Huriez | AC92: France | AS92: Yes | AW92: =IF(COUNTIFS(HCP_evidence!$A:$A, M92, HCP_evidence!$AH:$AH, "<>")>0, "Yes", "")
J93: Member of the teaching committee of Societe Francaise Pancreas. Performed research on PANCREATECTOMY after endoscopic astrojejunostomy (pancake) | K93: 930352929418248735 | M93: Mehdi El Amrani | N93: Medhi El Amrani | Q93: =IF(COUNTIFS(HCP_evidence!$A:$A, M93, HCP_evidence!$AB:$AB, "<>")>0, "Yes", "") | R93: Abdominal Surgery | S93: Abdominal Surgery | W93: ID00012 | X93: Hôpital Claude Huriez | AU93: Yes
J94: Contact person clinical trial | K94: 929771110859014712 | M94: Julie Veziant | N94: Julie Veziant | Q94: =IF(COUNTIFS(HCP_evidence!$A:$A, M94, HCP_evidence!$AB:$AB, "<>")>0, "Yes", "") | W94: ID00012 | X94: Hôpital Claude Huriez | AC94: France
B95: KOL | C95: Tier 1 | J95: Principal investigator clinical trial | K95: 621591848229553187 | M95: Thomas Walter | N95: Thomas Pierre Walter | Q95: =IF(COUNTIFS(HCP_evidence!$A:$A, M95, HCP_evidence!$AB:$AB, "<>")>0, "Yes", "") | R95: Oncology | S95: Oncology | W95: ID00013 | X95: Hôpital Édouard Herriot | AC95: France
B96: KOL | C96: Tier 3 | D96: Yes | I96: Works in department where pancreatic cancer is treated | J96: Responsible for pancreatic cancer within the department of visceral surgery | K96: 626127791913452550 | M96: Mustapha Adham | N96: Mustapha Adham | Q96: =IF(COUNTIFS(HCP_evidence!$A:$A, M96, HCP_evidence!$AB:$AB, "<>")>0, "Yes", "") | R96: Abdominal Surgery | S96: Abdominal Surgery | W96: ID00013 | X96: Hôpital Édouard Herriot | BC96: Yes
B97: KOL | C97: Tier 2 | J97: Specialized in neuroendocrine tumors and GI cancers. | K97: 931881467690091063 | L97: https://www.enets.org/y-nets-member/durand-alice.html | M97: Alice Durand | N97: Alice Durand | Q97: =IF(COUNTIFS(HCP_evidence!$A:$A, M97, HCP_evidence!$AB:$AB, "<>")>0, "Yes", "") | S97: Oncology | W97: ID00013 | X97: Hôpital Édouard Herriot | AC97: France | BB97: Yes
D98: Yes | I98: Works in department where pancreatic cancer is treated | J98: Responsible for pancreatic cancer within the department of visceral surgery, Principal investagator clinical trial | K98: 931469549561643551 | M98: Julie Perinel | Q98: =IF(COUNTIFS(HCP_evidence!$A:$A, M98, HCP_evidence!$AB:$AB, "<>")>0, "Yes", "") | W98: ID00013 | X98: Hôpital Édouard Herriot | AC98: France | BB98: Yes | BC98: Yes
J99: Reviewer of the guideline on PDAC | K99: 621591913526477828 | M99: Julien Forestier | Q99: =IF(COUNTIFS(HCP_evidence!$A:$A, M99, HCP_evidence!$AB:$AB, "<>")>0, "Yes", "") | W99: ID00013 | X99: Hôpital Édouard Herriot | AC99: France
J100: Reviewer guideline pancreatic cancer. | K100: 626078402910110727 | M100: Tullio Piardi | N100: Tullio Piardi | Q100: =IF(COUNTIFS(HCP_evidence!$A:$A, M100, HCP_evidence!$AB:$AB, "<>")>0, "Yes", "") | R100: Abdominal Surgery | S100: Abdominal Surgery | W100: ID00014 | X100: Hôpital Robert Debré | AC100: France
...

Sheet HCP_evidence
A1: Full name | C1: Biolink | D1: Guidelines | H1: Clinicial Trials and Keywords | I1: Clinical Trials_Link | J1: Unreseclatble | K1: Metastatic | M1: KRAS/RAS mutation | N1: Pancreatic Cancer | Q1: Publications | Z1: Speaking Events | AB1: Associations, Key Centers/Departments | AC1: Espoir Pancreas Patient Association | AD1: Pancreatic Cancer Conference | AE1: BACAP Partner | AF1: Societe Francaise Pancreas | AG1: ARCAD | AH1: Genetics and Cancer Group
B2: Check | D2: Guidelines Pancreatic Cancer | E2: Link | F2: Guideline Reviewer Pancreatic Cancer | G2: Link | H2: Clinical trial Title | I2: Link | J2: Unresectable | K2: Metastatic | L2: PDAC OR Pancreatic Adenocarcinoma | M2: KRAS mutation | N2: Pancreatic cancer | O2: Clinical trial Non-pancreatic specific | P2: Link | Q2: Publications - Pancreatic Cancer | R2: link | S2: PDAC or Pancreatic Adenocarcinoma | T2: link | U2: Publications - KRAS (KRAS & pancreatic cancer) | V2: link | W2: Publications - Molecular Oncology (e.g. profiling) | X2: Publications - Personalized medicine | Y2: Publications - Next Generation Sequencing | Z2: Speaking Pancreatic Cancer | AA2: Link | AB2: Head of Department | AC2: Espoir Pancreas Patient Association | AD2: Pancreatic Cancer Conference | AE2: BACAP Partner | AF2: Societe Francaise Pancreas | AG2: ARCAD | AH2: Genetics and Cancer Group
A3: Abdelkader Taibi | B3: =IF(COUNTIF(HCPs!M:M,HCP_evidence!A3)>0,"Yes","No") -> Yes | H3: Superior Mesenteric Artery First Versus Standard Approach in Pancreaticoduodenectomy | I3: https://clinicaltrials.gov/study/NCT07547033 | L3: Yes | N3: Yes
A4: Adeline Germain | B4: =IF(COUNTIF(HCPs!M:M,HCP_evidence!A4)>0,"Yes","No") -> Yes | F4: CONDUITES À TENIR DEVANT DES PATIENTS ATTEINTS D’ADÉNOCARCINOME DU PANCRÉAS | G4: https://ressources-aura.fr/wp-content/uploads/2020/01/Thesaurus_CAT_patients_atteints_adenocarcinomes_pancreas_mel_20191118.pdf
A5: Adrian Culetto | B5: =IF(COUNTIF(HCPs!M:M,HCP_evidence!A5)>0,"Yes","No") -> Yes | L5: Yes | AE5: https://www.bacap-pancreas.fr/fr/partenaires/
A6: Adrien Melis | B6: =IF(COUNTIF(HCPs!M:M,HCP_evidence!A6)>0,"Yes","No") -> Yes | H6: Randomized Phase II Study for Metastatic Pancreatic Cancers Comparing 5-FU/LV+Nal-IRI, versus gemcitabine+Nab-paclitaxel versus a sequential regimen alternating 5-FU/LV+Nal-IRI and gemcitabine+Nab-paclitaxel every 2 months | I6: https://www.ffcd.fr/index.php/recherche/essais-therapeutiques | K6: Yes | L6: Yes
A7: Agnès Tallet-Richard | B7: =IF(COUNTIF(HCPs!M:M,HCP_evidence!A7)>0,"Yes","No") -> Yes | H7: Evaluation of the Stereotactic MR-guided Adaptive Radiotherapy for Locally Advanced Pancreatic Cancers | I7: https://clinicaltrials.gov/study/NCT07097064 | L7: Yes | N7: Yes
A8: Ahmet Ayav | B8: =IF(COUNTIF(HCPs!M:M,HCP_evidence!A8)>0,"Yes","No") -> Yes | H8: Superior Mesenteric Artery First Versus Standard Approach in Pancreaticoduodenectomy | I8: https://clinicaltrials.gov/study/NCT07547033 | L8: Yes | N8: Yes
A9: Ahmet Ayav | B9: =IF(COUNTIF(HCPs!M:M,HCP_evidence!A9)>0,"Yes","No") -> Yes | F9: CONDUITES À TENIR DEVANT DES PATIENTS ATTEINTS D’ADÉNOCARCINOME DU PANCRÉAS | G9: https://ressources-aura.fr/wp-content/uploads/2020/01/Thesaurus_CAT_patients_atteints_adenocarcinomes_pancreas_mel_20191118.pdf
A10: Ahmet Ayav | B10: =IF(COUNTIF(HCPs!M:M,HCP_evidence!A10)>0,"Yes","No") -> Yes | Z10: Cancer du pancréas : débat sur la chimiothérapie néoadjuvante dans les cancers résécables d’emblée | AA10: https://www.onco-grandest.fr/wp-content/uploads/2026/05/Prog-prev_Dig-2026-au-260526.pdf
A11: Aimery de Gramont | B11: =IF(COUNTIF(HCPs!M:M,HCP_evidence!A11)>0,"Yes","No") -> Yes | L11: Yes | AC11: https://www.espoir-pancreas.fr/association-familles-entraide/
A12: Alain Sauvanet | B12: =IF(COUNTIF(HCPs!M:M,HCP_evidence!A12)>0,"Yes","No") -> Yes | H12: Superior Mesenteric Artery First Versus Standard Approach in Pancreaticoduodenectomy | I12: https://clinicaltrials.gov/study/NCT07547033 | L12: Yes | N12: Yes
A13: Alain Sauvanet | B13: =IF(COUNTIF(HCPs!M:M,HCP_evidence!A13)>0,"Yes","No") -> Yes | D13: CONDUITES À TENIR DEVANT DES PATIENTS ATTEINTS D’ADÉNOCARCINOME DU PANCRÉAS | E13: https://ressources-aura.fr/wp-content/uploads/2020/01/Thesaurus_CAT_patients_atteints_adenocarcinomes_pancreas_mel_20191118.pdf
A14: Alain Sauvanet | B14: =IF(COUNTIF(HCPs!M:M,HCP_evidence!A14)>0,"Yes","No") -> Yes | Z14: SESSION 2 CLINICAL PRACTICE | AA14: https://www.onco-hdf.fr/app/uploads/2019/11/Pancreatic-Cancer-1511.pdf
A15: Alain Sauvanet | B15: =IF(COUNTIF(HCPs!M:M,HCP_evidence!A15)>0,"Yes","No") -> Yes | Z15: SESSION 3 LOCAL THERAPIES | AA15: https://www.onco-hdf.fr/app/uploads/2019/11/Pancreatic-Cancer-1511.pdf
A16: Alain Sauvanet | B16: =IF(COUNTIF(HCPs!M:M,HCP_evidence!A16)>0,"Yes","No") -> Yes | F16: Cancer du pancréas – Chapitre 9, Thésaurus National de Cancérologie Digestive | G16: https://www.snfge.org/tncd/cancer-du-pancreas
A17: Albert Aleba | B17: =IF(COUNTIF(HCPs!M:M,HCP_evidence!A17)>0,"Yes","No") -> Yes | H17: Randomized Phase II Study for Metastatic Pancreatic Cancers Comparing 5-FU/LV+Nal-IRI, versus gemcitabine+Nab-paclitaxel versus a sequential regimen alternating 5-FU/LV+Nal-IRI and gemcitabine+Nab-paclitaxel every 2 months | I17: https://www.ffcd.fr/index.php/recherche/essais-therapeutiques | K17: Yes | L17: Yes
A18: Alexandre Doussot | B18: =IF(COUNTIF(HCPs!M:M,HCP_evidence!A18)>0,"Yes","No") -> Yes | H18: Superior Mesenteric Artery First Versus Standard Approach in Pancreaticoduodenectomy | I18: https://clinicaltrials.gov/study/NCT07547033 | L18: Yes | N18: Yes
A19: Alexandre Doussot | B19: =IF(COUNTIF(HCPs!M:M,HCP_evidence!A19)>0,"Yes","No") -> Yes | Z19: Management of pancreatic cancer – Part 1 | AA19: https://www.canceropole-est.org/journee-cancer-du-pancreas/
A20: Alexis Laurent | B20: =IF(COUNTIF(HCPs!M:M,HCP_evidence!A20)>0,"Yes","No") -> Yes | H20: Adjuvant Tumor-Stage Chemotherapy for Pancreatic Adenocarcinoma Operated After Neoadjuvant Chemotherapy with FOLFIRINOX - Phase II/III Multicenter Randomized Comparative Trial, FRENCH-PRODIGE | I20: https://www.ffcd.fr/index.php/recherche/essais-therapeutiques | K20: Yes | L20: Yes
A21: Alice Boilève | B21: =IF(COUNTIF(HCPs!M:M,HCP_evidence!A21)>0,"Yes","No") -> Yes | H21: Personalized neoadjuvant chemotherapy with RNA signature for patients with borderline pancreatic adenocarcinoma | I21: https://www.ffcd.fr/index.php/recherche/essais-therapeutiques | L21: Yes
A22: Alice Boilève | B22: =IF(COUNTIF(HCPs!M:M,HCP_evidence!A22)>0,"Yes","No") -> Yes | L22: Yes | AF22: https://www.societefrancaisepancreas.fr/commission-recherche/
A23: Alice Boilève | B23: =IF(COUNTIF(HCPs!M:M,HCP_evidence!A888)>0,"Yes","No") -> Yes | H23: Yoda | I23: https://www.fondationarcad.org/projets/yoda/
A24: Amandine Bruyas | B24: =IF(COUNTIF(HCPs!M:M,HCP_evidence!A23)>0,"Yes","No") -> Yes | L24: Yes | N24: Yes | O24: Predictive Value of Progastrin Titer at Diagnosis and of Progastrin Kinetics During Treatment in Cancer Patients | P24: https://clinicaltrials.gov/study/NCT03787056
A25: Amandine Bruyas | B25: =IF(COUNTIF(HCPs!M:M,HCP_evidence!A24)>0,"Yes","No") -> Yes | L25: Yes | N25: Yes | O25: Predictive Value of Progastrin Titer at Diagnosis and of Progastrin Kinetics During Treatment in Cancer Patients | P25: https://clinicaltrials.gov/study/NCT03787056
A26: Ana Hennino | B26: =IF(COUNTIF(HCPs!M:M,HCP_evidence!A25)>0,"Yes","No") -> Yes | H26: RASolute 304: A Phase 3 Multicenter, Open-label, Randomized, 2‑Arm Study of Adjuvant Daraxonrasib Versus Standard of Care Observation Following Completion of Neoadjuvant and/or Adjuvant Chemotherapy in Patients with Resected Pancreatic Ductal Adenocarcinoma (PDAC) | I26: https://www.sante.fr/essais-cliniques/2025-523495-23-00/rasolute-304-a-phase-3-multicenter-open-label-randomized-2-arm-study-of-adjuvant-daraxonrasib-versus-standard-of-care-observation-following-completion-of-neoadjuvant-and-or-adjuvant-chemotherapy-in-patients-with-resected-pancreatic-ductal-adenocarcinoma-pdac | L26: Yes | M26: Yes
A27: Anaïs Bodere | B27: =IF(COUNTIF(HCPs!M:M,HCP_evidence!A26)>0,"Yes","No") -> No | H27: Adjuvant Tumor-Stage Chemotherapy for Pancreatic Adenocarcinoma Operated After Neoadjuvant Chemotherapy with FOLFIRINOX - Phase II/III Multicenter Randomized Comparative Trial, FRENCH-PRODIGE | I27: https://www.ffcd.fr/index.php/recherche/essais-therapeutiques | K27: Yes | L27: Yes
A28: Angélique Vienot | B28: =IF(COUNTIF(HCPs!M:M,HCP_evidence!A27)>0,"Yes","No") -> Yes | H28: A Phase II, Multicenter, Open-Label, Three-Arm Randomized Study to Evaluate the Efficacy and Safety of TTX-030 in Combination with Chemotherapy, With or Without Budigalimab, Compared to Chemotherapy Alone, in the Treatment of Treatment-Naïve Patients for Metastatic Pancreatic Adenocarcinoma | I28: https://www.sante.fr/essais-cliniques/2023-508356-19-00/etude-de-phase-ii-multicentrique-ouverte-randomisee-a-trois-bras-visant-a-evaluer-l-efficacite-et-la-securite-d-emploi-du-ttx-030-associe-a-une-chimiotherapie-avec-ou-sans-budigalimab-par-rapport-a-la-chimiotherapie-seule-dans-le-traitement-de-patients-n-ayant-jamais-recu-de-traitement-contre-un-adenocarcinome-pancreatique-metastatique | K28: Yes | L28: Yes
A29: Angélique Vienot | B29: =IF(COUNTIF(HCPs!M:M,HCP_evidence!A28)>0,"Yes","No") -> Yes | H29: Adjuvant Tumor-Stage Chemotherapy for Pancreatic Adenocarcinoma Operated After Neoadjuvant Chemotherapy with FOLFIRINOX - Phase II/III Multicenter Randomized Comparative Trial, FRENCH-PRODIGE | I29: https://www.ffcd.fr/index.php/recherche/essais-therapeutiques | K29: Yes | L29: Yes
A30: Angélique Vienot | B30: =IF(COUNTIF(HCPs!M:M,HCP_evidence!A29)>0,"Yes","No") -> Yes | H30: CANOPE: Pancreatic Adenocarcinoma Cohort - Prognostic and predictive markers of treatment response in patients with pancreatic adenocarcinoma | I30: https://www.gercor.com/canope-gb-121/ | K30: Yes | L30: Yes
A31: Angélique Vienot | B31: =IF(COUNTIF(HCPs!M:M,HCP_evidence!A30)>0,"Yes","No") -> Yes | J31: Yes | K31: Yes | L31: Yes | O31: Dostarlimab for Locally Advanced or Metastatic Cancer (Non-colorectal/Non-endometrial) With Tumor dMMR/MSI | P31: https://clinicaltrials.gov/study/NCT06333314
A32: Angélique Vienot | B32: =IF(COUNTIF(HCPs!M:M,HCP_evidence!A31)>0,"Yes","No") -> Yes | H32: Personalized neoadjuvant chemotherapy with RNA signature for patients with borderline pancreatic adenocarcinoma | I32: https://www.ffcd.fr/index.php/recherche/essais-therapeutiques | L32: Yes
A33: Angélique Vienot | B33: =IF(COUNTIF(HCPs!M:M,HCP_evidence!A32)>0,"Yes","No") -> Yes | H33: Phase II trial evaluating the efficacy and safety of FOLFIRINOX3 therapy in patients with inoperable locally advanced or metastatic pancreatic cancer in first-line chemotherapy. | I33: https://www.sante.fr/essais-cliniques/2023-505889-29-01/essai-de-phase-ii-evaluant-l-efficacite-et-la-securite-du-traitement-par-folfirinox3-chez-des-patients-atteints-d-un-cancer-du-pancreas-localement-avance-ou-metastatique-inoperable-en-premiere-ligne-de-chimiotherapie | J33: Yes | K33: Yes | L33: Yes | N33: Yes
A34: Angélique Vienot | B34: =IF(COUNTIF(HCPs!M:M,HCP_evidence!A33)>0,"Yes","No") -> Yes | H34: Study of Nab-Paclitaxel and Gemcitabine With or Without SBP-101 in Pancreatic Cancer | I34: https://clinicaltrials.gov/study/NCT05254171 | K34: Yes | L34: Yes | N34: Yes
A35: Angélique Vienot | B35: =IF(COUNTIF(HCPs!M:M,HCP_evidence!A34)>0,"Yes","No") -> Yes | Z35: The role of pesticides in the epidemiology of pancreatic cancer | AA35: https://www.canceropole-est.org/journee-cancer-du-pancreas/
A36: Angélique Vienot | B36: =IF(COUNTIF(HCPs!M:M,HCP_evidence!A35)>0,"Yes","No") -> Yes | Z36: Management of pancreatic cancer – Part 2 | AA36: https://www.canceropole-est.org/journee-cancer-du-pancreas/
A37: Anna Farran | B37: =IF(COUNTIF(HCPs!M:M,HCP_evidence!A36)>0,"Yes","No") -> Yes | L37: Yes | M37: Yes | O37: KO-2806 Monotherapy and Combination Therapies in Advanced Solid Tumors | P37: https://clinicaltrials.gov/study/NCT06026410
A38: Anna Pellat | B38: =IF(COUNTIF(HCPs!M:M,HCP_evidence!A37)>0,"Yes","No") -> Yes | H38: Personalized neoadjuvant chemotherapy with RNA signature for patients with borderline pancreatic adenocarcinoma | I38: https://www.ffcd.fr/index.php/recherche/essais-therapeutiques | L38: Yes
A39: Anne Bignon | B39: =IF(COUNTIF(HCPs!M:M,HCP_evidence!A38)>0,"Yes","No") -> Yes | H39: Personalized neoadjuvant chemotherapy with RNA signature for patients with borderline pancreatic adenocarcinoma | I39: https://www.ffcd.fr/index.php/recherche/essais-therapeutiques | L39: Yes
A40: Anne Frin | B40: =IF(COUNTIF(HCPs!M:M,HCP_evidence!A39)>0,"Yes","No") -> Yes | H40: Personalized neoadjuvant chemotherapy with RNA signature for patients with borderline pancreatic adenocarcinoma | I40: https://www.ffcd.fr/index.php/recherche/essais-therapeutiques | L40: Yes
A41: Anne Laure Vedie | B41: =IF(COUNTIF(HCPs!M:M,HCP_evidence!A40)>0,"Yes","No") -> No | H41: Adjuvant Tumor-Stage Chemotherapy for Pancreatic Adenocarcinoma Operated After Neoadjuvant Chemotherapy with FOLFIRINOX - Phase II/III Multicenter Randomized Comparative Trial, FRENCH-PRODIGE | I41: https://www.ffcd.fr/index.php/recherche/essais-therapeutiques | K41: Yes | L41: Yes
A42: Anne Laure Vedie | B42: =IF(COUNTIF(HCPs!M:M,HCP_evidence!A41)>0,"Yes","No") -> Yes | H42: Sequential Treatment With GEMBRAX and Then FOLFIRINOX Followed by Stereotactic MRI-guided Radiotherapy in Patients With Locally Advanced Pancreatic Cancer | I42: https://clinicaltrials.gov/study/NCT04570943 | L42: Yes | N42: Yes
A43: Anne Laure Vedie | B43: =IF(COUNTIF(HCPs!M:M,HCP_evidence!A42)>0,"Yes","No") -> Yes | H43: Sequential Treatment With GEMBRAX and Then FOLFIRINOX Followed by Stereotactic MRI-guided Radiotherapy in Patients With Locally Advanced Pancreatic Cancer | I43: https://clinicaltrials.gov/study/NCT04570943 | L43: Yes | N43: Yes
A44: Anne Mourregot | B44: =IF(COUNTIF(HCPs!M:M,HCP_evidence!A43)>0,"Yes","No") -> Yes | L44: Yes | N44: Yes | O44: Prospective Monocentric Clinical-biological Database | P44: https://clinicaltrials.gov/study/NCT04136132
A45: Anne-Claire Frin | B45: =IF(COUNTIF(HCPs!M:M,HCP_evidence!A44)>0,"Yes","No") -> Yes | L45: Yes | AE45: https://www.bacap-pancreas.fr/fr/partenaires/
A46: Anne-Isabelle Lemaistre | B46: =IF(COUNTIF(HCPs!M:M,HCP_evidence!A45)>0,"Yes","No") -> Yes | L46: Yes | AE46: https://www.bacap-pancreas.fr/fr/partenaires/
A47: Anthony Gonçalves | B47: =IF(COUNTIF(HCPs!M:M,HCP_evidence!A46)>0,"Yes","No") -> Yes | K47: Yes | L47: Yes | N47: Yes | O47: A Phase 1 First-In-Human Study of the Anti-CD73 IPH5301 Alone or in Combination With Chemotherapy and Trastuzumab in Patients With Advanced Solid Tumors | P47: https://clinicaltrials.gov/study/NCT05143970
A48: Anthony Lopez | B48: =IF(COUNTIF(HCPs!M:M,HCP_evidence!A47)>0,"Yes","No") -> Yes | H48: Randomized Phase II Study for Metastatic Pancreatic Cancers Comparing 5-FU/LV+Nal-IRI, versus gemcitabine+Nab-paclitaxel versus a sequential regimen alternating 5-FU/LV+Nal-IRI and gemcitabine+Nab-paclitaxel every 2 months | I48: https://www.ffcd.fr/index.php/recherche/essais-therapeutiques | K48: Yes | L48: Yes
A49: Anthony Turpin | B49: =IF(COUNTIF(HCPs!M:M,HCP_evidence!A48)>0,"Yes","No") -> Yes | H49: CANOPE: Pancreatic Adenocarcinoma Cohort - Prognostic and predictive markers of treatment response in patients with pancreatic adenocarcinoma | I49: https://www.gercor.com/canope-gb-121/ | K49: Yes | L49: Yes
A50: Anthony Turpin | B50: =IF(COUNTIF(HCPs!M:M,HCP_evidence!A49)>0,"Yes","No") -> Yes | H50: PANORAMIX : Optimizing 1st-line NALIRIFOX and Exploring Microbiota's Role in 2nd Line Pancreatic Cancer Treatment | I50: https://clinicaltrials.gov/study/NCT07028424 | L50: Yes | N50: Yes
A51: Anthony Turpin | B51: =IF(COUNTIF(HCPs!M:M,HCP_evidence!A50)>0,"Yes","No") -> Yes | H51: Personalized First-line Chemotherapy Choice in Advanced Pancreatic Adenocarcinoma Using Transcriptomic Signatures | I51: https://clinicaltrials.gov/study/NCT05475366 | L51: Yes
A52: Anthony Turpin | B52: =IF(COUNTIF(HCPs!M:M,HCP_evidence!A51)>0,"Yes","No") -> Yes | H52: Personalized neoadjuvant chemotherapy with RNA signature for patients with borderline pancreatic adenocarcinoma | I52: https://www.ffcd.fr/index.php/recherche/essais-therapeutiques | L52: Yes
A53: Anthony Turpin | B53: =IF(COUNTIF(HCPs!M:M,HCP_evidence!A52)>0,"Yes","No") -> Yes | L53: Yes | AF53: https://www.societefrancaisepancreas.fr/commission-recherche/
A54: Antoine Adenis | B54: =IF(COUNTIF(HCPs!M:M,HCP_evidence!A53)>0,"Yes","No") -> Yes | L54: Yes | N54: Yes | O54: Prospective Monocentric Clinical-biological Database | P54: https://clinicaltrials.gov/study/NCT04136132
A55: Antoine De Pauw | B55: =IF(COUNTIF(HCPs!M:M,HCP_evidence!A54)>0,"Yes","No") -> Yes | L55: Yes | AH55: https://www.unicancer.fr/fr/les-groupes-d-experts/groupe-genetique-et-cancer/
A56: Antoine Drouillard | B56: =IF(COUNTIF(HCPs!M:M,HCP_evidence!A55)>0,"Yes","No") -> Yes | H56: Randomized Phase II Study for Metastatic Pancreatic Cancers Comparing 5-FU/LV+Nal-IRI, versus gemcitabine+Nab-paclitaxel versus a sequential regimen alternating 5-FU/LV+Nal-IRI and gemcitabine+Nab-paclitaxel every 2 months | I56: https://www.ffcd.fr/index.php/recherche/essais-therapeutiques | K56: Yes | L56: Yes
A57: Antoine Hollebecque | B57: =IF(COUNTIF(HCPs!M:M,HCP_evidence!A56)>0,"Yes","No") -> Yes | H57: A Phase 1b Study to Evaluate the Safety, Tolerability and Preliminary Efficacy of a Heterologous Prime Boost Vaccination (ATP150/ATP152/ATP162, VSV-GP154 and Ezabenlimab (BI 754091) in Patients with Pancreatic Ductal Adenocarcinoma | I57: https://www.sante.fr/essais-cliniques/2022-501854-12-01/a-phase-1b-study-to-evaluate-the-safety-tolerability-and-preliminary-efficacy-of-a-heterologous-prime-boost-vaccination-atp150-atp152-atp162-vsv-gp154-and-ezabenlimab-bi-754091-in-patients-with-pancreatic-ductal-adenocarcinoma | J57: Yes | K57: Yes | L57: Yes | M57: Yes
A58: Antoine Italiano | B58: =IF(COUNTIF(HCPs!M:M,HCP_evidence!A57)>0,"Yes","No") -> Yes | O58: Atezolizumab Combined With BDB001 AnD Immunogenic Radiotherapy in Patients With Advanced Solid Tumors | P58: https://clinicaltrials.gov/study/NCT03915678 | S58: Yes | U58: Yes
A59: Antoine Italiano | B59: =IF(COUNTIF(HCPs!M:M,HCP_evidence!A58)>0,"Yes","No") -> Yes | K59: Yes | L59: Yes | O59: tislelizUMaB in canceR Patients With molEcuLar residuaL Disease | P59: https://clinicaltrials.gov/study/NCT06332274
A60: Antonio Sa Cunha | B60: =IF(COUNTIF(HCPs!M:M,HCP_evidence!A59)>0,"Yes","No") -> Yes | H60: Adjuvant Tumor-Stage Chemotherapy for Pancreatic Adenocarcinoma Operated After Neoadjuvant Chemotherapy with FOLFIRINOX - Phase II/III Multicenter Randomized Comparative Trial, FRENCH-PRODIGE | I60: https://www.ffcd.fr/index.php/recherche/essais-therapeutiques | K60: Yes | L60: Yes
A61: Antonio Sa Cunha | B61: =IF(COUNTIF(HCPs!M:M,HCP_evidence!A60)>0,"Yes","No") -> Yes | D61: Cancer du pancréas – Chapitre 9, Thésaurus National de Cancérologie Digestive | E61: https://www.snfge.org/tncd/cancer-du-pancreas
A62: Antonio Sa Cunha | B62: =IF(COUNTIF(HCPs!M:M,HCP_evidence!A61)>0,"Yes","No") -> Yes | D62: Pancreatic cancer: French clinical practice guidelines for diagnosis, treatment and follow-up (SNFGE, FFCD, GERCOR, UNICANCER, SFCD, SFED, SFRO, ACHBT, AFC) | E62: https://pubmed.ncbi.nlm.nih.gov/30219670/
A63: Arnaud Jeanson | B63: =IF(COUNTIF(HCPs!M:M,HCP_evidence!A62)>0,"Yes","No") -> Yes | O63: Atezolizumab Combined With BDB001 AnD Immunogenic Radiotherapy in Patients With Advanced Solid Tumors | P63: https://clinicaltrials.gov/study/NCT03915678 | S63: Yes | U63: Yes
A64: Arthur Belle | B64: =IF(COUNTIF(HCPs!M:M,HCP_evidence!A63)>0,"Yes","No") -> Yes | D64: CONDUITES À TENIR DEVANT DES PATIENTS ATTEINTS D’ADÉNOCARCINOME DU PANCRÉAS | E64: https://ressources-aura.fr/wp-content/uploads/2020/01/Thesaurus_CAT_patients_atteints_adenocarcinomes_pancreas_mel_20191118.pdf
A65: Arthur Laquiere | B65: =IF(COUNTIF(HCPs!M:M,HCP_evidence!A64)>0,"Yes","No") -> Yes | AB65: https://www.hopital-saint-joseph.fr/espace-medias/les-actualites/les-dernieres-actualites/fondation--soutenez-letude-clinique-sur-le-diagnostic-du-cancer-du-pancreas-
A66: Asmahane Benmaziane-Teillet | B66: =IF(COUNTIF(HCPs!M:M,HCP_evidence!A65)>0,"Yes","No") -> Yes | H66: DOVIPA, a Study Evaluating Efficacy and Safety of DOstarlimab and VItamin D3 With mFOLFIRINOX in PAncreatic Cancer | I66: https://clinicaltrials.gov/study/NCT06757244 | K66: Yes | L66: Yes | N66: Yes
A67: Astrid Lièvre | B67: =IF(COUNTIF(HCPs!M:M,HCP_evidence!A66)>0,"Yes","No") -> Yes | Z67: Reste-t-il une place pour la radiothérapie avant la chirurgie du pancréas ? | AA67: https://www.oncobretagne.fr/wp-content/uploads/2026/02/pre-programme-hepato2026.pdf
A68: Aude Guillemin-Jobard | B68: =IF(COUNTIF(HCPs!M:M,HCP_evidence!A67)>0,"Yes","No") -> Yes | H68: Personalized First-line Chemotherapy Choice in Advanced Pancreatic Adenocarcinoma Using Transcriptomic Signatures | I68: https://clinicaltrials.gov/study/NCT05475366 | L68: Yes
A69: Aude Guillemin-Jobard | B69: =IF(COUNTIF(HCPs!M:M,HCP_evidence!A68)>0,"Yes","No") -> Yes | AB69: https://curie.fr/actualite/nominations-hopital-semestre-1-2026
A70: Aude-Marie Savoye | B70: =IF(COUNTIF(HCPs!M:M,HCP_evidence!A69)>0,"Yes","No") -> Yes | K70: Yes | L70: Yes | N70: Yes | O70: OncoSNIPE - Study of Molecular Profiles Associated With the Development of Resistance in Solid Cancer Patients | P70: https://clinicaltrials.gov/study/NCT04548960
A71: Aude-Marie Savoye | B71: =IF(COUNTIF(HCPs!M:M,HCP_evidence!A70)>0,"Yes","No") -> Yes | K71: Yes | L71: Yes | N71: Yes | O71: OncoSNIPE - Study of Molecular Profiles Associated With the Development of Resistance in Solid Cancer Patients | P71: https://clinicaltrials.gov/study/NCT04548960
A72: Audrey Remenieras | B72: =IF(COUNTIF(HCPs!M:M,HCP_evidence!A71)>0,"Yes","No") -> Yes | L72: Yes | AH72: https://www.unicancer.fr/fr/les-groupes-d-experts/groupe-genetique-et-cancer/
A73: Aurélie Parzy | B73: =IF(COUNTIF(HCPs!M:M,HCP_evidence!A72)>0,"Yes","No") -> Yes | AB73: https://www.baclesse.fr/specialite/endoscopies/
A74: Aurélien Carnot | B74: =IF(COUNTIF(HCPs!M:M,HCP_evidence!A73)>0,"Yes","No") -> Yes | H74: GABRINOX ART | I74: https://www.centreoscarlambret.fr/recherche-cancerologique/essais-cliniques/gabrinox-art
A75: Aurélien Dupre | B75: =IF(COUNTIF(HCPs!M:M,HCP_evidence!A74)>0,"Yes","No") -> Yes | H75: Adjuvant Tumor-Stage Chemotherapy for Pancreatic Adenocarcinoma Operated After Neoadjuvant Chemotherapy with FOLFIRINOX - Phase II/III Multicenter Randomized Comparative Trial, FRENCH-PRODIGE | I75: https://www.ffcd.fr/index.php/recherche/essais-therapeutiques | K75: Yes | L75: Yes
A76: Aurélien Dupre | B76: =IF(COUNTIF(HCPs!M:M,HCP_evidence!A75)>0,"Yes","No") -> Yes | H76: Immunoparalysis After Pancreaticoduodenectomy | I76: https://clinicaltrials.gov/study/NCT07144917 | L76: Yes
A77: Aurélien Dupre | B77: =IF(COUNTIF(HCPs!M:M,HCP_evidence!A76)>0,"Yes","No") -> Yes | H77: Superior Mesenteric Artery First Versus Standard Approach in Pancreaticoduodenectomy | I77: https://clinicaltrials.gov/study/NCT07547033 | L77: Yes | N77: Yes
A78: Aurélien Dupre | B78: =IF(COUNTIF(HCPs!M:M,HCP_evidence!A77)>0,"Yes","No") -> Yes | Z78: Introduction et présentation SOS Pancréas | AA78: https://onco-aura.fr/wp-content/uploads/2026/06/soiree-formation-sos-Pancreas_Haute-Savoie.pdf
A79: Aurélien Dupre | B79: =IF(COUNTIF(HCPs!M:M,HCP_evidence!A78)>0,"Yes","No") -> Yes | Z79: Epidémiologie, positionnement du problème | AA79: https://onco-aura.fr/wp-content/uploads/2026/06/soiree-formation-sos-Pancreas_Haute-Savoie.pdf
A80: Aurélien Dupre | B80: =IF(COUNTIF(HCPs!M:M,HCP_evidence!A79)>0,"Yes","No") -> Yes | Z80: Prise en charge clinique et thérapeutique | AA80: https://onco-aura.fr/wp-content/uploads/2026/06/soiree-formation-sos-Pancreas_Haute-Savoie.pdf
A81: Aurélien Dupre | B81: =IF(COUNTIF(HCPs!M:M,HCP_evidence!A80)>0,"Yes","No") -> Yes | F81: Cancer du pancréas – Chapitre 9, Thésaurus National de Cancérologie Digestive | G81: https://www.snfge.org/tncd/cancer-du-pancreas
A82: Aurélien Lambert | B82: =IF(COUNTIF(HCPs!M:M,HCP_evidence!A81)>0,"Yes","No") -> Yes | J82: Yes | K82: Yes | L82: Yes | O82: Dostarlimab for Locally Advanced or Metastatic Cancer (Non-colorectal/Non-endometrial) With Tumor dMMR/MSI | P82: https://clinicaltrials.gov/study/NCT06333314
A83: Aurélien Lambert | B83: =IF(COUNTIF(HCPs!M:M,HCP_evidence!A82)>0,"Yes","No") -> Yes | K83: Yes | L83: Yes | M83: Yes | O83: Study Investigating ASP3082 in Patients With Metastatic/Locally Advanced Non-small-cell Lung Cancer (NSCLC) and Pancreatic Ductal Adenocarcinoma (PDAC), With Biomarker Analysis to Characterize Response/Resistance | P83: https://clinicaltrials.gov/study/NCT07483983
A84: Aurélien Lambert | B84: =IF(COUNTIF(HCPs!M:M,HCP_evidence!A83)>0,"Yes","No") -> Yes | L84: Yes | AD84: https://www.espoir-pancreas.fr/nos-conferences/
A85: Aurélien Lambert | B85: =IF(COUNTIF(HCPs!M:M,HCP_evidence!A84)>0,"Yes","No") -> Yes | L85: Yes | AC85: https://www.espoir-pancreas.fr/association-familles-entraide/
A86: Barbara Alkofer | B86: =IF(COUNTIF(HCPs!M:M,HCP_evidence!A85)>0,"Yes","No") -> Yes | F86: CONDUITES À TENIR DEVANT DES PATIENTS ATTEINTS D’ADÉNOCARCINOME DU PANCRÉAS | G86: https://ressources-aura.fr/wp-content/uploads/2020/01/Thesaurus_CAT_patients_atteints_adenocarcinomes_pancreas_mel_20191118.pdf
A87: Barbara Bournet | B87: =IF(COUNTIF(HCPs!M:M,HCP_evidence!A86)>0,"Yes","No") -> Yes | H87: Anatomical-Clinical Base of Adenocarcinoma Pancreatic | I87: https://clinicaltrials.gov/study/NCT06128343 | L87: Yes
A88: Barbara Bournet | B88: =IF(COUNTIF(HCPs!M:M,HCP_evidence!A87)>0,"Yes","No") -> Yes | H88: PAncreatic Disease Cohort of TOuLouse | I88: https://clinicaltrials.gov/study/NCT05824403 | L88: Yes
A89: Barbara Bournet | B89: =IF(COUNTIF(HCPs!M:M,HCP_evidence!A88)>0,"Yes","No") -> Yes | L89: Yes | AE89: https://www.bacap-pancreas.fr/fr/partenaires/
A90: Barbara Bournet | B90: =IF(COUNTIF(HCPs!M:M,HCP_evidence!A89)>0,"Yes","No") -> Yes | F90: CONDUITES À TENIR DEVANT DES PATIENTS ATTEINTS D’ADÉNOCARCINOME DU PANCRÉAS | G90: https://ressources-aura.fr/wp-content/uploads/2020/01/Thesaurus_CAT_patients_atteints_adenocarcinomes_pancreas_mel_20191118.pdf
A91: Barbara Bournet | B91: =IF(COUNTIF(HCPs!M:M,HCP_evidence!A90)>0,"Yes","No") -> Yes | AB91: https://www.chu-toulouse.fr/pr-bournet-barbara
A92: Benjamin Angliviel | B92: =IF(COUNTIF(HCPs!M:M,HCP_evidence!A91)>0,"Yes","No") -> Yes | F92: CONDUITES À TENIR DEVANT DES PATIENTS ATTEINTS D’ADÉNOCARCINOME DU PANCRÉAS | G92: https://ressources-aura.fr/wp-content/uploads/2020/01/Thesaurus_CAT_patients_atteints_adenocarcinomes_pancreas_mel_20191118.pdf
A93: Benjamin Menahem | B93: =IF(COUNTIF(HCPs!M:M,HCP_evidence!A92)>0,"Yes","No") -> Yes | F93: Cancer du pancréas – Chapitre 9, Thésaurus National de Cancérologie Digestive | G93: https://www.snfge.org/tncd/cancer-du-pancreas
A94: Benoist Chibaudel | B94: =IF(COUNTIF(HCPs!M:M,HCP_evidence!A93)>0,"Yes","No") -> Yes | H94: Adjuvant Tumor-Stage Chemotherapy for Pancreatic Adenocarcinoma Operated After Neoadjuvant Chemotherapy with FOLFIRINOX - Phase II/III Multicenter Randomized Comparative Trial, FRENCH-PRODIGE | I94: https://www.ffcd.fr/index.php/recherche/essais-therapeutiques | K94: Yes | L94: Yes
A95: Benoist Chibaudel | B95: =IF(COUNTIF(HCPs!M:M,HCP_evidence!A94)>0,"Yes","No") -> Yes | D95: Pancreatic cancer: French clinical practice guidelines for diagnosis, treatment and follow-up (SNFGE, FFCD, GERCOR, UNICANCER, SFCD, SFED, SFRO, ACHBT, AFC) | E95: https://pubmed.ncbi.nlm.nih.gov/30219670/
A96: Benoît Terris | B96: =IF(COUNTIF(HCPs!M:M,HCP_evidence!A95)>0,"Yes","No") -> Yes | F96: CONDUITES À TENIR DEVANT DES PATIENTS ATTEINTS D’ADÉNOCARCINOME DU PANCRÉAS | G96: https://ressources-aura.fr/wp-content/uploads/2020/01/Thesaurus_CAT_patients_atteints_adenocarcinomes_pancreas_mel_20191118.pdf
A97: Benoit You | B97: =IF(COUNTIF(HCPs!M:M,HCP_evidence!A96)>0,"Yes","No") -> Yes | L97: Yes | N97: Yes | O97: Predictive Value of Progastrin Titer at Diagnosis and of Progastrin Kinetics During Treatment in Cancer Patients | P97: https://clinicaltrials.gov/study/NCT03787056
A98: Benoit You | B98: =IF(COUNTIF(HCPs!M:M,HCP_evidence!A97)>0,"Yes","No") -> Yes | L98: Yes | N98: Yes | O98: Predictive Value of Progastrin Titer at Diagnosis and of Progastrin Kinetics During Treatment in Cancer Patients | P98: https://clinicaltrials.gov/study/NCT03787056
A99: Bertrand Le Roy | B99: =IF(COUNTIF(HCPs!M:M,HCP_evidence!A98)>0,"Yes","No") -> Yes | Z99: Prise en charge chirurgicale et grands principes thérapeutiques | AA99: https://onco-aura.fr/wp-content/uploads/2026/06/soiree-formation-sos-Pancreas_Loire.pdf
A100: Bertrand Napoléon | B100: =IF(COUNTIF(HCPs!M:M,HCP_evidence!A99)>0,"Yes","No") -> Yes | H100: Anatomical-Clinical Base of Adenocarcinoma Pancreatic | I100: https://clinicaltrials.gov/study/NCT06128343 | L100: Yes
...

Sheet Testing Centres
A1: Testing Centre Information | G1: Testing Centre Details
A2: Comments | B2: Next Generation Sequencing | C2: Pancreatic cancer | D2: Liquid Biopsy | E2: KRAS (cancer in general) | F2: KRAS (pancreatic cancer) | G2: GDS_Testing_ID | H2: Testing Centre name | I2: Address | J2: Zipcode | K2: City | L2: Region | M2: Country | N2: Type (internal/external) | O2: Source
A3: filter | B3: filter | C3: filter | D3: filter | E3: filter | F3: filter | G3: filter | H3: filter | I3: filter | J3: filter | K3: filter | L3: filter | M3: filter | N3: filter | O3: filter
E4: Yes | G4: TEST_00001 | H4: CHU Estaing | I4: 1 PLACE LUCIE AUBRAC | J4: 63003 | K4: CLERMONT FERRAND | N4: Internal | O4: https://www.cancer.fr/Media/files/annuaire-des-correspondants_plateformes-de-genetique-moleculaire-des-cancers-2020
E5: Yes | G5: TEST_00002 | H5: Centre Jean Perrin | I5: 58 Rue Montalembert | J5: 63011 | K5: Clermont-Ferrand | L5: Auvergne-Rhône-Alpes | N5: Internal | O5: https://www.cancer.fr/Media/files/annuaire-des-correspondants_plateformes-de-genetique-moleculaire-des-cancers-2020
A6: Main site for KRAS testing within CHU de Grenoble | E6: Yes | G6: TEST_00003 | H6: Hôpital Albert Michallon | I6: BOULEVARD DE LA CHANTOURNE | J6: 38700 | K6: LA TRONCHE | N6: Internal | O6: https://www.cancer.fr/Media/files/annuaire-des-correspondants_plateformes-de-genetique-moleculaire-des-cancers-2020
A7: Main site for KRAS testing within Hospices Civils de Lyon | E7: Yes | G7: TEST_00004 | H7: Hôpital Édouard Herriot | N7: Internal | O7: https://www.cancer.fr/Media/files/annuaire-des-correspondants_plateformes-de-genetique-moleculaire-des-cancers-2020
E8: Yes | G8: TEST_00005 | H8: Centre Léon Bérard | I8: 28 Prom. Léa et Napoléon Bullukian | J8: 69008 | K8: Lyon | L8: Auvergne-Rhône-Alpes | N8: Internal | O8: https://www.cancer.fr/Media/files/annuaire-des-correspondants_plateformes-de-genetique-moleculaire-des-cancers-2020
E9: Yes | G9: TEST_00006 | H9: Hôpital Nord | I9: AVENUE ALBERT RAIMOND | J9: 42277 | K9: SAINT PRIEST EN JAREZ | N9: Internal | O9: https://www.cancer.fr/Media/files/annuaire-des-correspondants_plateformes-de-genetique-moleculaire-des-cancers-2020
E10: Yes | G10: TEST_00007 | H10: CHRU Jean Minjoz | I10: 3 BOULEVARD FLEMING | J10: 25030 | K10: BESANCON | N10: Internal | O10: https://www.cancer.fr/Media/files/annuaire-des-correspondants_plateformes-de-genetique-moleculaire-des-cancers-2020
E11: Yes | G11: TEST_00008 | H11: CHRU le Bocage | I11: 1 BOULEVARD JEANNE D ARC | J11: 21079 | K11: DIJON | N11: Internal | O11: https://www.cancer.fr/Media/files/annuaire-des-correspondants_plateformes-de-genetique-moleculaire-des-cancers-2020
E12: Yes | G12: TEST_00009 | H12: Centre Georges-François Leclerc | N12: Internal | O12: https://www.cancer.fr/Media/files/annuaire-des-correspondants_plateformes-de-genetique-moleculaire-des-cancers-2020
A13: Main site for KRAS testing within CHU de Brest | E13: Yes | G13: TEST_00010 | H13: Hôpital Morvan | N13: Internal | O13: https://www.cancer.fr/Media/files/annuaire-des-correspondants_plateformes-de-genetique-moleculaire-des-cancers-2020
A14: Main site for KRAS testing within CHU de Rennes | E14: Yes | G14: TEST_00011 | H14: Hôpital Pontchaillou | I14: 2 RUE HENRI LE GUILLOUX | J14: 35000 | K14: RENNES | N14: Internal | O14: https://www.cancer.fr/Media/files/annuaire-des-correspondants_plateformes-de-genetique-moleculaire-des-cancers-2020
A15: Main site for KRAS testing within CHU de Tours | E15: Yes | G15: TEST_00012 | H15: Hôpital Trousseau | I15: AVENUE DE LA REPUBLIQUE | J15: 37170 | K15: CHAMBRAY LES TOURS | N15: Internal | O15: https://www.cancer.fr/Media/files/annuaire-des-correspondants_plateformes-de-genetique-moleculaire-des-cancers-2020
A16: Main site for KRAS testing within CHR d'Orléans | E16: Yes | G16: TEST_00013 | H16: Hôpital de la Source | I16: 14 AVENUE DE L'HOPITAL | J16: 45067 | K16: ORLEANS | N16: Internal | O16: https://www.cancer.fr/Media/files/annuaire-des-correspondants_plateformes-de-genetique-moleculaire-des-cancers-2020
E17: Yes | G17: TEST_00014 | H17: ICL de Lorraine | I17: 6 AVENUE DE BOURGOGNE | J17: 54519 | K17: VANDOEUVRE LES NANCY | N17: Internal | O17: https://www.cancer.fr/Media/files/annuaire-des-correspondants_plateformes-de-genetique-moleculaire-des-cancers-2020
A18: Main site for KRAS testing within CHU de Reims | B18: Yes | E18: Yes | G18: TEST_00015 | H18: Hôpital Maison Blanche | I18: 45 RUE COGNACQ JAY | J18: 51092 | K18: REIMS | N18: Internal | O18: https://www.cancer.fr/Media/files/annuaire-des-correspondants_plateformes-de-genetique-moleculaire-des-cancers-2020
E19: Yes | G19: TEST_00016 | H19: Institut Jean Godinot | I19: 1 Rue du Général Koenig | J19: 51726 | K19: Reims | L19: Grand Est | N19: Internal | O19: https://www.cancer.fr/Media/files/annuaire-des-correspondants_plateformes-de-genetique-moleculaire-des-cancers-2020
E20: Yes | G20: TEST_00017 | H20: CH de Colmar | N20: Internal | O20: https://www.cancer.fr/Media/files/annuaire-des-correspondants_plateformes-de-genetique-moleculaire-des-cancers-2020
A21: Main site for KRAS testing within CHU d'Amiens -Picardie | E21: Yes | G21: TEST_00018 | H21: Hôpital Sud | I21: 1 Rue du Professeur Christian Cabrol | K21: Amiens | N21: Internal | O21: https://www.cancer.fr/Media/files/annuaire-des-correspondants_plateformes-de-genetique-moleculaire-des-cancers-2020
E22: Yes | G22: TEST_00019 | H22: CHRU de Lille (Siège) | I22: 2 AVENUE OSCAR LAMBRET | J22: 59037 | K22: LILLE | N22: Internal | O22: https://www.cancer.fr/Media/files/annuaire-des-correspondants_plateformes-de-genetique-moleculaire-des-cancers-2020
E23: Yes | G23: TEST_00020 | H23: Hôpital Avicenne | I23: 125 RUE DE STALINGRAD | J23: 93009 | K23: BOBIGNY | N23: Internal | O23: https://www.cancer.fr/Media/files/annuaire-des-correspondants_plateformes-de-genetique-moleculaire-des-cancers-2020
A24: Main site for KRAS testing within APHP Nord Université de Paris HUPNVS (BichatBeaujonLouisMourier) | E24: Yes | G24: TEST_00021 | H24: Hôpital Bichat | I24: 46 RUE HENRI HUCHARD | J24: 75877 | K24: PARIS | N24: Internal | O24: https://www.cancer.fr/Media/files/annuaire-des-correspondants_plateformes-de-genetique-moleculaire-des-cancers-2020
A25: Main site for KRAS testing within APHP Nord Université de Paris HUSLSLRB SaintLouis | E25: Yes | G25: TEST_00022 | H25: Hôpital Saint-Louis | I25: 1 AVENUE CLAUDE VELLEFAUX | J25: 75475 | K25: PARIS | N25: Internal | O25: https://www.cancer.fr/Media/files/annuaire-des-correspondants_plateformes-de-genetique-moleculaire-des-cancers-2020
E26: Yes | G26: TEST_00023 | H26: Hôpital Ambroise Paré | I26: 9 AVENUE CHARLES DE GAULLE | J26: 92104 | K26: BOULOGNE BILLANCOURT | N26: Internal | O26: https://www.cancer.fr/Media/files/annuaire-des-correspondants_plateformes-de-genetique-moleculaire-des-cancers-2020
E27: Yes | G27: TEST_00024 | H27: Hôpital Henri Mondor | I27: 51 AVENUE MAL DE LATTRE DE TASSIGNY | J27: 94010 | K27: CRETEIL | N27: Internal | O27: https://www.cancer.fr/Media/files/annuaire-des-correspondants_plateformes-de-genetique-moleculaire-des-cancers-2020
E28: Yes | G28: TEST_00025 | H28: HU Pitié-Salpêtrière | I28: 47 BOULEVARD DE L HOPITAL | J28: 75651 | K28: PARIS | N28: Internal | O28: https://www.cancer.fr/Media/files/annuaire-des-correspondants_plateformes-de-genetique-moleculaire-des-cancers-2020
E29: Yes | G29: TEST_00026 | H29: Hôpital Saint-Antoine | I29: 184 RUE DU FAUBOURG SAINT ANTOINE | J29: 75571 | K29: PARIS | N29: Internal | O29: https://www.cancer.fr/Media/files/annuaire-des-correspondants_plateformes-de-genetique-moleculaire-des-cancers-2020
E30: Yes | G30: TEST_00027 | H30: Hôpital Tenon | I30: 4 RUE DE LA CHINE | J30: 75970 | K30: PARIS | N30: Internal | O30: https://www.cancer.fr/Media/files/annuaire-des-correspondants_plateformes-de-genetique-moleculaire-des-cancers-2020
E31: Yes | G31: TEST_00028 | H31: Hôpital Européen Georges-Pompidou | N31: Internal | O31: https://www.cancer.fr/Media/files/annuaire-des-correspondants_plateformes-de-genetique-moleculaire-des-cancers-2020
E32: Yes | G32: TEST_00029 | H32: Hôpital Cochin | I32: 27 RUE DU FAUBOURG SAINT JACQUES | J32: 75679 | K32: PARIS | N32: Internal | O32: https://www.cancer.fr/Media/files/annuaire-des-correspondants_plateformes-de-genetique-moleculaire-des-cancers-2020
A33: Main site for KRAS testing within Institut Curie | E33: Yes | G33: TEST_00030 | H33: Institut Curie | I33: 26 Rue d'Ulm | J33: 75005 | K33: Paris | L33: Ile-de-France | N33: Internal | O33: https://www.cancer.fr/Media/files/annuaire-des-correspondants_plateformes-de-genetique-moleculaire-des-cancers-2020
E34: Yes | G34: TEST_00031 | H34: Institut Gustave Roussy | I34: 114 Rue Edouard Vaillant | J34: 94805 | K34: Villejuif | L34: Ile-de-France | N34: Internal | O34: https://www.cancer.fr/Media/files/annuaire-des-correspondants_plateformes-de-genetique-moleculaire-des-cancers-2020
E35: Yes | G35: TEST_00032 | H35: Hôpital Georges-Clémenceau | N35: Internal | O35: https://www.cancer.fr/Media/files/annuaire-des-correspondants_plateformes-de-genetique-moleculaire-des-cancers-2020
E36: Yes | G36: TEST_00033 | H36: Centre François Baclesse | I36: 3 Avenue du Général Harris | J36: 14000 | K36: Caen | L36: Normandie | N36: Internal | O36: https://www.cancer.fr/Media/files/annuaire-des-correspondants_plateformes-de-genetique-moleculaire-des-cancers-2020
E37: Yes | G37: TEST_00034 | H37: Hôpital Charles Nicolle | I37: 1 RUE DE GERMONT | J37: 76031 | K37: ROUEN | N37: Internal | O37: https://www.cancer.fr/Media/files/annuaire-des-correspondants_plateformes-de-genetique-moleculaire-des-cancers-2020
A38: Main site for KRAS testing within CHU de Bordeaux | E38: Yes | G38: TEST_00035 | H38: Hôpital Haut-Lévêque | I38: AVENUE DE MAGELLAN | J38: 33604 | K38: PESSAC | N38: Internal | O38: https://www.cancer.fr/Media/files/annuaire-des-correspondants_plateformes-de-genetique-moleculaire-des-cancers-2020
E39: Yes | G39: TEST_00036 | H39: Institut Bergonié | I39: 229 COURS DE L'ARGONNE | J39: 33076 | K39: BORDEAUX | N39: Internal | O39: https://www.cancer.fr/Media/files/annuaire-des-correspondants_plateformes-de-genetique-moleculaire-des-cancers-2020
E40: Yes | G40: TEST_00037 | H40: Hôpital Dupuytren | I40: 2 AVENUE MARTIN LUTHER KING | J40: 87042 | K40: LIMOGES | N40: Internal | O40: https://www.cancer.fr/Media/files/annuaire-des-correspondants_plateformes-de-genetique-moleculaire-des-cancers-2020
E41: Yes | G41: TEST_00038 | H41: Hôpital de la Milétrie | I41: 2 RUE DE LA MILETRIE | J41: 86021 | K41: POITIERS | N41: Internal | O41: https://www.cancer.fr/Media/files/annuaire-des-correspondants_plateformes-de-genetique-moleculaire-des-cancers-2020
